Workbook

Sheet Sheet1
A2: Estado de resultado integral por naturaleza de gasto
A3: PANGEA NATURAL PRODUCTS S.A.S.
A4: 901196219
A5: Septiembre 2018
A6: Valor expresado en Peso colombiano
A7: Comparativo
A10: Nombre | B10: 2018 | C10: 2017
A11: Ingresos de actividades ordinarias | B11: 91428 | C11: 0
A12: 41350101 - Comercio al por mayor y al detal | B12: 91428 | C12: 0
A13: Gastos por beneficios a los empleados | B13: -2952711 | C13: 0
A14: 51050601 - Sueldos | B14: -1400000 | C14: 0
A15: 51052701 - Auxilio de transporte | B15: -88211 | C15: 0
A16: 51053001 - Cesantías | B16: -123968 | C16: 0
A17: 51053301 - Intereses sobre cesantías | B17: -14876 | C17: 0
A18: 51053601 - Prima de servicios | B18: -123968 | C18: 0
A19: 51053901 - Vacaciones | B19: -58380 | C19: 0
A20: 51054502 - Auxilio transporte | B20: -912000 | C20: 0
A21: 51056801 - Aportes a administradora de riesgos laborales | B21: -7308 | C21: 0
A22: 51057001 - Aporte a fondos de pensión y/o cesantías | B22: -168000 | C22: 0
... A38: Ganancia (pérdida) | B38: -7576050 | C38: 0
A40: Procesado en: Octubre 07 2018 17:55

Sheet INFORME
A10: PANGEA NATURAL PRODUCTS S.A.S.
A11: NIT. 901.196.219 - 5
A12: INFORME MENSUAL AÑO 2026

Sheet PROYECCION IMP
H1: COSTO 46%
C3: =55760000+29240000 -> 85000000 | D3: UNIAGRO
C5: RENTA | F5: IVA 3 CUAT | K5: ICA
B6: INGRESOS | C6: =+GETPIVOTDATA("VALOR",'E.R. PPTO - REAL'!$S$11,"CLASE","INGRESO") -> #REF! | D6: ENE-SEPT | F6: =309756699+C8 -> 4.9702082e+08 | G6: INGRESOS | H6: 112604188 | I6: SEPTIEMBRE
C7: 197152511 | D7: OCT-NOV | F7: =+F6*19% -> 94433956 | G7: GENERADO | H7: =+C7 -> 197152511 | I7: =+D7 -> OCT-NOV
C8: =98524122.8235+(10200*8700) -> 1.8726412e+08 | D8: DICIEMBRE | F8: -18605395 | G8: DESCONTABLES | H8: =+C8 -> 1.8726412e+08 | I8: =+D8 -> DICIEMBRE
C9: =SUM(C6:C8) -> #REF! | F9: -5816000 | H9: =SUM(H6:H8) -> 4.9702082e+08 | K9: =+C9*3.3/1000 -> #REF!
C10: =(+C9*33%)+C3 -> #REF! | D10: COSTO 33% | E10: =+C10/C9 -> #REF! | F10: =SUM(F7:F9) -> 70012561 | G10: IVA A PAGAR | K10: -821000 | L10: RETEICA
C11: =+C9*42% -> #REF! | D11: GASTO 42% | K11: =SUM(K9:K10) -> #REF! | L11: A PAGAR
C12: =+C9-C10-C11 -> #REF! | D12: UTILIDAD OPER
C14: =+C12*35% -> #REF! | D14: IMPUESTO 35% | F14: ANTICIPO 1 | J14: ANTICIPO 2
C15: =-((10545000)/11)*12 -> -11503636 | D15: RETENCIONES | F15: IMPT 2022 | G15: 19327000 | J15: IMPT 2022 | K15: 19327000
C16: =-((3815000)/10)*12 -> -4578000 | D16: AUTORRENTA | F16: IMPT 2023 | G16: =+C14 -> #REF! | H16: =+G16*75% -> #REF! | J16: IMPT 2023 | K16: =+C14 -> #REF!
C17: =SUM(C14:C16) -> #REF! | D17: IMP DESP RETENC | H17: =+C15+C16 -> -16081636 | K17: =+(K15+K16)/2 -> #REF!
C18: =+H18 -> #REF! | D18: ANTICIPO | H18: =SUM(H16:H17) -> #REF! | K18: =+C15-C16 -> -6925636.4
C19: =+C17+C18 -> #REF! | D19: TOTAL A PAGAR | K19: =SUM(K17:K18) -> #REF!

Sheet E.R. PPTO - REAL
S2: PANGEA NATURAL PRODUCTS S.A.S.
S3: ESTADO DE RESULTADOS 2026
B7: AÑO | C7: 2025 | S7: AÑO | T7: 2026
B8: CENTRO DE COSTO | C8: (Varios elementos) | S8: CENTRO DE COSTO | T8: (Todas)
B9: ESTADO | C9: PRESUPUESTO | S9: ESTADO | T9: REAL
B10: UTILIDAD Y/O PÉRDIDA | C10: =+GETPIVOTDATA("VALOR",$B$11,"MES","ENERO","CLASE","INGRESO")-GETPIVOTDATA("VALOR",$B$11,"MES","ENERO","CLASE","COSTO")-GETPIVOTDATA("VALOR",$B$11,"MES","ENERO","CLASE","GASTO") -> 1.2230791e+08 | D10: =+GETPIVOTDATA("VALOR",$B$11,"MES","FEBRERO","CLASE","INGRESO")-GETPIVOTDATA("VALOR",$B$11,"MES","FEBRERO","CLASE","COSTO")-GETPIVOTDATA("VALOR",$B$11,"MES","FEBRERO","CLASE","GASTO") -> 1.2031502e+08 | E10: =+GETPIVOTDATA("VALOR",$B$11,"MES","MARZO","CLASE","INGRESO")-GETPIVOTDATA("VALOR",$B$11,"MES","MARZO","CLASE","COSTO")-GETPIVOTDATA("VALOR",$B$11,"MES","MARZO","CLASE","GASTO") -> 1.7341846e+08 | F10: =+GETPIVOTDATA("VALOR",$B$11,"MES","ABRIL","CLASE","INGRESO")-GETPIVOTDATA("VALOR",$B$11,"MES","ABRIL","CLASE","COSTO")-GETPIVOTDATA("VALOR",$B$11,"MES","ABRIL","CLASE","GASTO") -> #REF! | G10: =SUM(C10:F10) -> #REF! | H10: =+GETPIVOTDATA("VALOR",$B$11,"MES","JUNIO","CLASE","INGRESO")-GETPIVOTDATA("VALOR",$B$11,"MES","JUNIO","CLASE","COSTO")-GETPIVOTDATA("VALOR",$B$11,"MES","JUNIO","CLASE","GASTO") -> #REF! | I10: =+GETPIVOTDATA("VALOR",$B$11,"CLASE","INGRESO")-GETPIVOTDATA("VALOR",$B$11,"CLASE","COSTO")-GETPIVOTDATA("VALOR",$B$11,"CLASE","GASTO") -> 4.160414e+08 | J10: =+GETPIVOTDATA("VALOR",$B$11,"MES","AGOSTO","CLASE","INGRESO")-GETPIVOTDATA("VALOR",$B$11,"MES","AGOSTO","CLASE","COSTO")-GETPIVOTDATA("VALOR",$B$11,"MES","AGOSTO","CLASE","GASTO") -> #REF! | K10: =+K13-K15-K17 -> 0 | L10: =+L13-L15-L17 -> 0 | M10: =+GETPIVOTDATA("VALOR",$B$11,"MES","NOVIEMBRE","CLASE","INGRESO")-GETPIVOTDATA("VALOR",$B$11,"MES","NOVIEMBRE","CLASE","COSTO")-GETPIVOTDATA("VALOR",$B$11,"MES","NOVIEMBRE","CLASE","GASTO") -> #REF! | N10: =SUM(C10:M10) -> #REF! | P10: =+I10/GETPIVOTDATA("VALOR",$B$11,"CLASE","INGRESO","GRUPO","INGRESO OPERACIONAL") -> 0.46046124 | S10: UTILIDAD Y/O PÉRDIDA ANTES DE IMPUESTOS | T10: =+GETPIVOTDATA("VALOR",$S$11,"MES","ENERO","CLASE","INGRESOS")-GETPIVOTDATA("VALOR",$S$11,"MES","ENERO","CLASE","COSTOS DE VENTAS")-GETPIVOTDATA("VALOR",$S$11,"MES","ENERO","CLASE","GASTOS") -> 49824625 | U10: =+GETPIVOTDATA("VALOR",$S$11,"MES","FEBRERO","CLASE","INGRESOS")-GETPIVOTDATA("VALOR",$S$11,"MES","FEBRERO","CLASE","COSTOS DE VENTAS")-GETPIVOTDATA("VALOR",$S$11,"MES","FEBRERO","CLASE","GASTOS") -> -8039990.3 | V10: =+GETPIVOTDATA("VALOR",$S$11,"MES","MARZO","CLASE","INGRESOS")-GETPIVOTDATA("VALOR",$S$11,"MES","MARZO","CLASE","COSTOS DE VENTAS")-GETPIVOTDATA("VALOR",$S$11,"MES","MARZO","CLASE","GASTOS") -> 81139615 | W10: =+GETPIVOTDATA("VALOR",$S$11,"CLASE","INGRESOS")-GETPIVOTDATA("VALOR",$S$11,"CLASE","COSTOS DE VENTAS")-GETPIVOTDATA("VALOR",$S$11,"CLASE","GASTOS") -> 1.2292425e+08 | X10: =+X13-X16-X18 -> 0 | Y10: =+Y13-Y16-Y18 -> 0 | Z10: =+Z13-Z16-Z18 -> 0 | AA10: =+GETPIVOTDATA("VALOR",$S$11,"MES","AGOSTO","CLASE","INGRESO")-GETPIVOTDATA("VALOR",$S$11,"MES","AGOSTO","CLASE","COSTO")-GETPIVOTDATA("VALOR",$S$11,"MES","AGOSTO","CLASE","GASTO") -> #REF! | AB10: =+GETPIVOTDATA("VALOR",$S$11,"MES","SEPTIEMBRE","CLASE","INGRESO")-GETPIVOTDATA("VALOR",$S$11,"MES","SEPTIEMBRE","CLASE","COSTO")-GETPIVOTDATA("VALOR",$S$11,"MES","SEPTIEMBRE","CLASE","GASTO") -> #REF! | AC10: =+GETPIVOTDATA("VALOR",$S$11,"MES","OCTUBRE","CLASE","INGRESO")-GETPIVOTDATA("VALOR",$S$11,"MES","OCTUBRE","CLASE","COSTO")-GETPIVOTDATA("VALOR",$S$11,"MES","OCTUBRE","CLASE","GASTO") -> #REF! | AD10: =+GETPIVOTDATA("VALOR",$S$11,"MES","NOVIEMBRE","CLASE","INGRESO")-GETPIVOTDATA("VALOR",$S$11,"MES","NOVIEMBRE","CLASE","COSTO")-GETPIVOTDATA("VALOR",$S$11,"MES","NOVIEMBRE","CLASE","GASTO") -> #REF! | AE10: =+AE13-AE16-AE18 -> 0 | AF10: =+GETPIVOTDATA("VALOR",$S$11,"CLASE","INGRESO")-GETPIVOTDATA("VALOR",$S$11,"CLASE","COSTO")-GETPIVOTDATA("VALOR",$S$11,"CLASE","GASTO") -> #REF! | AG10: =+Z10/GETPIVOTDATA("VALOR",$S$11,"CLASE","INGRESO","GRUPO","INGRESO OPERACIONAL") -> #REF!
B11: PRESUPUESTO | C11: PERIODO | S11: COMPORTAMIENTO REAL | T11: PERIODO
B12: CUENTA | C12: ENERO | D12: FEBRERO | E12: MARZO | F12: TOTAL REAL | P12: % | S12: CUENTA | T12: ENERO | U12: FEBRERO | V12: MARZO | W12: TOTAL REAL | AN12: 46023 | AO12: 46054 | AP12: 46082 | AQ12: 46113 | AR12: 46143 | AS12: 46174 | AT12: 46204 | AU12: 46235 | AV12: 46266 | AW12: 46296 | AX12: 46327 | AY12: 46357 | AZ12: 46388 | BA12: 46419 | BB12: 46447 | BC12: 46478 | BD12: 46508 | BE12: 46539 | BF12: 46569 | BG12: 46600 | BH12: 46631 | BI12: 46661 | BJ12: 46692 | BK12: 46722
B13: INGRESO | C13: 2.8260899e+08 | D13: 2.5076796e+08 | E13: 3.7015489e+08 | F13: 9.0353184e+08 | P13: =+GETPIVOTDATA("VALOR",$B$11,"CLASE","INGRESO")/GETPIVOTDATA("VALOR",$B$11,"CLASE","INGRESO") -> 1 | S13: INGRESOS | T13: 1.9304348e+08 | U13: 1.4352729e+08 | V13: 2.2589183e+08 | W13: 5.6246259e+08 | AG13: =+GETPIVOTDATA("VALOR",$S$11,"CLASE","INGRESO")/GETPIVOTDATA("VALOR",$S$11,"CLASE","INGRESO") -> #REF! | AM13: INGRESO | AN13: 1.9304348e+08 | AO13: 1.4352729e+08 | AP13: 2.2589183e+08
B14: INGRESO OPERACIONAL | C14: 2.8260899e+08 | D14: 2.5076796e+08 | E14: 3.7015489e+08 | F14: 9.0353184e+08 | P14: =+GETPIVOTDATA("VALOR",$B$11,"CLASE","INGRESO","GRUPO","INGRESO OPERACIONAL")/GETPIVOTDATA("VALOR",$B$11,"CLASE","INGRESO","GRUPO","INGRESO OPERACIONAL") -> 1 | S14: OPERACIONALES | T14: 1.9304348e+08 | U14: 1.4352729e+08 | V14: 2.2589183e+08 | W14: 5.6246259e+08 | AG14: =+GETPIVOTDATA("VALOR",$S$11,"CLASE","INGRESO","GRUPO","INGRESO OPERACIONAL")/GETPIVOTDATA("VALOR",$S$11,"CLASE","INGRESO") -> #REF! | AM14: INGRESO OPERACIONAL | AN14: 1.9304348e+08 | AO14: 1.4352729e+08 | AP14: 2.2589183e+08
B15: COSTO | C15: 96544492 | D15: 73879686 | E15: 1.1322948e+08 | F15: 2.8365366e+08 | P15: =+GETPIVOTDATA("VALOR",$B$11,"CLASE","COSTO")/GETPIVOTDATA("VALOR",$B$11,"CLASE","INGRESO","GRUPO","INGRESO OPERACIONAL") -> 0.31393876 | S15: COSTOS DE VENTAS | T15: 8904289.3 | U15: 8775774 | V15: 10284181 | W15: 27964244 | AG15: =+GETPIVOTDATA("VALOR",$S$11,"CLASE","INGRESO","GRUPO","INGRESO NO OPERACIONAL")/GETPIVOTDATA("VALOR",$S$11,"CLASE","INGRESO") -> #REF! | AM15: INGRESO NO OPERACIONAL | AN15: 0
B16: COSTO DE VENTA | C16: 96544492 | D16: 73879686 | E16: 1.1322948e+08 | F16: 2.8365366e+08 | P16: =+GETPIVOTDATA("VALOR",$B$11,"CLASE","COSTO","GRUPO","COSTO DE VENTA")/GETPIVOTDATA("VALOR",$B$11,"CLASE","INGRESO","GRUPO","INGRESO OPERACIONAL") -> 0.31393876 | S16: COMERCIO AL POR MAYOR Y POR MENOR | T16: 2777735.3 | U16: 1249100 | V16: 3724720 | W16: 7751555.3 | AG16: =+GETPIVOTDATA("VALOR",$S$11,"CLASE","COSTO")/GETPIVOTDATA("VALOR",$S$11,"CLASE","INGRESO") -> #REF! | AM16: COSTO | AN16: 8904289.3 | AO16: 8775774 | AP16: 10284181
B17: GASTO | C17: 63756589 | D17: 56573252 | E17: 83506942 | F17: 2.0383678e+08 | P17: =+GETPIVOTDATA("VALOR",$B$11,"CLASE","GASTO")/GETPIVOTDATA("VALOR",$B$11,"CLASE","INGRESO","GRUPO","INGRESO OPERACIONAL") -> 0.2256 | S17: TRANSPORTE | T17: 1751100 | U17: 2837710 | V17: 2776730 | W17: 7365540 | AG17: =+GETPIVOTDATA("VALOR",$S$11,"CLASE","GASTO")/GETPIVOTDATA("VALOR",$S$11,"CLASE","INGRESO") -> #REF! | AM17: COMERCIO AL POR MAYOR Y POR MENOR | AN17: 2777735.3 | AO17: 1249100 | AP17: 3724720
B18: OPERACIONAL DE ADMINISTRACIÓN | C18: 63756589 | D18: 56573252 | E18: 83506942 | F18: 2.0383678e+08 | P18: =+GETPIVOTDATA("VALOR",$B$11,"CLASE","GASTO","GRUPO","OPERACIONAL DE ADMINISTRACIÓN")/GETPIVOTDATA("VALOR",$B$11,"CLASE","INGRESO","GRUPO","INGRESO OPERACIONAL") -> 0.2256 | S18: ALMACENAMIENTO | T18: 2645071 | U18: 2688079 | V18: 2182256 | W18: 7515406 | AG18: =+GETPIVOTDATA("VALOR",$S$11,"CLASE","GASTO","GRUPO","OPERACIONAL DE ADMINISTRACIÓN")/GETPIVOTDATA("VALOR",$S$11,"CLASE","INGRESO") -> #REF! | AM18: TRANSPORTE | AN18: 1751100 | AO18: 2837710 | AP18: 2776730
S19: PROCESO LOGISTICO | T19: 1730383 | U19: 2000885 | V19: 1456443 | W19: 5187711 | AG19: =+GETPIVOTDATA("VALOR",$S$11,"CLASE","GASTO","GRUPO","GASTOS DE VENTAS")/GETPIVOTDATA("VALOR",$S$11,"CLASE","INGRESO") -> #REF! | AM19: ALMACENAMIENTO | AN19: 2645071 | AO19: 2688079 | AP19: 2182256
S20: ANALISIS BIOLOGICO | V20: 144032 | W20: 144032 | AG20: =+GETPIVOTDATA("VALOR",$S$11,"CLASE","GASTO","GRUPO","NO OPERACIONALES")/GETPIVOTDATA("VALOR",$S$11,"CLASE","INGRESO") -> #REF! | AM20: PROCESO LOGISTICO | AN20: 1730383 | AO20: 2000885 | AP20: 1456443
S21: GASTOS | T21: 1.3431457e+08 | U21: 1.427915e+08 | V21: 1.3446803e+08 | W21: 4.115741e+08 | AM21: ANALISIS BIOLOGICO | AP21: 144032
S22: OPERACIONALES DE ADMINISTRACIÓN | T22: 85819509 | U22: 86358543 | V22: 91189193 | W22: 2.6336725e+08 | AM22: GASTO | AN22: 1.3431457e+08 | AO22: 1.427915e+08 | AP22: 1.3446803e+08
S23: OPERACIONALES DE VENTAS | T23: 43550562 | U23: 45040726 | V23: 40234066 | W23: 128825354 | AG23: =+GETPIVOTDATA("VALOR",$S$11,"CLASE","IMPUESTO DE RENTA Y COMPLEMENTARIOS")/GETPIVOTDATA("VALOR",$S$11,"CLASE","INGRESO") -> #REF! | AM23: OPERACIONAL DE ADMINISTRACIÓN | AN23: 85819509 | AO23: 86358543 | AP23: 91189193
S24: NO OPERACIONALES | T24: 4944496.2 | U24: 11392233 | V24: 3044772.7 | W24: 19381502 | AM24: GASTOS DE VENTAS | AN24: 43550562 | AO24: 45040726 | AP24: 40234066
AM25: NO OPERACIONALES | AN25: 4944496.2 | AO25: 11392233 | AP25: 3044772.7 | AQ25: =+AQ13-AQ16-AQ21 -> 0 | AR25: =+AR13-AR16-AR21 -> 0 | AS25: =+AS13-AS16-AS21 -> 0 | AT25: =+AT13-AT16-AT21 -> 0 | AU25: =+AU13-AU16-AU21 -> 0 | AV25: =+AV13-AV16-AV21 -> 0 | AW25: =+AW13-AW16-AW21 -> 0 | AX25: =+AX13-AX16-AX21 -> 0 | ... BK25: =+BK13-BK16-BK21 -> 0
AM26: UTILIDAD Y/O PÉRDIDA | AN26: =+AN13-AN16-AN22 -> 49824625 | AO26: =+AO13-AO16-AO22 -> -8039990.3 | AP26: =+AP13-AP16-AP22 -> 81139615
AM27: MARGEN NETO | AN27: =+AN26/AN13 -> 0.25810053 | AO27: =+AO26/AO13 -> -0.056017155 | AP27: =+AP26/AP13 -> 0.35919677
M47: NOVIEMBRE | N47: DICIEMBRE
M48: =+M10 -> #REF! | N48: =+N10 -> #REF!
M49: =+AD10 -> #REF! | N49: =+AE10 -> 0
AE66: -806334
C112: ENERO | D112: FEBRERO | E112: MARZO | F112: ABRIL | G112: MAYO | H112: JUNIO | I112: JULIO | J112: AGOSTO | K112: SEPTIEMBRE | L112: OCTUBRE
B113: UTILIDAD Y/O PÉRDIDA PPTO. | C113: 4463158.5 | D113: 1436994.7 | E113: 9386186.7 | F113: 674977.37 | G113: 4229930.2 | H113: 4846082.7 | I113: =+I10 -> 4.160414e+08 | J113: =+J10 -> #REF! | K113: =+K10 -> 0 | L113: =+L10 -> 0
B114: UTILIDAD Y/O PÉRDIDA REAL | C114: 7291266 | D114: 6559927.2 | E114: 10493418 | F114: 8366502.1 | G114: 7780923.3 | H114: 9761695 | I114: =+Z10 -> 0 | J114: =+AA10 -> #REF! | K114: =+AB10 -> #REF! | L114: =+AC10 -> #REF!

Sheet BASE DE DATOS E.R.
A1: MES | B1: ESTADO | C1: AÑO | D1: CENTRO DE COSTO | E1: CLASE | F1: GRUPO | G1: SUBGRUPO | H1: CUENTA | I1: TERCERO | J1: VALOR
A2: AGOSTO | B2: REAL | C2: 2018 | D2: HARINA | E2: GASTO | F2: OPERACIONAL DE ADMINISTRACIÓN | G2: SERVICIOS | H2: 51352001 - Servicios - Procesamiento electrónico de datos | J2: 178235
A3: AGOSTO | B3: REAL | C3: 2018 | D3: HARINA | E3: GASTO | F3: OPERACIONAL DE ADMINISTRACIÓN | G3: SERVICIOS | H3: 513560 - Publicidad y Propaganda | J3: 450000
A4: AGOSTO | B4: REAL | C4: 2018 | D4: HARINA | E4: GASTO | F4: OPERACIONAL DE ADMINISTRACIÓN | G4: GASTOS LEGALES | H4: 51401501 - Tramites y licencias | J4: 1622610
A5: AGOSTO | B5: REAL | C5: 2018 | D5: HARINA | E5: GASTO | F5: OPERACIONAL DE ADMINISTRACIÓN | G5: DIVERSOS | H5: 51953001 - Útiles papelería y fotocopias | J5: 105067
A6: AGOSTO | B6: REAL | C6: 2018 | D6: HARINA | E6: GASTO | F6: NO OPERACIONALES | G6: DIVERSOS | H6: 53959502 - No deducibles | J6: 1314850
A7: SEPTIEMBRE | B7: REAL | C7: 2018 | D7: HARINA | E7: INGRESO | F7: INGRESO OPERACIONAL | G7: COMERCIO AL POR MAYOR Y AL POR MENOR | H7: 41350101 - Comercio al por mayor y al detal | J7: 0
A8: SEPTIEMBRE | B8: REAL | C8: 2018 | D8: HARINA | E8: GASTO | F8: OPERACIONAL DE ADMINISTRACIÓN | G8: GASTOS DE PERSONAL | H8: 51050601 - Sueldos | J8: 1400000
A9: SEPTIEMBRE | B9: REAL | C9: 2018 | D9: HARINA | E9: GASTO | F9: OPERACIONAL DE ADMINISTRACIÓN | G9: GASTOS DE PERSONAL | H9: 51052701 - Auxilio de transporte | J9: 88211
A10: SEPTIEMBRE | B10: REAL | C10: 2018 | D10: HARINA | E10: GASTO | F10: OPERACIONAL DE ADMINISTRACIÓN | G10: GASTOS DE PERSONAL | H10: 51053001 - Cesantías | J10: 123968
A11: SEPTIEMBRE | B11: REAL | C11: 2018 | D11: HARINA | E11: GASTO | F11: OPERACIONAL DE ADMINISTRACIÓN | G11: GASTOS DE PERSONAL | H11: 51053301 - Intereses sobre cesantías | J11: 14876
A12: SEPTIEMBRE | B12: REAL | C12: 2018 | D12: HARINA | E12: GASTO | F12: OPERACIONAL DE ADMINISTRACIÓN | G12: GASTOS DE PERSONAL | H12: 51053601 - Prima de servicios | J12: 123968
A13: SEPTIEMBRE | B13: REAL | C13: 2018 | D13: HARINA | E13: GASTO | F13: OPERACIONAL DE ADMINISTRACIÓN | G13: GASTOS DE PERSONAL | H13: 51053901 - Vacaciones | J13: 58380
... A30: SEPTIEMBRE | B30: REAL | C30: 2018 | D30: HARINA | E30: GASTO | F30: NO OPERACIONALES | G30: EXTRAORDINARIOS | H30: 53152002 - Otros impuestos asumidos | J30: 28000
A31: AGOSTO | B31: PRESUPUESTO | C31: 2018 | D31: HARINA | E31: INGRESO | F31: INGRESO OPERACIONAL | G31: COMERCIO AL POR MAYOR Y AL POR MENOR | H31: 41350101 - Comercio al por mayor y al detal
A32: AGOSTO | B32: PRESUPUESTO | C32: 2018 | D32: HARINA | E32: COSTO | F32: COSTO DE VENTA | G32: COMERCIO AL POR MAYOR Y AL POR MENOR | H32: 621006 - Empaques | J32: 3381600
A33: AGOSTO | B33: PRESUPUESTO | C33: 2018 | D33: HARINA | E33: COSTO | F33: COSTO DE VENTA | G33: COMERCIO AL POR MAYOR Y AL POR MENOR | H33: 621005 - Materia Prima
A34: AGOSTO | B34: PRESUPUESTO | C34: 2018 | D34: HARINA | E34: GASTO | F34: OPERACIONAL DE ADMINISTRACIÓN | G34: GASTOS DE PERSONAL | H34: 51050601 - Sueldos
A35: AGOSTO | B35: PRESUPUESTO | C35: 2018 | D35: HARINA | E35: GASTO | F35: OPERACIONAL DE ADMINISTRACIÓN | G35: GASTOS DE PERSONAL | H35: 51052701 - Auxilio de transporte
A36: AGOSTO | B36: PRESUPUESTO | C36: 2018 | D36: HARINA | E36: GASTO | F36: OPERACIONAL DE ADMINISTRACIÓN | G36: GASTOS DE PERSONAL | H36: 51053001 - Cesantías
A37: AGOSTO | B37: PRESUPUESTO | C37: 2018 | D37: HARINA | E37: GASTO | F37: OPERACIONAL DE ADMINISTRACIÓN | G37: GASTOS DE PERSONAL | H37: 51053301 - Intereses sobre cesantías
A38: AGOSTO | B38: PRESUPUESTO | C38: 2018 | D38: HARINA | E38: GASTO | F38: OPERACIONAL DE ADMINISTRACIÓN | G38: GASTOS DE PERSONAL | H38: 51053601 - Prima de servicios
A39: AGOSTO | B39: PRESUPUESTO | C39: 2018 | D39: HARINA | E39: GASTO | F39: OPERACIONAL DE ADMINISTRACIÓN | G39: GASTOS DE PERSONAL | H39: 51053901 - Vacaciones
A40: AGOSTO | B40: PRESUPUESTO | C40: 2018 | D40: HARINA | E40: GASTO | F40: OPERACIONAL DE ADMINISTRACIÓN | G40: GASTOS DE PERSONAL | H40: 51054502 - Auxilio transporte
A41: AGOSTO | B41: PRESUPUESTO | C41: 2018 | D41: HARINA | E41: GASTO | F41: OPERACIONAL DE ADMINISTRACIÓN | G41: GASTOS DE PERSONAL | H41: 51056801 - Aportes a administradora de riesgos laborales
A42: AGOSTO | B42: PRESUPUESTO | C42: 2018 | D42: HARINA | E42: GASTO | F42: OPERACIONAL DE ADMINISTRACIÓN | G42: GASTOS DE PERSONAL | H42: 51057001 - Aporte a fondos de pensión y/o cesantías
A43: AGOSTO | B43: PRESUPUESTO | C43: 2018 | D43: HARINA | E43: GASTO | F43: OPERACIONAL DE ADMINISTRACIÓN | G43: GASTOS DE PERSONAL | H43: 51057201 - Aportes cajas de compensación familiar
A44: AGOSTO | B44: PRESUPUESTO | C44: 2018 | D44: HARINA | E44: GASTO | F44: OPERACIONAL DE ADMINISTRACIÓN | G44: IMPUESTOS | H44: 51159501 - Otros impuestos
... A46: AGOSTO | B46: PRESUPUESTO | C46: 2018 | D46: HARINA | E46: GASTO | F46: OPERACIONAL DE ADMINISTRACIÓN | G46: SERVICIOS | H46: 51352001 - Servicios - Procesamiento electrónico de datos
A47: AGOSTO | B47: PRESUPUESTO | C47: 2018 | D47: HARINA | E47: GASTO | F47: OPERACIONAL DE ADMINISTRACIÓN | G47: SERVICIOS | H47: 513560 - Publicidad y Propaganda | J47: =6000000+1000000 -> 7000000
A48: AGOSTO | B48: PRESUPUESTO | C48: 2018 | D48: HARINA | E48: GASTO | F48: OPERACIONAL DE ADMINISTRACIÓN | G48: GASTOS LEGALES | H48: 51401501 - Tramites y licencias | J48: 12800000
A49: AGOSTO | B49: PRESUPUESTO | C49: 2018 | D49: HARINA | E49: GASTO | F49: OPERACIONAL DE ADMINISTRACIÓN | G49: GASTOS LEGALES | H49: 51501501 - Reparaciones locativas | J49: 1000000
A50: AGOSTO | B50: PRESUPUESTO | C50: 2018 | D50: HARINA | E50: GASTO | F50: OPERACIONAL DE ADMINISTRACIÓN | G50: DIVERSOS | H50: 51951001 - Libros suscripciones periódicos y revistas
A51: AGOSTO | B51: PRESUPUESTO | C51: 2018 | D51: HARINA | E51: GASTO | F51: OPERACIONAL DE ADMINISTRACIÓN | G51: DIVERSOS | H51: 51953001 - Útiles papelería y fotocopias | J51: 350000
A52: AGOSTO | B52: PRESUPUESTO | C52: 2018 | D52: HARINA | E52: GASTO | F52: OPERACIONAL DE ADMINISTRACIÓN | G52: DIVERSOS | H52: 51956501 - Parqueaderos
A53: AGOSTO | B53: PRESUPUESTO | C53: 2018 | D53: HARINA | E53: GASTO | F53: NO OPERACIONALES | G53: FINANCIEROS | H53: 53051501 - Comisiones
A54: AGOSTO | B54: PRESUPUESTO | C54: 2018 | D54: HARINA | E54: GASTO | F54: NO OPERACIONALES | G54: FINANCIEROS | H54: 53053501 - Descuentos comerciales condicionados
A55: AGOSTO | B55: PRESUPUESTO | C55: 2018 | D55: HARINA | E55: GASTO | F55: NO OPERACIONALES | G55: DIVERSOS | H55: 53959502 - No deducibles
A56: AGOSTO | B56: PRESUPUESTO | C56: 2018 | D56: HARINA | E56: GASTO | F56: NO OPERACIONALES | G56: EXTRAORDINARIOS | H56: 53152001 - Gravamen al movimiento financiero
A57: AGOSTO | B57: PRESUPUESTO | C57: 2018 | D57: HARINA | E57: GASTO | F57: NO OPERACIONALES | G57: EXTRAORDINARIOS | H57: 53152002 - Otros impuestos asumidos
A58: AGOSTO | B58: PRESUPUESTO | C58: 2018 | D58: HARINA | E58: GASTO | F58: DE VENTAS | G58: DIVERSOS | H58: 529545 - Taxis y buses
A59: SEPTIEMBRE | B59: PRESUPUESTO | C59: 2018 | D59: HARINA | E59: INGRESO | F59: INGRESO OPERACIONAL | G59: COMERCIO AL POR MAYOR Y AL POR MENOR | H59: 41350101 - Comercio al por mayor y al detal | J59: =3400000-J60 -> 2900000
A60: SEPTIEMBRE | B60: PRESUPUESTO | C60: 2018 | D60: CAPSULAS | E60: INGRESO | F60: INGRESO OPERACIONAL | G60: COMERCIO AL POR MAYOR Y AL POR MENOR | H60: 41350101 - Comercio al por mayor y al detal | J60: 500000
A61: SEPTIEMBRE | B61: PRESUPUESTO | C61: 2018 | D61: HARINA | E61: COSTO | F61: COSTO DE VENTA | G61: COMERCIO AL POR MAYOR Y AL POR MENOR | H61: 621006 - Empaques
A62: SEPTIEMBRE | B62: PRESUPUESTO | C62: 2018 | D62: HARINA | E62: COSTO | F62: COSTO DE VENTA | G62: COMERCIO AL POR MAYOR Y AL POR MENOR | H62: 621005 - Materia Prima
A63: SEPTIEMBRE | B63: PRESUPUESTO | C63: 2018 | D63: HARINA | E63: COSTO | F63: COSTO DE VENTA | G63: COMERCIO AL POR MAYOR Y AL POR MENOR | H63: 621006 - Transporte | J63: 1000000
A64: SEPTIEMBRE | B64: PRESUPUESTO | C64: 2018 | D64: HARINA | E64: GASTO | F64: OPERACIONAL DE ADMINISTRACIÓN | G64: GASTOS DE PERSONAL | H64: 51050601 - Sueldos | J64: 1400000
A65: SEPTIEMBRE | B65: PRESUPUESTO | C65: 2018 | D65: HARINA | E65: GASTO | F65: OPERACIONAL DE ADMINISTRACIÓN | G65: GASTOS DE PERSONAL | H65: 51052701 - Auxilio de transporte | J65: 88211
A66: SEPTIEMBRE | B66: PRESUPUESTO | C66: 2018 | D66: HARINA | E66: GASTO | F66: OPERACIONAL DE ADMINISTRACIÓN | G66: GASTOS DE PERSONAL | H66: 51053001 - Cesantías | J66: 124017.58
A67: SEPTIEMBRE | B67: PRESUPUESTO | C67: 2018 | D67: HARINA | E67: GASTO | F67: OPERACIONAL DE ADMINISTRACIÓN | G67: GASTOS DE PERSONAL | H67: 51053301 - Intereses sobre cesantías | J67: 14882.11
A68: SEPTIEMBRE | B68: PRESUPUESTO | C68: 2018 | D68: HARINA | E68: GASTO | F68: OPERACIONAL DE ADMINISTRACIÓN | G68: GASTOS DE PERSONAL | H68: 51053601 - Prima de servicios | J68: 124017.58
A69: SEPTIEMBRE | B69: PRESUPUESTO | C69: 2018 | D69: HARINA | E69: GASTO | F69: OPERACIONAL DE ADMINISTRACIÓN | G69: GASTOS DE PERSONAL | H69: 51053901 - Vacaciones | J69: 58333.333
A70: SEPTIEMBRE | B70: PRESUPUESTO | C70: 2018 | D70: HARINA | E70: GASTO | F70: OPERACIONAL DE ADMINISTRACIÓN | G70: GASTOS DE PERSONAL | H70: 51054502 - Auxilio transporte | J70: 88211
A71: SEPTIEMBRE | B71: PRESUPUESTO | C71: 2018 | D71: HARINA | E71: GASTO | F71: OPERACIONAL DE ADMINISTRACIÓN | G71: GASTOS DE PERSONAL | H71: 51056801 - Aportes a administradora de riesgos laborales | J71: 7308
A72: SEPTIEMBRE | B72: PRESUPUESTO | C72: 2018 | D72: HARINA | E72: GASTO | F72: OPERACIONAL DE ADMINISTRACIÓN | G72: GASTOS DE PERSONAL | H72: 51057001 - Aporte a fondos de pensión y/o cesantías | J72: 168000
A73: SEPTIEMBRE | B73: PRESUPUESTO | C73: 2018 | D73: HARINA | E73: GASTO | F73: OPERACIONAL DE ADMINISTRACIÓN | G73: GASTOS DE PERSONAL | H73: 51057201 - Aportes cajas de compensación familiar | J73: 56000
A74: SEPTIEMBRE | B74: PRESUPUESTO | C74: 2018 | D74: HARINA | E74: GASTO | F74: OPERACIONAL DE ADMINISTRACIÓN | G74: GASTOS DE PERSONAL | H74: 51057201 - Aportes cajas de compensación familiar | J74: 56000
A75: SEPTIEMBRE | B75: PRESUPUESTO | C75: 2018 | D75: HARINA | E75: GASTO | F75: OPERACIONAL DE ADMINISTRACIÓN | G75: HONORARIOS | H75: 51102501 - Honorarios - Asesoría jurídica | J75: 390621
A76: SEPTIEMBRE | B76: PRESUPUESTO | C76: 2018 | D76: HARINA | E76: GASTO | F76: OPERACIONAL DE ADMINISTRACIÓN | G76: IMPUESTOS | H76: 51159501 - Otros impuestos
A77: SEPTIEMBRE | B77: PRESUPUESTO | C77: 2018 | D77: HARINA | E77: GASTO | F77: OPERACIONAL DE ADMINISTRACIÓN | G77: ARRENDAMIENTOS | H77: 51201001 - Arrendamientos - Construcciones y edificaciones
A78: SEPTIEMBRE | B78: PRESUPUESTO | C78: 2018 | D78: HARINA | E78: GASTO | F78: OPERACIONAL DE ADMINISTRACIÓN | G78: SERVICIOS | H78: 51352001 - Servicios - Procesamiento electrónico de datos
A79: SEPTIEMBRE | B79: PRESUPUESTO | C79: 2018 | D79: HARINA | E79: GASTO | F79: OPERACIONAL DE ADMINISTRACIÓN | G79: SERVICIOS | H79: 513560 - Publicidad y Propaganda
A80: SEPTIEMBRE | B80: PRESUPUESTO | C80: 2018 | D80: HARINA | E80: GASTO | F80: OPERACIONAL DE ADMINISTRACIÓN | G80: GASTOS LEGALES | H80: 51401501 - Tramites y licencias
A81: SEPTIEMBRE | B81: PRESUPUESTO | C81: 2018 | D81: HARINA | E81: GASTO | F81: OPERACIONAL DE ADMINISTRACIÓN | G81: DIVERSOS | H81: 51951001 - Libros suscripciones periódicos y revistas
A82: SEPTIEMBRE | B82: PRESUPUESTO | C82: 2018 | D82: HARINA | E82: GASTO | F82: OPERACIONAL DE ADMINISTRACIÓN | G82: DIVERSOS | H82: 51953001 - Útiles papelería y fotocopias | J82: 30000
A83: SEPTIEMBRE | B83: PRESUPUESTO | C83: 2018 | D83: HARINA | E83: GASTO | F83: OPERACIONAL DE ADMINISTRACIÓN | G83: DIVERSOS | H83: 51956501 - Parqueaderos
A84: SEPTIEMBRE | B84: PRESUPUESTO | C84: 2018 | D84: HARINA | E84: GASTO | F84: NO OPERACIONALES | G84: FINANCIEROS | H84: 53051501 - Comisiones
A85: SEPTIEMBRE | B85: PRESUPUESTO | C85: 2018 | D85: HARINA | E85: GASTO | F85: NO OPERACIONALES | G85: FINANCIEROS | H85: 53053501 - Descuentos comerciales condicionados
A86: SEPTIEMBRE | B86: PRESUPUESTO | C86: 2018 | D86: HARINA | E86: GASTO | F86: NO OPERACIONALES | G86: DIVERSOS | H86: 53959502 - No deducibles
A87: SEPTIEMBRE | B87: PRESUPUESTO | C87: 2018 | D87: HARINA | E87: GASTO | F87: NO OPERACIONALES | G87: EXTRAORDINARIOS | H87: 53152001 - Gravamen al movimiento financiero
A88: SEPTIEMBRE | B88: PRESUPUESTO | C88: 2018 | D88: HARINA | E88: GASTO | F88: NO OPERACIONALES | G88: EXTRAORDINARIOS | H88: 53152002 - Otros impuestos asumidos
A89: SEPTIEMBRE | B89: PRESUPUESTO | C89: 2018 | D89: HARINA | E89: GASTO | F89: DE VENTAS | G89: DIVERSOS | H89: 529545 - Taxis y buses
A90: OCTUBRE | B90: PRESUPUESTO | C90: 2018 | D90: HARINA | E90: INGRESO | F90: INGRESO OPERACIONAL | G90: COMERCIO AL POR MAYOR Y AL POR MENOR | H90: 41350101 - Comercio al por mayor y al detal | J90: =3625000-J91 -> 3125000
A91: OCTUBRE | B91: PRESUPUESTO | C91: 2018 | D91: CAPSULAS | E91: INGRESO | F91: INGRESO OPERACIONAL | G91: COMERCIO AL POR MAYOR Y AL POR MENOR | H91: 41350101 - Comercio al por mayor y al detal | J91: 500000
A92: OCTUBRE | B92: PRESUPUESTO | C92: 2018 | D92: HARINA | E92: COSTO | F92: COSTO DE VENTA | G92: COMERCIO AL POR MAYOR Y AL POR MENOR | H92: 621006 - Empaques
A93: OCTUBRE | B93: PRESUPUESTO | C93: 2018 | D93: HARINA | E93: COSTO | F93: COSTO DE VENTA | G93: COMERCIO AL POR MAYOR Y AL POR MENOR | H93: 621005 - Materia Prima
A94: OCTUBRE | B94: PRESUPUESTO | C94: 2018 | D94: HARINA | E94: COSTO | F94: COSTO DE VENTA | G94: COMERCIO AL POR MAYOR Y AL POR MENOR | H94: 621006 - Transporte | J94: 1000000
A95: OCTUBRE | B95: PRESUPUESTO | C95: 2018 | D95: HARINA | E95: GASTO | F95: OPERACIONAL DE ADMINISTRACIÓN | G95: GASTOS DE PERSONAL | H95: 51050601 - Sueldos | J95: 1400000
A96: OCTUBRE | B96: PRESUPUESTO | C96: 2018 | D96: HARINA | E96: GASTO | F96: OPERACIONAL DE ADMINISTRACIÓN | G96: GASTOS DE PERSONAL | H96: 51052701 - Auxilio de transporte | J96: 88211
A97: OCTUBRE | B97: PRESUPUESTO | C97: 2018 | D97: HARINA | E97: GASTO | F97: OPERACIONAL DE ADMINISTRACIÓN | G97: GASTOS DE PERSONAL | H97: 51053001 - Cesantías | J97: 124017.58
A98: OCTUBRE | B98: PRESUPUESTO | C98: 2018 | D98: HARINA | E98: GASTO | F98: OPERACIONAL DE ADMINISTRACIÓN | G98: GASTOS DE PERSONAL | H98: 51053301 - Intereses sobre cesantías | J98: 14882.11
A99: OCTUBRE | B99: PRESUPUESTO | C99: 2018 | D99: HARINA | E99: GASTO | F99: OPERACIONAL DE ADMINISTRACIÓN | G99: GASTOS DE PERSONAL | H99: 51053601 - Prima de servicios | J99: 124017.58
A100: OCTUBRE | B100: PRESUPUESTO | C100: 2018 | D100: HARINA | E100: GASTO | F100: OPERACIONAL DE ADMINISTRACIÓN | G100: GASTOS DE PERSONAL | H100: 51053901 - Vacaciones | J100: 58333.333
A101: OCTUBRE | B101: PRESUPUESTO | C101: 2018 | D101: HARINA | E101: GASTO | F101: OPERACIONAL DE ADMINISTRACIÓN | G101: GASTOS DE PERSONAL | H101: 51054502 - Auxilio transporte | J101: 88211
A102: OCTUBRE | B102: PRESUPUESTO | C102: 2018 | D102: HARINA | E102: GASTO | F102: OPERACIONAL DE ADMINISTRACIÓN | G102: GASTOS DE PERSONAL | H102: 51056801 - Aportes a administradora de riesgos laborales | J102: 7308
A103: OCTUBRE | B103: PRESUPUESTO | C103: 2018 | D103: HARINA | E103: GASTO | F103: OPERACIONAL DE ADMINISTRACIÓN | G103: GASTOS DE PERSONAL | H103: 51057001 - Aporte a fondos de pensión y/o cesantías | J103: 168000
A104: OCTUBRE | B104: PRESUPUESTO | C104: 2018 | D104: HARINA | E104: GASTO | F104: OPERACIONAL DE ADMINISTRACIÓN | G104: GASTOS DE PERSONAL | H104: 51057201 - Aportes cajas de compensación familiar | J104: 56000
A105: OCTUBRE | B105: PRESUPUESTO | C105: 2018 | D105: HARINA | E105: GASTO | F105: OPERACIONAL DE ADMINISTRACIÓN | G105: GASTOS DE PERSONAL | H105: 51057201 - Aportes cajas de compensación familiar | J105: 56000
A106: OCTUBRE | B106: PRESUPUESTO | C106: 2018 | D106: HARINA | E106: GASTO | F106: OPERACIONAL DE ADMINISTRACIÓN | G106: HONORARIOS | H106: 51102501 - Honorarios - Asesoría jurídica | J106: 390621
A107: OCTUBRE | B107: PRESUPUESTO | C107: 2018 | D107: HARINA | E107: GASTO | F107: OPERACIONAL DE ADMINISTRACIÓN | G107: IMPUESTOS | H107: 51159501 - Otros impuestos
A108: OCTUBRE | B108: PRESUPUESTO | C108: 2018 | D108: HARINA | E108: GASTO | F108: OPERACIONAL DE ADMINISTRACIÓN | G108: ARRENDAMIENTOS | H108: 51201001 - Arrendamientos - Construcciones y edificaciones
A109: OCTUBRE | B109: PRESUPUESTO | C109: 2018 | D109: HARINA | E109: GASTO | F109: OPERACIONAL DE ADMINISTRACIÓN | G109: SERVICIOS | H109: 51352001 - Servicios - Procesamiento electrónico de datos
A110: OCTUBRE | B110: PRESUPUESTO | C110: 2018 | D110: HARINA | E110: GASTO | F110: OPERACIONAL DE ADMINISTRACIÓN | G110: SERVICIOS | H110: 513560 - Publicidad y Propaganda
A111: OCTUBRE | B111: PRESUPUESTO | C111: 2018 | D111: HARINA | E111: GASTO | F111: OPERACIONAL DE ADMINISTRACIÓN | G111: GASTOS LEGALES | H111: 51401501 - Tramites y licencias
A112: OCTUBRE | B112: PRESUPUESTO | C112: 2018 | D112: HARINA | E112: GASTO | F112: OPERACIONAL DE ADMINISTRACIÓN | G112: DIVERSOS | H112: 51951001 - Libros suscripciones periódicos y revistas
A113: OCTUBRE | B113: PRESUPUESTO | C113: 2018 | D113: HARINA | E113: GASTO | F113: OPERACIONAL DE ADMINISTRACIÓN | G113: DIVERSOS | H113: 51953001 - Útiles papelería y fotocopias | J113: 30000
A114: OCTUBRE | B114: PRESUPUESTO | C114: 2018 | D114: HARINA | E114: GASTO | F114: OPERACIONAL DE ADMINISTRACIÓN | G114: DIVERSOS | H114: 51956501 - Parqueaderos
A115: OCTUBRE | B115: PRESUPUESTO | C115: 2018 | D115: HARINA | E115: GASTO | F115: NO OPERACIONALES | G115: FINANCIEROS | H115: 53051501 - Comisiones
A116: OCTUBRE | B116: PRESUPUESTO | C116: 2018 | D116: HARINA | E116: GASTO | F116: NO OPERACIONALES | G116: FINANCIEROS | H116: 53053501 - Descuentos comerciales condicionados
A117: OCTUBRE | B117: PRESUPUESTO | C117: 2018 | D117: HARINA | E117: GASTO | F117: NO OPERACIONALES | G117: DIVERSOS | H117: 53959502 - No deducibles
...

Sheet E.R. COMPARATIVO
B2: PANGEA NATURAL PRODUCTS S.A.S.
B3: COMPARATIVO 2020 - 2021 -2022 - 2023 - 2024 - 2025
B8: CENTRO DE COSTO | C8: (Todas)
B9: UTILIDAD Y/O PÉRDIDA | C9: =+C14-C17-C25 -> -29785.18 | D9: =+D14-D17-D25 -> 7291266 | E9: =+E14-E17-E25 -> 8312002.3 | F9: =+F14-F17-F25 -> 33114195 | G9: =+G14-G17-G25 -> 25384477 | H9: =+H14-H17-H25 -> 2.441081e+08 | I9: =+I14-I17-I25 -> 0 | J9: =+J14-J17-J25 -> 3.1818026e+08 | ... CT9: =+CT14-CT17-CT25 -> -6.1326093e+08
B10: ESTADO DE RESULTADOS | C10: PERIODO
C11: ENERO | K11: Total ENERO | L11: FEBRERO | S11: Total FEBRERO | T11: MARZO | AA11: Total MARZO | AB11: ABRIL | AI11: Total ABRIL | AJ11: MAYO | AQ11: Total MAYO | AR11: JUNIO | AY11: Total JUNIO | AZ11: JULIO | BG11: Total JULIO | BH11: AGOSTO | BO11: Total AGOSTO | BP11: SEPTIEMBRE | BW11: Total SEPTIEMBRE | BX11: OCTUBRE | CE11: Total OCTUBRE | CF11: NOVIEMBRE | CM11: Total NOVIEMBRE | CN11: DICIEMBRE | CU11: Total DICIEMBRE
C12: REAL | J12: Total REAL | L12: REAL | R12: Total REAL | T12: REAL | Z12: Total REAL | AB12: REAL | AH12: Total REAL | AJ12: REAL | AP12: Total REAL | AR12: REAL | AX12: Total REAL | AZ12: REAL | BF12: Total REAL | BH12: REAL | BN12: Total REAL | BP12: REAL | BV12: Total REAL | BX12: REAL | CD12: Total REAL | CF12: REAL | CL12: Total REAL | CN12: REAL | CT12: Total REAL
B13: CUENTA | C13: 2020 | D13: 2021 | E13: 2022 | F13: 2023 | G13: 2024 | H13: 2025 | I13: 2026 | L13: 2020 | M13: 2021 | N13: 2022 | O13: 2023 | P13: 2024 | Q13: 2025 | T13: 2020 | U13: 2021 | V13: 2022 | W13: 2023 | X13: 2024 | Y13: 2025 | AB13: 2020 | AC13: 2021 | AD13: 2022 | AE13: 2023 | AF13: 2024 | AG13: 2025 | AJ13: 2020 | AK13: 2021 | AL13: 2022 | AM13: 2023 | AN13: 2024 | AO13: 2025 | AR13: 2020 | AS13: 2021 | AT13: 2022 | AU13: 2023 | AV13: 2024 | AW13: 2025 | AZ13: 2020 | BA13: 2021 | BB13: 2022 | BC13: 2023 | BD13: 2024 | BE13: 2025 | BH13: 2020 | BI13: 2021 | BJ13: 2022 | BK13: 2023 | BL13: 2024 | BM13: 2025 | BP13: 2020 | BQ13: 2021 | BR13: 2022 | BS13: 2023 | BT13: 2024 | BU13: 2025 | BX13: 2020 | BY13: 2021 | BZ13: 2022 | CA13: 2023 | CB13: 2024 | CC13: 2025 | CF13: 2020 | CG13: 2021 | CH13: 2022 | CI13: 2023 | CJ13: 2024 | CK13: 2025 | CN13: 2020 | CO13: 2021 | CP13: 2022 | CQ13: 2023 | CR13: 2024 | CS13: 2025
B14: INGRESO | C14: 6031177.2 | D14: 23566695 | E14: 45742925 | F14: 71358813 | G14: 85870783 | H14: 3.2072335e+08 | J14: 5.5329375e+08 | K14: 5.5329375e+08 | L14: 4299272 | M14: 24367830 | N14: 44799526 | O14: 69503543 | P14: 91956981 | Q14: 3.169696e+08 | R14: 5.5189675e+08 | S14: 5.5189675e+08 | T14: 12090117 | U14: 30112667 | V14: 64959508 | W14: 56096883 | X14: 90911120 | Y14: 5.1474171e+08 | Z14: 7.68912e+08 | AA14: 7.68912e+08 | AB14: 8494540 | AC14: 25718752 | AD14: 51632426 | AE14: 83359788 | AF14: 1.2431374e+08 | AG14: 1.6439559e+08 | AH14: 4.5791484e+08 | AI14: 4.5791484e+08 | AJ14: 7437580.5 | AK14: 33739236 | AL14: 50404730 | AM14: 88719293 | AN14: 1.7481787e+08 | AO14: 2.3733651e+08 | AP14: 5.9245522e+08 | AQ14: 5.9245522e+08 | AR14: 5728837 | AS14: 33736754 | AT14: 52358539 | AU14: 73394617 | AV14: 1.101378e+08 | AW14: 2.3947519e+08 | AX14: 5.1483173e+08 | AY14: 5.1483173e+08 | AZ14: 13756023 | BA14: 34656350 | BB14: 56553269 | BC14: 82363376 | BD14: 1.7592706e+08 | BE14: 2.4891128e+08 | BF14: 6.1216735e+08 | BG14: 6.1216735e+08 | BH14: 19006192 | BI14: 27849166 | BJ14: 56128488 | BK14: 94620496 | BL14: 1.3153474e+08 | BM14: 2.2840484e+08 | BN14: 5.5754392e+08 | BO14: 5.5754392e+08 | BP14: 20752627 | BQ14: 31200136 | BR14: 60620593 | BS14: 1.1324488e+08 | BT14: 1.6693452e+08 | BU14: 2.6959633e+08 | BV14: 6.6234908e+08 | BW14: 6.6234908e+08 | BX14: 25555612 | BY14: 38404950 | BZ14: 57211340 | CA14: 93847420 | CB14: 2.9098796e+08 | CC14: 1.9420759e+08 | CD14: 7.0021487e+08 | CE14: 7.0021487e+08 | CF14: 16500645 | CG14: 36867504 | CH14: 67583931 | CI14: 1.0331009e+08 | CJ14: 2.5574671e+08 | CK14: 2.1671167e+08 | CL14: 6.9672055e+08 | CM14: 6.9672055e+08 | CN14: 18561884 | CO14: 30659547 | CP14: 56025703 | CQ14: 1.7558088e+08 | CR14: 1.9489124e+08 | CS14: 3.399617e+08 | CT14: 8.1568095e+08 | CU14: 8.1568095e+08
B15: INGRESO OPERACIONAL | C15: 5965744 | D15: 23565829 | E15: 45739562 | F15: 71358810 | G15: 84577075 | H15: 3.2072335e+08 | J15: 5.5193037e+08 | K15: 5.5193037e+08 | L15: 4232271 | M15: 24367830 | N15: 44773515 | O15: 69503327 | P15: 91956434 | Q15: 3.167596e+08 | R15: 5.5159297e+08 | S15: 5.5159297e+08 | T15: 11974135 | U15: 30112163 | V15: 64936976 | W15: 56094023 | X15: 90859778 | Y15: 5.1474171e+08 | Z15: 7.6871878e+08 | AA15: 7.6871878e+08 | AB15: 8494060 | AC15: 25717564 | AD15: 51350410 | AE15: 83359788 | AF15: 1.2431374e+08 | AG15: 1.6439559e+08 | AH15: 4.5763115e+08 | AI15: 4.5763115e+08 | AJ15: 7437042 | AK15: 33738468 | AL15: 50403533 | AM15: 88718989 | AN15: 1.743192e+08 | AO15: 2.3733651e+08 | AP15: 5.9195374e+08 | AQ15: 5.9195374e+08 | AR15: 5728837 | AS15: 33736108 | AT15: 52337583 | AU15: 73394617 | AV15: 1.101378e+08 | AW15: 2.3947519e+08 | AX15: 5.1481013e+08 | AY15: 5.1481013e+08 | AZ15: 13755981 | BA15: 34656349 | BB15: 56524733 | BC15: 82348409 | BD15: 1.7592706e+08 | BE15: 2.4891128e+08 | BF15: 6.1212381e+08 | BG15: 6.1212381e+08 | BH15: 19006192 | BI15: 27797034 | BJ15: 56126585 | BK15: 94620300 | BL15: 1.3152963e+08 | BM15: 2.2840484e+08 | BN15: 5.5748458e+08 | BO15: 5.5748458e+08 | BP15: 20765643 | BQ15: 31198164 | BR15: 60617582 | BS15: 1.1260419e+08 | BT15: 1.6693452e+08 | BU15: 2.6584033e+08 | BV15: 6.5796043e+08 | BW15: 6.5796043e+08 | BX15: 25555612 | BY15: 38396333 | BZ15: 57187567 | CA15: 93842419 | CB15: 2.9098796e+08 | CC15: 1.9420759e+08 | CD15: 7.0017748e+08 | CE15: 7.0017748e+08 | CF15: 16499808 | CG15: 36385057 | CH15: 67583890 | CI15: 1.0331009e+08 | CJ15: 2.5574671e+08 | CK15: 2.1296168e+08 | CL15: 6.9248724e+08 | CM15: 6.9248724e+08 | CN15: 18320945 | CO15: 30608260 | CP15: 56023892 | CQ15: 1.7557933e+08 | CR15: 1.9489124e+08 | CS15: 3.399617e+08 | CT15: 8.1538537e+08 | CU15: 8.1538537e+08
B16: INGRESO NO OPERACIONAL | C16: 65433.18 | D16: 866 | E16: 3363.14 | F16: 3.12 | G16: 1293708.3 | J16: 1363373.8 | K16: 1363373.8 | L16: 67001 | N16: 26010.93 | O16: 215.25 | P16: 546.88 | Q16: 210000 | R16: 303774.06 | S16: 303774.06 | T16: 115982 | U16: 504.44 | V16: 22532.3 | W16: 2860 | X16: 51341.54 | Z16: 193220.28 | AA16: 193220.28 | AB16: 480 | AC16: 1188 | AD16: 282016.16 | AH16: 283684.16 | AI16: 283684.16 | AJ16: 538.47 | AK16: 767.28 | AL16: 1196.68 | AM16: 304 | AN16: 498672 | AP16: 501478.43 | AQ16: 501478.43 | AS16: 646 | AT16: 20955.96 | AX16: 21601.96 | AY16: 21601.96 | AZ16: 42 | BA16: 1.28 | BB16: 28536.39 | BC16: 14967.13 | BF16: 43546.8 | BG16: 43546.8 | BI16: 52132.61 | BJ16: 1902.33 | BK16: 196 | BL16: 5110 | BN16: 59340.94 | BO16: 59340.94 | BP16: -13015.68 | BQ16: 1972.25 | BR16: 3010.1 | BS16: 640690.58 | BU16: 3756000 | BV16: 4388657.2 | BW16: 4388657.2 | BY16: 8617 | BZ16: 23773.61 | CA16: 5000.19 | CD16: 37390.8 | CE16: 37390.8 | CF16: 837 | CG16: 482446.52 | CH16: 41.34 | CK16: 3749986 | CL16: 4233310.9 | CM16: 4233310.9 | CN16: 240938.72 | CO16: 51287.22 | CP16: 1810.97 | CQ16: 1550.2 | CT16: 295587.11 | CU16: 295587.11
B17: COSTO | C17: 1720570 | D17: 7329138 | E17: 15417299 | F17: 4824040 | G17: 3825592 | H17: 10358455 | J17: 43475094 | K17: 43475094 | L17: 1385741 | M17: 8538026 | N17: 14770146 | O17: 18554340 | P17: 10039129 | Q17: 17525571 | R17: 70812953 | S17: 70812953 | T17: 2647861 | U17: 8774320 | V17: 21417333 | W17: 18835761 | X17: 8410328 | Y17: 124094437 | Z17: 184180040 | AA17: 184180040 | AB17: 2186873 | AC17: 7696276 | AD17: 16521888 | AE17: 27910815 | AF17: 11615888 | AG17: 56803552 | AH17: 122735292 | AI17: 122735292 | AJ17: 2071758 | AK17: 10472560 | AL17: 39862184 | AM17: 26727012 | AN17: 40856680 | AO17: 100124342 | AP17: 2.2011454e+08 | AQ17: 2.2011454e+08 | AR17: 1719011 | AS17: 11308754 | AT17: 17603764 | AU17: 53056993 | AV17: 109351701 | AW17: 81953375 | AX17: 2.749936e+08 | AY17: 2.749936e+08 | AZ17: 4200013 | BA17: 10714108 | BB17: 20808812 | BC17: 27472857 | BD17: 71494978 | BE17: 78717307 | BF17: 2.1340808e+08 | BG17: 2.1340808e+08 | BH17: 4446181 | BI17: 8750840 | BJ17: 16279478 | BK17: 30604959 | BL17: 44475582 | BM17: 192786587 | BN17: 297343627 | BO17: 297343627 | BP17: 7403508 | BQ17: 26448456 | BR17: 19768785 | BS17: 36317892 | BT17: 60284881 | BU17: 189000011 | BV17: 339223533 | BW17: 339223533 | BX17: 6942464 | BY17: 23175424 | BZ17: 20156334 | CA17: 28872236 | CB17: 90750223 | CC17: 1.2471208e+08 | CD17: 2.9460876e+08 | CE17: 2.9460876e+08 | CF17: 6016979 | CG17: 15230915 | CH17: 21429897 | CI17: 68948897 | CJ17: 233524244 | CK17: 70497104 | CL17: 4.1564804e+08 | CM17: 4.1564804e+08 | CN17: 6279059 | CO17: 30801526 | CP17: 81442108 | CQ17: 199526388 | CR17: 2.5473029e+08 | CS17: 453631606 | CT17: 1.026411e+09 | CU17: 1.026411e+09
B18: COSTO DE VENTA | C18: 1720570 | D18: 7329138 | E18: 15417299 | F18: 4824040 | G18: 3825592 | H18: 10358455 | J18: 43475094 | K18: 43475094 | L18: 1385741 | M18: 8538026 | N18: 14770146 | O18: 18554340 | P18: 10039129 | Q18: 17525571 | R18: 70812953 | S18: 70812953 | T18: 2647861 | U18: 8774320 | V18: 21417333 | W18: 18835761 | X18: 8410328 | Y18: 124094437 | Z18: 184180040 | AA18: 184180040 | AB18: 2186873 | AC18: 7696276 | AD18: 16521888 | AE18: 27910815 | AF18: 11615888 | AG18: 56803552 | AH18: 122735292 | AI18: 122735292 | AJ18: 2071758 | AK18: 10472560 | AL18: 39862184 | AM18: 26727012 | AN18: 40856680 | AO18: 100124342 | AP18: 2.2011454e+08 | AQ18: 2.2011454e+08 | AR18: 1719011 | AS18: 11308754 | AT18: 17603764 | AU18: 53056993 | AV18: 109351701 | AW18: 81953375 | AX18: 2.749936e+08 | AY18: 2.749936e+08 | AZ18: 4200013 | BA18: 10714108 | BB18: 20808812 | BC18: 27472857 | BD18: 71494978 | BE18: 78717307 | BF18: 2.1340808e+08 | BG18: 2.1340808e+08 | BH18: 4446181 | BI18: 8750840 | BJ18: 16279478 | BK18: 30604959 | BL18: 44475582 | BM18: 192786587 | BN18: 297343627 | BO18: 297343627 | BP18: 7403508 | BQ18: 26448456 | BR18: 19768785 | BS18: 36317892 | BT18: 60284881 | BU18: 189000011 | BV18: 339223533 | BW18: 339223533 | BX18: 6942464 | BY18: 23175424 | BZ18: 20156334 | CA18: 28872236 | CB18: 90750223 | CC18: 1.2471208e+08 | CD18: 2.9460876e+08 | CE18: 2.9460876e+08 | CF18: 6016979 | CG18: 15230915 | CH18: 21429897 | CI18: 68948897 | CJ18: 233524244 | CK18: 70497104 | CL18: 4.1564804e+08 | CM18: 4.1564804e+08 | CN18: 6279059 | CO18: 30801526 | CP18: 81442108 | CQ18: 199526388 | CR18: 2.5473029e+08 | CS18: 453631606 | CT18: 1.026411e+09 | CU18: 1.026411e+09
B19: COMERCIO AL POR MAYOR Y AL POR MENOR | C19: 1720570 | D19: 5996138 | E19: 12951728 | F19: 2390410 | H19: 816000 | J19: 23874846 | K19: 23874846 | L19: 1078691 | M19: 6500386 | N19: 11214956 | O19: 14400940 | P19: 2203840 | Q19: 7482434 | R19: 42881247 | S19: 42881247 | T19: 2241361 | U19: 7539300 | V19: 18198382 | W19: 14861850 | X19: 1573000 | Y19: 116319223 | Z19: 160733116 | AA19: 160733116 | AB19: 1721773 | AC19: 6173632 | AD19: 13759720 | AE19: 24165036 | AF19: 3693141 | AG19: 43653522 | AH19: 93166824 | AI19: 93166824 | AJ19: 1736358 | AK19: 8599540 | AL19: 37150483 | AM19: 21807901 | AN19: 34215522 | AO19: 90876266 | AP19: 194386070 | AQ19: 194386070 | AR19: 1295611 | AS19: 8996364 | AT19: 14793165 | AU19: 47986980 | AV19: 99724403 | AW19: 72440976 | AX19: 2.452375e+08 | AY19: 2.452375e+08 | AZ19: 3654792 | BA19: 8595062 | BB19: 18279404 | BC19: 23020787 | BD19: 65131036 | BE19: 70433974 | BF19: 189115055 | BG19: 189115055 | BH19: 4267581 | BI19: 6676810 | BJ19: 13781838 | BK19: 25643459 | BL19: 40425918 | BM19: 178859515 | BN19: 269655121 | BO19: 269655121 | BP19: 6412408 | BQ19: 7833026 | BR19: 17049252 | BS19: 29082751 | BT19: 48344739 | BU19: 180808173 | BV19: 289530349 | BW19: 289530349 | BX19: 5773064 | BY19: 21466402 | BZ19: 17143484 | CA19: 23346391 | CB19: 80732240 | CC19: 1.1796683e+08 | CD19: 2.6642841e+08 | CE19: 2.6642841e+08 | CF19: 4730279 | CG19: 12740825 | CH19: 18823897 | CI19: 62604690 | CJ19: 76532273 | CK19: 63146243 | CL19: 238578207 | CM19: 238578207 | CN19: 4596659 | CO19: 10779616 | CP19: 47152852 | CQ19: 192308303 | CR19: 2.4578525e+08 | CS19: 444567253 | CT19: 9.4518993e+08 | CU19: 9.4518993e+08
B20: SERVICIOS | P20: 156000 | R20: 156000 | S20: 156000 | AF20: 120509 | AH20: 120509 | AI20: 120509 | AN20: 361527 | AP20: 361527 | AQ20: 361527 | BD20: 341400 | BF20: 341400 | BG20: 341400 | BL20: 238200 | BM20: 5521356 | BN20: 5759556 | BO20: 5759556 | CC20: 71000 | CD20: 71000 | CE20: 71000 | CJ20: 11000 | CL20: 11000 | CM20: 11000 | CQ20: 203000 | CT20: 203000 | CU20: 203000
B21: TRANSPORTE, ALMACENAMIENTO Y COMUNICACIONES | D21: 1333000 | E21: 2215571 | F21: 2433630 | G21: 2609152 | H21: 6991737 | J21: 15583090 | K21: 15583090 | L21: 307050 | M21: 2037640 | N21: 3205190 | O21: 4153400 | P21: 4510429 | Q21: 6626639 | R21: 20840348 | S21: 20840348 | T21: 406500 | U21: 1235020 | V21: 3218951 | W21: 3973911 | X21: 4753633 | Y21: 5635278 | Z21: 19223293 | AA21: 19223293 | AB21: 465100 | AC21: 1522644 | AD21: 2762168 | AE21: 3745779 | AF21: 4317463 | AG21: 10644957 | AH21: 23458111 | AI21: 23458111 | AJ21: 335400 | AK21: 1873020 | AL21: 2711701 | AM21: 4919111.2 | AN21: 4482611 | AO21: 6293583 | AP21: 20615426 | AQ21: 20615426 | AR21: 423400 | AS21: 2012390 | AT21: 2810599 | AU21: 5070013 | AV21: 7589973 | AW21: 6941375 | AX21: 24847750 | AY21: 24847750 | AZ21: 545221.01 | BA21: 2119046 | BB21: 2529408 | BC21: 4452070 | BD21: 4828162 | BE21: 5685370 | BF21: 20159277 | BG21: 20159277 | BH21: 178600 | BI21: 2074030 | BJ21: 2497640 | BK21: 4961500 | BL21: 2566639 | BM21: 6071364 | BN21: 18349773 | BO21: 18349773 | BP21: 991100 | BQ21: 2415430 | BR21: 2719533 | BS21: 7235141 | BT21: 9709432 | BU21: 5730418 | BV21: 28801054 | BW21: 28801054 | BX21: 1169400 | BY21: 1709023 | BZ21: 3012850 | CA21: 4370445 | CB21: 7372598 | CC21: 5012089 | CD21: 22646405 | CE21: 22646405 | CF21: 1286700 | CG21: 2490090 | CH21: 2606000 | CI21: 5002004.4 | CJ21: 6501401 | CK21: 5986578 | CL21: 23872773 | CM21: 23872773 | CN21: 1682400 | CO21: 2471910 | CP21: 4139256 | CQ21: 5887839 | CR21: 5841541 | CS21: 6732442 | CT21: 26755388 | CU21: 26755388
B22: OTRAS ACTIVIDADES DE SERVICIOS | E22: 250000 | J22: 250000 | K22: 250000 | N22: 350000 | R22: 350000 | S22: 350000 | AS22: 300000 | AX22: 300000 | AY22: 300000
B23: OTROS CULTIVOS AGRÍCOLAS | BQ23: 16200000 | BV23: 16200000 | BW23: 16200000 | CJ23: 148650000 | CL23: 148650000 | CM23: 148650000 | CO23: 17550000 | CP23: 30150000 | CT23: 47700000 | CU23: 47700000
B24: PROCESO LOGÍSTICO | G24: 1216440 | H24: 2550718 | J24: 3767158 | K24: 3767158 | P24: 3168860 | Q24: 3416498 | R24: 6585358 | S24: 6585358 | X24: 2083695 | Y24: 2139936 | Z24: 4223631 | AA24: 4223631 | AF24: 3484775 | AG24: 2505073 | AH24: 5989848 | AI24: 5989848 | AN24: 1797020 | AO24: 2954493 | AP24: 4751513 | AQ24: 4751513 | AV24: 2037325 | AW24: 2571024 | AX24: 4608349 | AY24: 4608349 | BD24: 1194380 | BE24: 2597963 | BF24: 3792343 | BG24: 3792343 | BL24: 1244825 | BM24: 2334352 | BN24: 3579177 | BO24: 3579177 | BT24: 2230710 | BU24: 2461420 | BV24: 4692130 | BW24: 4692130 | CA24: 1155400 | CB24: 2645385 | CC24: 1662159 | CD24: 5462944 | CE24: 5462944 | CI24: 1342203 | CJ24: 1829570 | CK24: 1364283 | CL24: 4536056 | CM24: 4536056 | CQ24: 1127246 | CR24: 3103500 | CS24: 2331911 | CT24: 6562657 | CU24: 6562657
B25: GASTO | C25: 4340392.4 | D25: 8946290.7 | E25: 22013624 | F25: 33420578 | G25: 56660714 | H25: 66256797 | J25: 1.916384e+08 | K25: 1.916384e+08 | L25: 4186227.2 | M25: 9269876.3 | N25: 22678114 | O25: 30457861 | P25: 56609633 | Q25: 93239392 | R25: 2.164411e+08 | S25: 2.164411e+08 | T25: 4029476.8 | U25: 10844930 | V25: 25148415 | W25: 32116422 | X25: 43650119 | Y25: 1.0050179e+08 | Z25: 2.1629115e+08 | AA25: 2.1629115e+08 | AB25: 4971716 | AC25: 10496310 | AD25: 36520631 | AE25: 29466618 | AF25: 64692637 | AG25: 1.2943372e+08 | AH25: 2.7558163e+08 | AI25: 2.7558163e+08 | AJ25: 4445828.1 | AK25: 15485752 | AL25: 28909976 | AM25: 30635012 | AN25: 57315262 | AO25: 1.0149466e+08 | AP25: 2.3828649e+08 | AQ25: 2.3828649e+08 | AR25: 4837217.1 | AS25: 12666305 | AT25: 27223221 | AU25: 31997575 | AV25: 46476266 | AW25: 95489782 | AX25: 2.1869037e+08 | AY25: 2.1869037e+08 | AZ25: 4678597 | BA25: 15765789 | BB25: 28393770 | BC25: 36323165 | BD25: 69918753 | BE25: 1.0822887e+08 | BF25: 2.6330894e+08 | BG25: 2.6330894e+08 | BH25: 6532458.3 | BI25: 15768191 | BJ25: 26067259 | BK25: 38979287 | BL25: 56649185 | BM25: 1.0118112e+08 | BN25: 2.451775e+08 | BO25: 2.451775e+08 | BP25: 6552389.8 | BQ25: 19151812 | BR25: 29978948 | BS25: 45202912 | BT25: 64320459 | BU25: 1.1155981e+08 | BV25: 2.7676633e+08 | BW25: 2.7676633e+08 | BX25: 7546999.3 | BY25: 23348832 | BZ25: 25961509 | CA25: 45799920 | CB25: 62094727 | CC25: 1.2492948e+08 | CD25: 2.8968147e+08 | CE25: 2.8968147e+08 | CF25: 7475477.7 | CG25: 21938239 | CH25: 28619243 | CI25: 39494544 | CJ25: 72777444 | CK25: 1.2567781e+08 | CL25: 2.9598275e+08 | CM25: 2.9598275e+08 | CN25: 8685189.4 | CO25: 23059577 | CP25: 28149265 | CQ25: 36261608 | CR25: 77162661 | CS25: 2.2921261e+08 | CT25: 4.0253091e+08 | CU25: 4.0253091e+08
B26: OPERACIONAL DE ADMINISTRACIÓN | C26: 4107892 | D26: 7756304 | E26: 17112607 | F26: 22890906 | G26: 35294968 | H26: 42863314 | J26: 1.3002599e+08 | K26: 1.3002599e+08 | L26: 3963989 | M26: 8451524 | N26: 16896726 | O26: 23345414 | P26: 42187508 | Q26: 52381600 | R26: 1.4722676e+08 | S26: 1.4722676e+08 | T26: 3583173 | U26: 9331949 | V26: 19745065 | W26: 24297939 | X26: 29726019 | Y26: 57091286 | Z26: 1.4377543e+08 | AA26: 1.4377543e+08 | AB26: 4283063 | AC26: 7499436 | AD26: 26586008 | AE26: 22663189 | AF26: 49477466 | AG26: 52758193 | AH26: 1.6326736e+08 | AI26: 1.6326736e+08 | AJ26: 3448580 | AK26: 12293882 | AL26: 22590079 | AM26: 23876009 | AN26: 40922939 | AO26: 66727437 | AP26: 1.6985893e+08 | AQ26: 1.6985893e+08 | AR26: 4299861 | AS26: 9228143 | AT26: 22504910 | AU26: 24760880 | AV26: 33111839 | AW26: 55591779 | AX26: 1.4949741e+08 | AY26: 1.4949741e+08 | AZ26: 4454349 | BA26: 12600952 | BB26: 21382859 | BC26: 23218108 | BD26: 49587785 | BE26: 73495749 | BF26: 1.847398e+08 | BG26: 1.847398e+08 | BH26: 5505483.3 | BI26: 12361064 | BJ26: 19580878 | BK26: 23430517 | BL26: 39840634 | BM26: 66835386 | BN26: 1.6755396e+08 | BO26: 1.6755396e+08 | BP26: 6006935 | BQ26: 16081747 | BR26: 24286086 | BS26: 31106723 | BT26: 42785299 | BU26: 77474956 | BV26: 1.9774175e+08 | BW26: 1.9774175e+08 | BX26: 6989143 | BY26: 18729601 | BZ26: 19745300 | CA26: 27191185 | CB26: 43985020 | CC26: 88911418 | CD26: 2.0555167e+08 | CE26: 2.0555167e+08 | CF26: 7137812 | CG26: 17267227 | CH26: 22845911 | CI26: 25306941 | CJ26: 52783232 | CK26: 85848369 | CL26: 2.1118949e+08 | CM26: 2.1118949e+08 | CN26: 8991604 | CO26: 18265234 | CP26: 22753013 | CQ26: 24175897 | CR26: 51590891 | CS26: 1.9111641e+08 | CT26: 3.1689305e+08 | CU26: 3.1689305e+08
B27: GASTOS DE PERSONAL | C27: 2589941 | D27: 5174554 | E27: 11268126 | F27: 15524513 | G27: 22878541 | H27: 26475050 | J27: 83910725 | K27: 83910725 | L27: 2589941 | M27: 5326554 | N27: 10824126 | O27: 14997730 | P27: 22843723 | Q27: 29505146 | R27: 86087220 | S27: 86087220 | T27: 1922513 | U27: 5166554 | V27: 10824126 | W27: 15379769 | X27: 21561511 | Y27: 27538918 | Z27: 82393391 | AA27: 82393391 | AB27: 1954413 | AC27: 5166554 | AD27: 13849577 | AE27: 16681173 | AF27: 25384851 | AG27: 22057508 | AH27: 85094076 | AI27: 85094076 | AJ27: 1836719 | AK27: 5166554 | AL27: 13876305 | AM27: 16161612 | AN27: 25853296 | AO27: 31859230 | AP27: 94753716 | AQ27: 94753716 | AR27: 1808119 | AS27: 5301554 | AT27: 13876305 | AU27: 17513281 | AV27: 22837745 | AW27: 27682835 | AX27: 89019839 | AY27: 89019839 | AZ27: 1922513 | BA27: 7344792 | BB27: 13876305 | BC27: 16444590 | BD27: 22613295 | BE27: 29413444 | BF27: 91614939 | BG27: 91614939 | BH27: 1922513 | BI27: 7366197 | BJ27: 13876305 | BK27: 16181173 | BL27: 22613295 | BM27: 33881432 | BN27: 95840915 | BO27: 95840915 | BP27: 3936350 | BQ27: 7380792 | BR27: 13876305 | BS27: 15203188 | BT27: 22051880 | BU27: 30854209 | BV27: 93302724 | BW27: 93302724 | BX27: 3936350 | BY27: 7380792 | BZ27: 13894972 | CA27: 15582766 | CB27: 24221442 | CC27: 42905877 | CD27: 107922199 | CE27: 107922199 | CF27: 3936350 | CG27: 9401383 | CH27: 13192783 | CI27: 13775188 | CJ27: 36416264 | CK27: 48992956 | CL27: 1.2571492e+08 | CM27: 1.2571492e+08 | CN27: 5166460 | CO27: 9401723 | CP27: 13630007 | CQ27: 14342150 | CR27: 25611670 | CS27: 137811176 | CT27: 2.0596319e+08 | CU27: 2.0596319e+08
B28: HONORARIOS | C28: 414058 | D28: 438902 | E28: 1906526 | F28: 600000 | G28: 1370000 | H28: 2768340 | J28: 7497826 | K28: 7497826 | L28: 414058 | M28: 438902 | N28: 1906526 | O28: 600000 | P28: 3900000 | Q28: 3849433 | R28: 11108919 | S28: 11108919 | T28: 414058 | U28: 438902 | V28: 1906526 | W28: 600000 | X28: 1600000 | Y28: 3646100 | Z28: 8605586 | AA28: 8605586 | AB28: 414058 | AC28: 438902 | AD28: 1906526 | AE28: 1200000 | AF28: 2644840 | AG28: 10896100 | AH28: 17500426 | AI28: 17500426 | AJ28: 414058 | AK28: 438902 | AL28: 2815052 | AM28: 2400000 | AN28: 2689680 | AO28: 5407100 | AP28: 14164792 | AQ28: 14164792 | AR28: 414058 | AS28: 877804 | AT28: 1598000 | AU28: 1200000 | AV28: 1344840 | AW28: 6368700 | AX28: 11803402 | AY28: 11803402 | AZ28: 828116 | BA28: 908526 | BB28: 1598000 | BC28: 1200000 | BD28: 9096195 | BE28: 7168284.8 | BF28: 20799122 | BG28: 20799122 | BH28: 414058 | BI28: 908526 | BJ28: 600000 | BK28: 1432000 | BL28: 9261340 | BM28: 5896100 | BN28: 18512024 | BO28: 18512024 | BP28: 414058 | BQ28: 908526 | BR28: 2200000 | BS28: 1200000 | BT28: 2644840 | BU28: 7903939 | BV28: 15271363 | BW28: 15271363 | BX28: 438902 | BY28: 2217052 | BZ28: 600000 | CA28: 1450000 | CB28: 3944840 | CC28: 3978900 | CD28: 12629694 | CE28: 12629694 | CF28: 878902 | CG28: 1544494 | CH28: 1598000 | CI28: 1200000 | CJ28: 3944840 | CK28: 6324234 | CL28: 15490470 | CM28: 15490470 | CN28: 879325 | CO28: 908526 | CP28: 1598000 | CQ28: 1200000 | CR28: 3944840 | CS28: 6294000 | CT28: 14824691 | CU28: 14824691
B29: IMPUESTOS | E29: 448 | F29: 79690 | G29: 20890 | H29: 83976 | J29: 185004 | K29: 185004 | N29: 35648 | O29: 81564 | P29: 44041 | Q29: 224203.71 | R29: 385456.71 | S29: 385456.71 | U29: 33900 | V29: 36248 | W29: 3857 | X29: 741 | Y29: 859986.52 | Z29: 934732.52 | AA29: 934732.52 | AD29: 70726 | AE29: 6227 | AF29: 103293.63 | AG29: 4737533.3 | AH29: 4917780 | AI29: 4917780 | AJ29: 0 | AL29: 448 | AM29: 40272 | AN29: 130676 | AO29: 96097.41 | AP29: 267493.41 | AQ29: 267493.41 | AR29: 50 | AT29: 116175 | AU29: 40972 | AV29: 887 | AW29: 74750.74 | AX29: 232834.74 | AY29: 232834.74 | BB29: 451 | BC29: 113145 | BD29: 23587 | BE29: 275792.84 | BF29: 412975.84 | BG29: 412975.84 | BH29: 100 | BJ29: 451 | BK29: 41038.07 | BL29: 47406 | BM29: 208013.86 | BN29: 297008.93 | BO29: 297008.93 | BQ29: 68000 | BR29: 36951 | BS29: 153138.07 | BT29: 89500 | BU29: 819681.32 | BV29: 1167270.4 | BW29: 1167270.4 | BY29: 91586 | BZ29: 36951 | CA29: 37629 | CB29: 109212.21 | CC29: 553721.66 | CD29: 829099.87 | CE29: 829099.87 | CG29: 448 | CH29: 72305 | CI29: 209722.82 | CJ29: 119370.3 | CK29: 220363.53 | CL29: 622209.65 | CM29: 622209.65 | CN29: 525578.29 | CO29: 34448 | CP29: 550 | CQ29: 4113 | CR29: 125483.57 | CS29: 439891.78 | CT29: 1130064.6 | CU29: 1130064.6
B30: ARRENDAMIENTOS | C30: 800000 | D30: 800000 | E30: 800000 | F30: 800000 | G30: 800000 | H30: 2500000 | J30: 6500000 | K30: 6500000 | L30: 800000 | M30: 800000 | N30: 800000 | O30: 800000 | Q30: 2300000 | R30: 5500000 | S30: 5500000 | T30: 800000 | U30: 800000 | V30: 800000 | W30: 800000 | Y30: 2300000 | Z30: 5500000 | AA30: 5500000 | AB30: 829016 | AC30: 800000 | AD30: 4050000 | AE30: 800000 | AG30: 2300000 | AH30: 8779016 | AI30: 8779016 | AJ30: 829000 | AK30: 800000 | AL30: 800000 | AM30: 800000 | AN30: 1686667 | AO30: 2300000 | AP30: 7215667 | AQ30: 7215667 | AR30: 829016 | AS30: 800000 | AT30: 800000 | AU30: 800000 | AW30: 2300000 | AX30: 5529016 | AY30: 5529016 | AZ30: 829016 | BA30: 800000 | BB30: 800000 | BC30: 800000 | BD30: 4600000 | BE30: 3827000 | BF30: 11656016 | BG30: 11656016 | BH30: 829016 | BI30: 800000 | BJ30: 800000 | BM30: 2300000 | BN30: 4729016 | BO30: 4729016 | BP30: 829016 | BQ30: 800000 | BR30: 800000 | BS30: 1600000 | BT30: 5014608 | BU30: 2300000 | BV30: 11343624 | BW30: 11343624 | BX30: 829016 | BY30: 800000 | BZ30: 800000 | CA30: 800000 | CB30: 2300000 | CC30: 4657600 | CD30: 10186616 | CE30: 10186616 | CF30: 829016 | CG30: 800000 | CH30: 1178375 | CI30: 800000 | CJ30: 2300000 | CK30: 2445189.9 | CL30: 8352580.9 | CM30: 8352580.9 | CN30: 829016 | CO30: 800000 | CP30: 800000 | CQ30: 800000 | CR30: 2300000 | CS30: 2500000 | CT30: 8029016 | CU30: 8029016
B31: SERVICIOS | C31: 117326 | D31: 1291248 | E31: 1895964 | F31: 3949001 | G31: 7000937.8 | H31: 2913052.8 | J31: 17167530 | K31: 17167530 | L31: 159990 | M31: 1723868 | N31: 2257235 | O31: 2787813 | P31: 8795098.2 | Q31: 5306790 | R31: 21030794 | S31: 21030794 | T31: 446602 | U31: 1548746 | V31: 2884051 | W31: 4780055 | X31: 3418810.2 | Y31: 8969429.8 | Z31: 22047694 | AA31: 22047694 | AB31: 159990 | AC31: 932160 | AD31: 4594987 | AE31: 2300218 | AF31: 10150197 | AG31: 7294973 | AH31: 25432525 | AI31: 25432525 | AJ31: 319980 | AK31: 1884224 | AL31: 4052264 | AM31: 2989684 | AN31: 7305754 | AO31: 15730959 | AP31: 32282865 | AQ31: 32282865 | AR31: 330332.94 | AS31: 1914179 | AT31: 3025182 | AU31: 3466064.8 | AV31: 4156298.2 | AW31: 9573067.4 | AX31: 22465124 | AY31: 22465124 | AZ31: 569980 | BA31: 2882072.3 | BB31: 3112505 | BC31: 3630081 | BD31: 4569082.1 | BE31: 12926391 | BF31: 27690111 | BG31: 27690111 | BH31: 470263 | BI31: 2510677 | BJ31: 3330102 | BK31: 3394289 | BL31: 5165386 | BM31: 12324700 | BN31: 27195417 | BO31: 27195417 | BP31: 827511 | BQ31: 4230480 | BR31: 3027193 | BS31: 7928266 | BT31: 6782761.3 | BU31: 16060611 | BV31: 38856822 | BW31: 38856822 | BX31: 1784875 | BY31: 3683097 | BZ31: 3566270 | CA31: 3676912.1 | CB31: 6650812.8 | CC31: 16793687 | CD31: 36155654 | CE31: 36155654 | CF31: 1493544 | CG31: 1986085 | CH31: 3755225 | CI31: 4867997.1 | CJ31: 4327220 | CK31: 18594586 | CL31: 35024657 | CM31: 35024657 | CN31: 1591224.7 | CO31: 2290418 | CP31: 3296151 | CQ31: 1752975.4 | CR31: 6086177.8 | CS31: 21915064 | CT31: 36932011 | CU31: 36932011
B32: DIVERSOS | C32: 186567 | D32: 51600 | E32: 638836.89 | F32: 660983.73 | G32: 1546191.2 | H32: 4408977.8 | J32: 7493156.6 | K32: 7493156.6 | M32: 156000 | N32: 783890.85 | O32: 2211453.5 | P32: 6029651.7 | Q32: 7198308.2 | R32: 16379304 | S32: 16379304 | U32: 480725 | V32: 1436113.8 | W32: 1103865 | X32: 1149127 | Y32: 4233502 | Z32: 8403332.8 | AA32: 8403332.8 | AB32: 904578 | AC32: 161820 | AD32: 1439792.2 | AE32: 812903 | AF32: 6342182.8 | AG32: 4236705.6 | AH32: 13897982 | AI32: 13897982 | AJ32: 48823 | AK32: 4201.7 | AL32: 1046010.5 | AM32: 692641.48 | AN32: 1868894.3 | AO32: 8734534.5 | AP32: 12395106 | AQ32: 12395106 | AR32: 515085.08 | AS32: 334606.04 | AT32: 1864748.4 | AU32: 638861.89 | AV32: 1542509 | AW32: 8182607.8 | AX32: 13078418 | AY32: 13078418 | AZ32: 304724 | BA32: 665562 | BB32: 1995597.9 | BC32: 500692 | BD32: 4197132.5 | BE32: 14932400 | BF32: 22596108 | BG32: 22596108 | BH32: 309533.33 | BI32: 525664 | BJ32: 974020.15 | BK32: 687417 | BL32: 2439277.5 | BM32: 9835308.1 | BN32: 14771220 | BO32: 14771220 | BQ32: 1976149 | BR32: 1625037.1 | BS32: 3013152 | BT32: 4029740.3 | BU32: 10405297 | BV32: 21049375 | BW32: 21049375 | BY32: 2017580 | BZ32: 355107.02 | CA32: 2184127 | CB32: 4425351.5 | CC32: 11262161 | CD32: 20244327 | CE32: 20244327 | CG32: 2729836 | CH32: 1592523.1 | CI32: 3072202 | CJ32: 3624131.3 | CK32: 6431283 | CL32: 17449975 | CM32: 17449975 | CO32: 2173189 | CP32: 1727270.9 | CQ32: 2319596 | CR32: 7591464.1 | CS32: 12481776 | CT32: 26293296 | CU32: 26293296
B33: LEGALES | M33: 6200 | N33: 6500 | R33: 12700 | S33: 12700 | U33: 546000 | V33: 780000 | W33: 759200 | X33: 1901900 | Y33: 2175100 | Z33: 6162200 | AA33: 6162200 | AR33: 403200 | AV33: 2155462.2 | AX33: 2558662.2 | AY33: 2558662.2 | BD33: 2155462.2 | BF33: 2155462.2 | BG33: 2155462.2 | BI33: 250000 | BL33: 150000 | BN33: 400000 | BO33: 400000 | BR33: 110000 | BU33: 3300469 | BV33: 3410469 | BW33: 3410469 | CJ33: 1587800 | CL33: 1587800 | CM33: 1587800 | CR33: 239100 | CT33: 239100 | CU33: 239100
B34: GASTOS DE VIAJE | F34: 1276718 | G34: 394051 | H34: 1098570 | J34: 2769339 | K34: 2769339 | N34: 282800 | O34: 1160720 | P34: 332600 | Q34: 1572800 | R34: 3348920 | S34: 3348920 | U34: 317122 | V34: 798000 | W34: 495000 | Y34: 6717877 | Z34: 8327999 | AA34: 8327999 | AD34: 674400 | AF34: 4808171.7 | AG34: 625000 | AH34: 6107571.7 | AI34: 6107571.7 | AM34: 791800 | AN34: 1037559 | AO34: 1191900 | AP34: 3021259 | AQ34: 3021259 | AT34: 1224500 | AU34: 876600 | AV34: 610000 | AW34: 544908.08 | AX34: 3256008.1 | AY34: 3256008.1 | BC34: 401200 | BD34: 389101 | BE34: 1510300 | BF34: 2300601 | BG34: 2300601 | BK34: 1694600 | BM34: 1689460 | BN34: 3384060 | BO34: 3384060 | BQ34: 717800 | BR34: 867000 | BS34: 1595049 | BT34: 1989930 | BU34: 3017899 | BV34: 8187678 | BW34: 8187678 | BY34: 847494 | BZ34: 492000 | CA34: 2149751 | CB34: 2118355.8 | CC34: 4670498 | CD34: 10278099 | CE34: 10278099 | CG34: 86000 | CH34: 1456700 | CI34: 1337901 | CJ34: 415600 | CK34: 1946905 | CL34: 5243106 | CM34: 5243106 | CO34: 527600 | CQ34: 115000 | CR34: 460000 | CS34: 2340562 | CT34: 3443162 | CU34: 3443162
B35: MANTENIMIENTO Y REPARACION | E35: 602706 | G35: 1210427 | H35: 2004974.8 | J35: 3818107.8 | K35: 3818107.8 | O35: 706134 | P35: 112676 | Q35: 1814546.2 | R35: 2633356.2 | S35: 2633356.2 | V35: 280000 | W35: 196218 | Y35: 40000 | Z35: 516218 | AA35: 516218 | AB35: 21008 | AE35: 862668 | AH35: 883676 | AI35: 883676 | AK35: 4000000 | AN35: 256483 | AO35: 677244 | AP35: 4933727 | AQ35: 4933727 | AU35: 225100 | AW35: 174537.81 | AX35: 399637.81 | AY35: 399637.81 | BC35: 128400 | BD35: 1800000 | BE35: 2831764.7 | BF35: 4760164.7 | BG35: 4760164.7 | BL35: 120000 | BN35: 120000 | BO35: 120000 | BT35: 134033.61 | BU35: 2200000 | BV35: 2334033.6 | BW35: 2334033.6 | CA35: 1310000 | CB35: 167000 | CC35: 3476121 | CD35: 4953121 | CE35: 4953121 | CG35: 718981 | CK35: 280000 | CL35: 998981 | CM35: 998981 | CO35: 2129330 | CR35: 3446722.7 | CS35: 6721087 | CT35: 12297140 | CU35: 12297140
B36: AMORTIZACIONES | BH36: 1560000 | BN36: 1560000 | BO36: 1560000 | BR36: 1743600 | BV36: 1743600 | BW36: 1743600 | BY36: 1692000 | CD36: 1692000 | CE36: 1692000 | CP36: 736667 | CQ36: 1258333 | CT36: 1995000 | CU36: 1995000
B37: DEPRECIACIÓN | G37: 30000 | H37: 562366.58 | J37: 592366.58 | K37: 592366.58 | Q37: 562366.58 | R37: 562366.58 | S37: 562366.58 | X37: 50000 | Y37: 562366.58 | Z37: 612366.58 | AA37: 612366.58 | AG37: 562366.58 | AH37: 562366.58 | AI37: 562366.58 | AO37: 562366.58 | AP37: 562366.58 | AQ37: 562366.58 | AW37: 562366.58 | AX37: 562366.58 | AY37: 562366.58 | BD37: 100000 | BE37: 562366.58 | BF37: 662366.58 | BG37: 662366.58 | BM37: 652366.58 | BN37: 652366.58 | BO37: 652366.58 | BS37: 370000 | BU37: 562366.58 | BV37: 932366.58 | BW37: 932366.58 | CC37: 562366.58 | CD37: 562366.58 | CE37: 562366.58 | CK37: 562366.58 | CL37: 562366.58 | CM37: 562366.58 | CP37: 964367 | CQ37: 1774001 | CR37: 1737425.9 | CS37: 562366.58 | CT37: 5038160.5 | CU37: 5038160.5
B38: ARREGLOS ORNAMENTALES | W38: 179974.79 | Z38: 179974.79 | AA38: 179974.79 | AO38: 120000 | AP38: 120000 | AQ38: 120000 | AV38: 420168 | AW38: 80000 | AX38: 500168 | AY38: 500168
B39: SEGUROS | G39: 43930 | H39: 48006 | J39: 91936 | K39: 91936 | P39: 43930 | Q39: 48006 | R39: 91936 | S39: 91936 | X39: 43930 | Y39: 48006 | Z39: 91936 | AA39: 91936 | AF39: 43930 | AG39: 48006 | AH39: 91936 | AI39: 91936 | AN39: 43930 | AO39: 48006 | AP39: 91936 | AQ39: 91936 | AV39: 43930 | AW39: 48006 | AX39: 91936 | AY39: 91936 | BD39: 43930 | BE39: 48006 | BF39: 91936 | BG39: 91936 | BL39: 43930 | BM39: 48006 | BN39: 91936 | BO39: 91936 | BS39: 43930 | BT39: 48006 | BU39: 50485 | BV39: 142421 | BW39: 142421 | CB39: 48006 | CC39: 50485 | CD39: 98491 | CE39: 98491 | CI39: 43930 | CJ39: 48006 | CK39: 50485 | CL39: 142421 | CM39: 142421 | CQ39: 43930 | CR39: 48006 | CS39: 50485 | CT39: 142421 | CU39: 142421
B40: REPARACIONES LOCATIVAS | P40: 85787.4 | R40: 85787.4 | S40: 85787.4 | AN40: 50000 | AP40: 50000 | AQ40: 50000 | CQ40: 565798.32 | CT40: 565798.32 | CU40: 565798.32
B41: GASTOS DE VENTAS | E41: 3904979 | F41: 8531743 | G41: 19514472 | H41: 18390404 | J41: 50341598 | K41: 50341598 | N41: 3904979 | O41: 5611726 | P41: 12637231 | Q41: 34152832 | R41: 56306768 | S41: 56306768 | V41: 3904979 | W41: 5611726 | X41: 12013481 | Y41: 33246181 | Z41: 54776367 | AA41: 54776367 | AC41: 2200591 | AD41: 7216821 | AE41: 5565726 | AF41: 12867342 | AG41: 64082621 | AH41: 91933101 | AI41: 91933101 | AK41: 2200591 | AL41: 3904977.3 | AM41: 4347619 | AN41: 13959132 | AO41: 30339943 | AP41: 54752262 | AQ41: 54752262 | AS41: 2618770 | AT41: 3904977.3 | AU41: 5291266 | AV41: 9579646 | AW41: 32919181 | AX41: 54313840 | AY41: 54313840 | BA41: 2458917 | BB41: 4980660 | BC41: 11177430 | BD41: 9934646 | BE41: 31869181 | BF41: 60420834 | BG41: 60420834 | BI41: 2714610 | BJ41: 5030660 | BK41: 11957476 | BL41: 9934646 | BM41: 31342570 | BN41: 60979962 | BO41: 60979962 | BQ41: 2200591 | BR41: 4512102 | BS41: 11957404 | BT41: 17383312 | BU41: 30868893 | BV41: 66922302 | BW41: 66922302 | BY41: 2977750 | BZ41: 5185160 | CA41: 13615331 | CB41: 12739614 | CC41: 31181326 | CD41: 65699181 | CE41: 65699181 | CG41: 3947107 | CH41: 5186082 | CI41: 11957404 | CJ41: 15642264 | CK41: 36555390 | CL41: 73288247 | CM41: 73288247 | CO41: 3875107 | CP41: 5186500 | CQ41: 10649985 | CR41: 18971306 | CS41: 33918684 | CT41: 72601582 | CU41: 72601582
B42: GASTOS DE PERSONAL | E42: 3904979 | F42: 8531743 | G42: 19514472 | H42: 18390404 | J42: 50341598 | K42: 50341598 | N42: 3904979 | O42: 5611726 | P42: 12637231 | Q42: 34152832 | R42: 56306768 | S42: 56306768 | V42: 3904979 | W42: 5611726 | X42: 12013481 | Y42: 33246181 | Z42: 54776367 | AA42: 54776367 | AC42: 2200591 | AD42: 7216821 | AE42: 5565726 | AF42: 12867342 | AG42: 64082621 | AH42: 91933101 | AI42: 91933101 | AK42: 2200591 | AL42: 3904977.3 | AM42: 4347619 | AN42: 13959132 | AO42: 30339943 | AP42: 54752262 | AQ42: 54752262 | AS42: 2315375 | AT42: 3904977.3 | AU42: 5291266 | AV42: 9579646 | AW42: 32919181 | AX42: 54010445 | AY42: 54010445 | BA42: 2458917 | BB42: 4980660 | BC42: 11177430 | BD42: 9934646 | BE42: 31869181 | BF42: 60420834 | BG42: 60420834 | BI42: 2714610 | BJ42: 5030660 | BK42: 11957476 | BL42: 9934646 | BM42: 31342570 | BN42: 60979962 | BO42: 60979962 | BQ42: 2200591 | BR42: 4512102 | BS42: 11957404 | BT42: 14366812 | BU42: 30868893 | BV42: 63905802 | BW42: 63905802 | BY42: 2977750 | BZ42: 5185160 | CA42: 13615331 | CB42: 9723114 | CC42: 31181326 | CD42: 62682681 | CE42: 62682681 | CG42: 3947107 | CH42: 5186082 | CI42: 11957404 | CJ42: 10059546 | CK42: 36555390 | CL42: 67705529 | CM42: 67705529 | CO42: 3875107 | CP42: 5186500 | CQ42: 10649985 | CR42: 18971306 | CS42: 33918684 | CT42: 72601582 | CU42: 72601582
B43: SERVICIOS | BT43: 3016500 | BV43: 3016500 | BW43: 3016500 | CB43: 3016500 | CD43: 3016500 | CE43: 3016500 | CJ43: 3082718 | CL43: 3082718 | CM43: 3082718
B44: DIVERSOS | AS44: 303395 | AX44: 303395 | AY44: 303395 | CJ44: 2500000 | CL44: 2500000 | CM44: 2500000
B45: NO OPERACIONALES | C45: 232500.36 | D45: 1189986.7 | E45: 996037.84 | F45: 1997929.3 | G45: 1851273.5 | H45: 5003079.3 | J45: 11270807 | K45: 11270807 | L45: 222238.23 | M45: 818352.26 | N45: 1876409 | O45: 1500720.2 | P45: 1784894.8 | Q45: 6704960 | R45: 12907575 | S45: 12907575 | T45: 446303.83 | U45: 1512980.7 | V45: 1498371 | W45: 2206757.3 | X45: 1910618.4 | Y45: 10164319 | Z45: 17739350 | AA45: 17739350 | AB45: 688653 | AC45: 796283.17 | AD45: 2717802 | AE45: 1237703 | AF45: 2347828.7 | AG45: 12592905 | AH45: 20381175 | AI45: 20381175 | AJ45: 997248.11 | AK45: 991279.58 | AL45: 2414919 | AM45: 2411383.2 | AN45: 2433190.7 | AO45: 4427278.9 | AP45: 13675299 | AQ45: 13675299 | AR45: 537356.08 | AS45: 819391.95 | AT45: 813333.11 | AU45: 1945429.4 | AV45: 3784780.3 | AW45: 6978821.3 | AX45: 14879112 | AY45: 14879112 | AZ45: 224248.02 | BA45: 705919.79 | BB45: 2030251 | BC45: 1927626.9 | BD45: 10396322 | BE45: 2863937.8 | BF45: 18148305 | BG45: 18148305 | BH45: 1026975 | BI45: 692516.72 | BJ45: 1455721 | BK45: 3591294.2 | BL45: 6873904.8 | BM45: 3003166.6 | BN45: 16643578 | BO45: 16643578 | BP45: 545454.8 | BQ45: 869474.06 | BR45: 1180759.7 | BS45: 2138784.6 | BT45: 4151847.8 | BU45: 3215962 | BV45: 12102283 | BW45: 12102283 | BX45: 557856.29 | BY45: 1641480.6 | BZ45: 1031049.2 | CA45: 4993403.6 | CB45: 5370092.3 | CC45: 4836737.7 | CD45: 18430620 | CE45: 18430620 | CF45: 337665.67 | CG45: 723904.98 | CH45: 587249.82 | CI45: 2230198.8 | CJ45: 4351948.2 | CK45: 3274047.7 | CL45: 11505015 | CM45: 11505015 | CN45: -306414.62 | CO45: 919236.38 | CP45: 209751.72 | CQ45: 1435726.6 | CR45: 6600464.9 | CS45: 4177518.8 | CT45: 13036284 | CU45: 13036284
B46: FINANCIEROS | C46: 211891.28 | D46: 233021 | E46: 419436 | F46: 571064.72 | G46: 909356.75 | H46: 2762425.8 | J46: 5107195.6 | K46: 5107195.6 | L46: 169687.2 | M46: 672371.49 | N46: 780486 | O46: 774505 | P46: 1114184.7 | Q46: 3804201 | R46: 7315435.4 | S46: 7315435.4 | T46: 310043.8 | U46: 537429.37 | V46: 619587 | W46: 751522.34 | X46: 1137934.6 | Y46: 8142384.4 | Z46: 11498901 | AA46: 11498901 | AB46: 98218 | AC46: 260563.78 | AD46: 699059 | AE46: 656085 | AF46: 1283879.5 | AG46: 11575054 | AH46: 14572859 | AI46: 14572859 | AJ46: 329379.55 | AK46: 685925.48 | AL46: 1072497.8 | AM46: 1127882.2 | AN46: 1106974 | AO46: 1684535 | AP46: 6007194 | AQ46: 6007194 | AR46: 193651.05 | AS46: 642437.32 | AT46: 561806.09 | AU46: 946404 | AV46: 3016887.6 | AW46: 1623165 | AX46: 6984351.1 | AY46: 6984351.1 | AZ46: 176537.8 | BA46: 143366.22 | BB46: 648006.73 | BC46: 901263.54 | BD46: 5311077 | BE46: 1762992 | BF46: 8943243.3 | BG46: 8943243.3 | BH46: 144237.45 | BI46: 284796.48 | BJ46: 694195.15 | BK46: 983762.21 | BL46: 5790346 | BM46: 1574928 | BN46: 9472265.3 | BO46: 9472265.3 | BP46: 436134.64 | BQ46: 302708 | BR46: 838462.15 | BS46: 910403.67 | BT46: 3113592.7 | BU46: 1497319 | BV46: 7098620.1 | BW46: 7098620.1 | BX46: 467944.53 | BY46: 484738 | BZ46: 771101.5 | CA46: 1077307.8 | CB46: 4616801.8 | CC46: 3258660 | CD46: 10676554 | CE46: 10676554 | CF46: 180163.96 | CG46: 486471 | CH46: 194072.47 | CI46: 1243857 | CJ46: 3294552.7 | CK46: 1952014.2 | CL46: 7351131.4 | CM46: 7351131.4 | CN46: 168171.18 | CO46: 487222 | CP46: 750703.78 | CQ46: 952137.73 | CR46: 2303075.9 | CS46: 2031791.4 | CT46: 6693101.9 | CU46: 6693101.9
B47: EXTRAORDINARIOS | C47: 20609.08 | D47: 956965.7 | E47: 576601.84 | F47: 1426864.6 | G47: 941916.8 | H47: 2240653.5 | J47: 6163611.5 | K47: 6163611.5 | L47: 52551.03 | M47: 145980.77 | N47: 1095923 | O47: 726215.25 | P47: 670710.11 | Q47: 841759.01 | R47: 3533139.2 | S47: 3533139.2 | T47: 136260.03 | U47: 975551.33 | V47: 878784 | W47: 1455235 | X47: 772683.77 | Y47: 2021934.4 | Z47: 6240448.6 | AA47: 6240448.6 | AB47: 590435 | AC47: 535719.39 | AD47: 2018743 | AE47: 581618 | AF47: 1063949.2 | AG47: 1017851.5 | AH47: 5808316.1 | AI47: 5808316.1 | AJ47: 667868.56 | AK47: 305354.1 | AL47: 1342421.2 | AM47: 1283501 | AN47: 1326216.7 | AO47: 2742743.9 | AP47: 7668105.5 | AQ47: 7668105.5 | AR47: 343705.03 | AS47: 176954.63 | AT47: 251527.02 | AU47: 999025.4 | AV47: 767892.61 | AW47: 5355656.3 | AX47: 7894761 | AY47: 7894761 | AZ47: 47710.22 | BA47: 562553.57 | BB47: 1382244.3 | BC47: 1026363.3 | BD47: 5085244.9 | BE47: 1100945.8 | BF47: 9205062.1 | BG47: 9205062.1 | BH47: 882737.52 | BI47: 407720.24 | BJ47: 761525.88 | BK47: 2607532 | BL47: 1083558.8 | BM47: 1428238.6 | BN47: 7171313 | BO47: 7171313 | BP47: 109320.16 | BQ47: 566766.06 | BR47: 342297.53 | BS47: 1228380.9 | BT47: 1038255.1 | BU47: 1718643 | BV47: 5003662.8 | BW47: 5003662.8 | BX47: 89911.76 | BY47: 1156742.6 | BZ47: 259947.74 | CA47: 3916095.8 | CB47: 753290.57 | CC47: 1578077.7 | CD47: 7754066.2 | CE47: 7754066.2 | CF47: 157501.71 | CG47: 237433.98 | CH47: 393177.35 | CI47: 986341.81 | CJ47: 1057395.5 | CK47: 1322033.4 | CL47: 4153883.8 | CM47: 4153883.8 | CN47: -474585.8 | CO47: 432014.38 | CP47: -540952.06 | CQ47: 483588.9 | CR47: 4297389.1 | CS47: 2145727.5 | CT47: 6343181.9 | CU47: 6343181.9
B48: DIVERSOS | Q48: 2059000 | R48: 2059000 | S48: 2059000
B49: IMPUESTO DE RENTA Y COMPLEMENTARIOS
B50: IMPUESTO DE RENTA Y COMPLEMENTARIOS
B51: IMPUESTO DE RENTA Y COMPLEMENTARIOS | CN51: 3691000 | CO51: 9038000 | CP51: 18712000 | CQ51: 56184190 | CR51: 85705000 | CS51: 1.4795555e+08 | CT51: 3.2128574e+08 | CU51: 3.2128574e+08
B52: IMPUESTO DE RENTA Y COMPLEMENTARIOS | CN52: 3691000 | CO52: 9038000 | CP52: 18712000 | CQ52: 56184190 | CR52: 85705000 | CS52: 1.4795555e+08 | CT52: 3.2128574e+08 | CU52: 3.2128574e+08
B53: IMPUESTO DE RENTA Y COMPLEMENTARIOS | CN53: 3691000 | CO53: 9038000 | CP53: 18712000 | CQ53: 56184190 | CR53: 85705000 | CT53: 173330190 | CU53: 173330190
B54: VIGENCIA CORRIENTE | CS54: 1.4795555e+08 | CT54: 1.4795555e+08 | CU54: 1.4795555e+08
B55: RENTA | CS55: 1.4795555e+08 | CT55: 1.4795555e+08 | CU55: 1.4795555e+08
B56: INGRESOS | I56: 1.9304348e+08 | J56: 1.9304348e+08 | K56: 1.9304348e+08
B57: OPERACIONALES | I57: 1.9304348e+08 | J57: 1.9304348e+08 | K57: 1.9304348e+08
B58: SERVICIOS | I58: 201680.64 | J58: 201680.64 | K58: 201680.64
B59: COMERCIO AL POR MAYOR Y AL DETAL | I59: 2.200697e+08 | J59: 2.200697e+08 | K59: 2.200697e+08
B60: 41350101 - Comercio al por mayor y al detal | I60: 2.200697e+08 | J60: 2.200697e+08 | K60: 2.200697e+08
B61: DEVOLUCION EN VENTA | I61: -26222276 | J61: -26222276 | K61: -26222276
B62: 41750501 - Devolución en ventas | I62: -26213872 | J62: -26213872 | K62: -26213872
B63: 41750502 - Devolución en servicios | I63: -8403.36 | J63: -8403.36 | K63: -8403.36
B64: DESCUENTO EN SERVICIOS | I64: -1005622 | J64: -1005622 | K64: -1005622
B65: 41800102 - Descuentos en servicios | I65: -1005622 | J65: -1005622 | K65: -1005622
B66: GASTOS | I66: 1.3321094e+08 | J66: 1.3321094e+08 | K66: 1.3321094e+08
B67: NO OPERACIONALES | I67: 4944496.1 | J67: 4944496.1 | K67: 4944496.1
... B101: 614525 - Proceso logístico | I101: 2834010 | J101: 2834010 | K101: 2834010
B121: UTILIDAD Y/O PÉRDIDA | C121: =+C9 -> -29785.18 | D121: =+D9 -> 7291266 | E121: =+E9 -> 8312002.3 | F121: =+F9 -> 33114195 | G121: =+G9 -> 25384477 | H121: =+H9 -> 2.441081e+08 | I121: =+I9 -> 0 | J121: =+J9 -> 3.1818026e+08 | ... CT121: =+CT9 -> -6.1326093e+08
B122: MARGEN NETO | C122: =+C121/C15 -> -0.0049927017 | D122: =+D121/D15 -> 0.30939994 | E122: =+E121/E15 -> 0.18172457 | F122: =+F121/F15 -> 0.46405195 | G122: =+G121/G15 -> 0.30013426 | H122: =+H121/H15 -> 0.76111733 | I122: =+I121/I15 -> #DIV/0! | J122: =+J121/J15 -> 0.57648622 | ... CT122: =+CT121/CT15 -> -0.75211177

Sheet ESTIMADO CIERRE 2023
B1: =1160000*11.24% -> 130384 | C1: =+B1+1160000 -> 1290384 | D1: =+C1*13 -> 16774992 | H1: COSTO 46%
C3: 55760000 | D3: UNIAGRO | E3: =+C3/2 -> 27880000 | F3: =29240000+29750000+30000000 -> 88990000 | G3: =+E8-F3 -> #REF!
K4: ICA
C5: RENTA | F5: IVA 3 CUAT
B6: INGRESOS | C6: =+GETPIVOTDATA("VALOR",'E.R. PPTO - REAL'!$S$11,"CLASE","INGRESO") -> #REF! | D6: ENE-SEPT | F6: =309756699+C8 -> 475456699 | G6: INGRESOS | H6: 112604188 | I6: SEPTIEMBRE
C7: 197152511 | D7: OCT-NOV | F7: =+F6*19% -> 90336773 | G7: GENERADO | H7: =+C7 -> 197152511 | I7: =+D7 -> OCT-NOV
C8: =160700000+5000000 -> 165700000 | D8: DICIEMBRE | E8: =+C9*7.85% -> #REF! | F8: -18605395 | G8: DESCONTABLES | H8: =+C8 -> 165700000 | I8: =+D8 -> DICIEMBRE
A9: =+(C9/B9)-1 -> #REF! | B9: 663000000 | C9: =SUM(C6:C8) -> #REF! | D9: 65000000 | E9: =+D9/C9 -> #REF! | F9: -5816000 | H9: =SUM(H6:H8) -> 475456699 | K9: =+C9*3.3/1000 -> #REF!
C10: =(((+C6+C7+C8)*33%)+C3)+62000000 -> #REF! | D10: COSTO 43% | E10: =+C10/C9 -> #REF! | F10: =SUM(F7:F9) -> 65915378 | G10: IVA A PAGAR | K10: -821000 | L10: RETEICA
C11: =+(C9*42%)+10000000 -> #REF! | D11: GASTO 42% | E11: =+C7+C8 -> 362852511 | K11: =SUM(K9:K10) -> #REF! | L11: A PAGAR
A12: 28878975 | B12: =+C12/C9 -> #REF! | C12: =+C9-C10-C11 -> #REF! | D12: UTILIDAD OPER | E12: =+D25/E11 -> #REF!
A13: =+(C12/A12)-1 -> #REF! | D13: =+C9*4.35% -> #REF!
C14: =+C12*35% -> #REF! | D14: IMPUESTO 35% | F14: ANTICIPO 1 | J14: ANTICIPO 2
C15: =-((10545000)/11)*12 -> -11503636 | D15: RETENCIONES | F15: IMPT 2022 | G15: 19327000 | J15: IMPT 2022 | K15: 19327000
C16: =-((3815000)/10)*12 -> -4578000 | D16: AUTORRENTA | F16: IMPT 2023 | G16: =+C14 -> #REF! | H16: =+G16*75% -> #REF! | J16: IMPT 2023 | K16: =+C14 -> #REF!
C17: =SUM(C14:C16) -> #REF! | D17: IMP DESP RETENC | H17: =+C15+C16 -> -16081636 | K17: =+(K15+K16)/2 -> #REF!
C18: =+H18 -> #REF! | D18: ANTICIPO | H18: =SUM(H16:H17) -> #REF! | K18: =+C15-C16 -> -6925636.4
C19: =+C17+C18 -> #REF! | D19: TOTAL A PAGAR | K19: =SUM(K17:K18) -> #REF!
C20: =+C19/2 -> #REF! | D20: 2 CUOTAS | F20: =+C9*3.3/1000 -> #REF! | G20: ICA 2023
C22: =+GETPIVOTDATA("VALOR",'E.R. PPTO - REAL'!$S$11,"MES","SEPTIEMBRE","CLASE","INGRESO","GRUPO","INGRESO OPERACIONAL")+'PROYECCION IMP (2)'!C7+'PROYECCION IMP (2)'!C8 -> #REF! | D22: =+C22/4 -> #REF! | F22: 39000000 | G22: FE1120 FITOBIOCELL | I22: =(15970-4000)*4900.15 -> 58654795
D23: =+D22*39% -> #REF! | F23: 17700000 | G23: FE11510
D24: =122462000-D23 -> #REF! | F24: 3800000 | G24: FE11497
D25: =+D24+D23 -> #REF! | F25: 97162192
F26: =120000000-F25 -> 22837808 | G26: INV OCT
D27: =10588*8700 -> 92115600 | F27: 67000000
D28: =+D27*42% -> 38688552 | F28: =+F26+F25 -> 120000000
D29: =+D25+D28 -> #REF! | E29: =+D29-D28 -> #REF!
D30: =+D29+F24 -> #REF!

Sheet PROYECCION IMP (2)
H1: COSTO 46%
C3: 55760000 | D3: UNIAGRO | E3: =+C3/2 -> 27880000 | F3: =29240000+29750000 -> 58990000 | G3: =+E8-F3 -> #REF!
K4: ICA
C5: RENTA | F5: IVA 3 CUAT
B6: INGRESOS | C6: =+GETPIVOTDATA("VALOR",'E.R. PPTO - REAL'!$S$11,"CLASE","INGRESO") -> #REF! | D6: ENE-SEPT | F6: =309756699+C8 -> 4.9702082e+08 | G6: INGRESOS | H6: 112604188 | I6: SEPTIEMBRE
C7: 197152511 | D7: OCT-NOV | F7: =+F6*19% -> 94433956 | G7: GENERADO | H7: =+C7 -> 197152511 | I7: =+D7 -> OCT-NOV
C8: =98524122.8235+(10200*8700) -> 1.8726412e+08 | D8: DICIEMBRE | E8: =+C9*7.85% -> #REF! | F8: -18605395 | G8: DESCONTABLES | H8: =+C8 -> 1.8726412e+08 | I8: =+D8 -> DICIEMBRE
C9: =SUM(C6:C8) -> #REF! | D9: 65000000 | E9: =+D9/C9 -> #REF! | F9: -5816000 | H9: =SUM(H6:H8) -> 4.9702082e+08 | K9: =+C9*3.3/1000 -> #REF!
C10: =((+C6+C7+C8)*33%)+C3+107000000 -> #REF! | D10: COSTO 43% | E10: =+C10/C9 -> #REF! | F10: =SUM(F7:F9) -> 70012561 | G10: IVA A PAGAR | K10: -821000 | L10: RETEICA
C11: =+C9*42% -> #REF! | D11: GASTO 42% | E11: =+C7+C8 -> 3.8441663e+08 | K11: =SUM(K9:K10) -> #REF! | L11: A PAGAR
C12: =+C9-C10-C11 -> #REF! | D12: UTILIDAD OPER | E12: =+D25/E11 -> #REF!
C14: =+C12*35% -> #REF! | D14: IMPUESTO 35% | F14: ANTICIPO 1 | J14: ANTICIPO 2
C15: =-((10545000)/11)*12 -> -11503636 | D15: RETENCIONES | F15: IMPT 2022 | G15: 19327000 | J15: IMPT 2022 | K15: 19327000
C16: =-((3815000)/10)*12 -> -4578000 | D16: AUTORRENTA | F16: IMPT 2023 | G16: =+C14 -> #REF! | H16: =+G16*75% -> #REF! | J16: IMPT 2023 | K16: =+C14 -> #REF!
C17: =SUM(C14:C16) -> #REF! | D17: IMP DESP RETENC | H17: =+C15+C16 -> -16081636 | K17: =+(K15+K16)/2 -> #REF!
C18: =+H18 -> #REF! | D18: ANTICIPO | H18: =SUM(H16:H17) -> #REF! | K18: =+C15-C16 -> -6925636.4
C19: =+C17+C18 -> #REF! | D19: TOTAL A PAGAR | K19: =SUM(K17:K18) -> #REF!
C20: =+C19/2 -> #REF! | D20: 2 CUOTAS
C22: =+GETPIVOTDATA("VALOR",'E.R. PPTO - REAL'!$S$11,"MES","SEPTIEMBRE","CLASE","INGRESO","GRUPO","INGRESO OPERACIONAL")+'PROYECCION IMP (2)'!C7+'PROYECCION IMP (2)'!C8 -> #REF! | D22: =+C22/4 -> #REF! | F22: =+'PROYECCION IMP'!C10 -> #REF! | I22: =(15970-4000)*4900.15 -> 58654795
D23: =+D22*39% -> #REF! | F23: =-C10 -> #REF!
D24: =122462000-D23 -> #REF! | F24: =SUM(F22:F23) -> #REF! | G24: =+F24+F26 -> #REF!
D25: =+D24+D23 -> #REF! | F25: =+F24+D25 -> #REF!
F26: -19000000
D27: =10588*8700 -> 92115600 | F27: =+F26+F25 -> #REF!
D28: =+D27*42% -> 38688552
D29: =+D25+D28 -> #REF! | E29: =+D29-D28 -> #REF! | F29: =+E29/4900.15 -> #REF!
D30: =+D29+F24 -> #REF! | F30: 16000
F31: =+F30-F29 -> #REF!

Sheet GRÁFICA

Sheet G.MARGEN NETO
C39: ENERO | D39: FEBRERO | E39: MARZO | F39: ABRIL | G39: MAYO | H39: JUNIO | I39: JULIO | J39: AGOSTO | K39: SEPTIEMBRE | L39: OCTUBRE | M39: NOVIEMBRE | N39: DICIEMBRE
B40: 2020 | C40: -0.0049927017 | D40: -0.30071237 | E40: 0.45203926 | F40: 0.15728062 | G40: 0.12370434 | H40: -0.14442567 | I40: 0.35456671 | J40: 0.42236513 | K40: 0.32730646 | L40: 0.43302226 | M40: 0.18231659 | N40: -0.0050960411
B41: 2021 | C41: 0.30939994 | D41: 0.26920441 | E41: 0.34847771 | F41: 0.29264692 | G41: 0.23062467 | H41: 0.28935451 | I41: 0.23592944 | J41: 0.11980183 | K41: -0.46156986 | L41: -0.21146047 | M41: -0.008290494 | N41: -1.0532959
B42: 2022 | C42: 0.18172457 | D42: 0.16418782 | E42: 0.28325558 | F42: -0.027460202 | G42: -0.36440759 | H42: 0.14390336 | I42: 0.13004373 | J42: 0.24554764 | K42: 0.17936809 | L42: 0.19398442 | M42: 0.25945223 | N42: -1.2901223
B43: 2023 | C43: 0.46405195 | D43: 0.29482534 | E43: 0.09171565 | F43: 0.31168932 | G43: 0.35344485 | H43: -0.15886658 | I43: 0.22547314 | J43: 0.26459703 | K43: 0.28173086 | L43: 0.20433471 | M43: -0.049688743 | N43: -0.66289865
B44: 2024 | C44: 0.30013426 | D44: 0.27521967 | E44: 0.42758934 | F44: 0.38616177 | G44: 0.43968724 | H44: -0.41484552 | I44: 0.19617974 | J44: 0.23120246 | K44: 0.25356756 | L44: 0.47473789 | M44: -0.19767598 | N44: -0.70316277
B45: 2025 | C45: 0.76111733 | D45: 0.65098149 | E45: 0.56367199 | F45: -0.1328605 | G45: 0.15049312 | H45: 0.25903323 | I45: 0.24894455 | J45: -0.28704679 | K45: -0.11647402 | L45: -0.28543667 | M45: 0.096434051 | N45: -1.0085916
B46: 2026 | C46: =+'E.R. PPTO - REAL'!AN27 -> 0.25810053 | D46: =+'E.R. PPTO - REAL'!AO27 -> -0.056017155 | E46: =+'E.R. PPTO - REAL'!AP27 -> 0.35919677

Sheet G. COMP. PPTO - EJEC.

Sheet BALANCE GENERAL
B2: PANGEA NATURAL PRODUCTS S.A.S.
B3: NIT. 901.196.219 - 5
B4: ESTADO DE SITUACIÓN FINANCIERA ACUMULADO 2026
B8: AÑO | C8: 2026
B9: CENTRO DE COSTO | C9: (Todas)
B10: ECUACIÓN PATRIMONIAL | C10: =+GETPIVOTDATA("VALOR",$B$11,"MES","ENERO","CLASE","ACTIVO")-GETPIVOTDATA("VALOR",$B$11,"MES","ENERO","CLASE","PASIVO")-GETPIVOTDATA("VALOR",$B$11,"MES","ENERO","CLASE","PATRIMONIO") -> 0 | D10: =+GETPIVOTDATA("VALOR",$B$11,"MES","FEBRERO","CLASE","ACTIVO")-GETPIVOTDATA("VALOR",$B$11,"MES","FEBRERO","CLASE","PASIVO")-GETPIVOTDATA("VALOR",$B$11,"MES","FEBRERO","CLASE","PATRIMONIO") -> 0 | E10: =+GETPIVOTDATA("VALOR",$B$11,"MES","MARZO","CLASE","ACTIVO")-GETPIVOTDATA("VALOR",$B$11,"MES","MARZO","CLASE","PASIVO")-GETPIVOTDATA("VALOR",$B$11,"MES","MARZO","CLASE","PATRIMONIO") -> 0
B11: Suma de VALOR | C11: PERIODO
B12: CUENTA | C12: ENERO | D12: FEBRERO | E12: MARZO
B13: ACTIVO | C13: 1.2608168e+09 | D13: 1.309589e+09 | E13: 1.4614346e+09
B14: ACTIVO CORRIENTE | C14: 1.243846e+09 | D14: 1.292964e+09 | E14: 1.4451554e+09
B15: DISPONIBLE | C15: 2.0710516e+08 | D15: 1.2154508e+08 | E15: 51435450
B16: INVENTARIOS | C16: 105797673 | D16: 161701353 | E16: 252008791
B17: DEUDORES | C17: 9.3094313e+08 | D17: 1.0097176e+09 | E17: 1.1417112e+09
B18: ACTIVO NO CORRIENTE | C18: 16970846 | D18: 16625008 | E18: 16279170
B19: INTANGIBLES | C19: 4118887 | D19: 4084274 | E19: 4049661
B20: PROPIEDADES, PLANTA Y EQUIPO | C20: 12851959 | D20: 12540734 | E20: 12229509
B21: PASIVO | C21: 4.2822131e+08 | D21: 4.8503354e+08 | E21: 5.5573944e+08
B22: PASIVO CORRIENTE | C22: 4.2822131e+08 | D22: 4.8503354e+08 | E22: 5.5573944e+08
B23: OBLIGACIONES FINANCIERAS | C23: 4064231 | D23: 1178498 | E23: 2496658
B24: CUENTAS POR PAGAR | C24: 1.9690422e+08 | D24: 267401879 | E24: 2.9117209e+08
... B33: RESULTADOS DEl EJERCICIO | C33: 49824625 | D33: -8039990.3 | E33: 81139615
O40: =+C40+18000000 -> 18000000

Sheet PROYECCIÓN CIERRE 2024
A1: PROYECCIÓN CIERRE CONTABLE 2024 | E1: CÁLCULO ANTICIPO
A3: INGRESOS | B3: =+((GETPIVOTDATA("VALOR",'E.R. PPTO - REAL'!$S$11,"CLASE","INGRESO")/9)*12)+230000000 -> #REF! | C3: =+B3/B3 -> #REF! | E3: OPCIÓN 1 | H3: OPCIÓN 2
A4: COSTO | B4: =+B3*35% -> #REF! | C4: =+B4/B3 -> #REF! | E4: Impuesto de Renta 2023 | F4: 58748000 | H4: Promedio 2023 - 2024 | I4: =+(F4+F5)/2 -> #REF!
A5: GASTOS DE ADMINISTRACIÓN Y VENTAS | B5: =+(((GETPIVOTDATA("VALOR",'E.R. PPTO - REAL'!$S$11,"CLASE","GASTO")-GETPIVOTDATA("VALOR",'E.R. PPTO - REAL'!$S$11,"CLASE","GASTO","GRUPO","NO OPERACIONALES")))/9)*12 -> #REF! | C5: =+B5/B3 -> #REF! | E5: Impuesto de Renta 2024 | F5: =+B7 -> #REF! | I5: 0.75
A6: UTILIDAD | B6: =+B3-B4-B5 -> #REF! | C6: =+B6/B3 -> #REF! | E6: OPCIÓN 1 | F6: 0.75
A7: IMPUESTO DE RENTA 35% | B7: =+B6*35% -> #REF! | E7: Menos Retención en la Fuente | F7: =+(26923045.08/9)*12 -> 35897393 | H7: Menos Retención en la Fuente | I7: =+F7 -> 35897393
A8: ANTICIPO AÑO 2025 | B8: =+SMALL(E8:I8,1) -> #REF! | E8: ANTICIPO OPCIÓN 1 | F8: =+(F5*F6)-F7 -> #REF! | H8: ANTICIPO OPCIÓN 2 | I8: =+(I4*I5)-I7 -> #REF!
A9: RETENCIONES EN LA FUENTE | B9: =+B3*3.1% -> #REF!
A10: ANTICIPO DEL AÑO 2024 (PAGADO EN 2023) | B10: 5602000
A11: TOTAL A PAGAR | B11: =+B7+B8-B9-B10 -> #REF! | C11: =+B11/B3 -> #REF!
A12: CUOTA 1 | B12: =+B11*50% -> #REF!
A13: CUOTA 2 | B13: =+B11*50% -> #REF!
A17: TOTAL PAGADO AÑO 2023 | B17: 44288000
A18: INGRESOS 2023 | B18: 1104734298
A19: INGRESOS 2024 | B19: =+B3 -> #REF!
A20: INCREMENTO INGRESOS | B20: =+(B19/B18)-1 -> #REF!
A22: INCREMENTO IMPUESTO DE RENTA | B22: =+(F5/F4)-1 -> #REF!
A25: PROYECCIÓN CIERRE AJUSTADO - ESCENARIO 1 | E25: CÁLCULO ANTICIPO
A27: INGRESOS | B27: =+B3 -> #REF! | C27: =+B27/B27 -> #REF! | E27: OPCIÓN 1 | H27: OPCIÓN 2
A28: COSTO | B28: =+(360354759+(55000000*2)+F41)+F48 -> #REF! | C28: =+B28/B27 -> #REF! | E28: Impuesto de Renta 2023 | F28: 58748000 | H28: Promedio 2023 - 2024 | I28: =+(F28+F29)/2 -> #REF!
A29: GASTOS DE ADMINISTRACIÓN Y VENTAS | B29: =+B5 -> #REF! | C29: =+B29/B27 -> #REF! | E29: Impuesto de Renta 2024 | F29: =+B31 -> #REF! | I29: 0.75
A30: UTILIDAD | B30: =+B27-B28-B29 -> #REF! | C30: =+B30/B27 -> #REF! | E30: OPCIÓN 1 | F30: 0.75
A31: IMPUESTO DE RENTA 35% | B31: =+B30*35% -> #REF! | E31: Menos Retención en la Fuente | F31: =+(26923045.08/9)*12 -> 35897393 | H31: Menos Retención en la Fuente | I31: =+F31 -> 35897393
A32: ANTICIPO AÑO 2025 | B32: =+SMALL(E32:I32,1) -> #REF! | E32: ANTICIPO OPCIÓN 1 | F32: =+(F29*F30)-F31 -> #REF! | H32: ANTICIPO OPCIÓN 2 | I32: =+(I28*I29)-I31 -> #REF!
A33: RETENCIONES EN LA FUENTE | B33: =+F31 -> 35897393
A34: ANTICIPO DEL AÑO 2024 (PAGADO EN 2023) | B34: 5602000
A35: TOTAL A PAGAR | B35: =+B31+B32-B33-B34 -> #REF!
A36: CUOTA 1 | B36: =+B35*50% -> #REF!
A37: CUOTA 2 | B37: =+B35*50% -> #REF!
A39: TOTAL PAGADO AÑO 2023 | B39: 44288000 | E39: UNIAGRO 2023 | F39: 88990000
A40: INGRESOS 2023 | B40: 1104734298 | E40: UNIAGRO 2024 | F40: =+(F39*B20)+F39 -> #REF!
A41: INGRESOS 2024 | B41: =+B27 -> #REF! | E41: EXCEDENTE | F41: =+F40-32760000 -> #REF! | G41: =+F41-45150000 -> #REF!
A42: INCREMENTO INGRESOS | B42: =+(B41/B40)-1 -> #REF!
E43: ESTIMADO COSTO
A44: INCREMENTO IMPUESTO DE RENTA | B44: =+(B31/F28)-1 -> #REF! | E44: ENERO | F44: =+GETPIVOTDATA("VALOR",'E.R. PPTO - REAL'!$S$11,"MES","ENERO","CLASE","INGRESO","GRUPO","INGRESO OPERACIONAL")*35% -> #REF!
A45: BENEFICIO DE AUDITORÍA | B45: 12 MESES | E45: FEBRERO | F45: =+GETPIVOTDATA("VALOR",'E.R. PPTO - REAL'!$S$11,"MES","FEBRERO","CLASE","INGRESO","GRUPO","INGRESO OPERACIONAL")*35% -> #REF!
E46: MARZO | F46: =+GETPIVOTDATA("VALOR",'E.R. PPTO - REAL'!$S$11,"MES","MARZO","CLASE","INGRESO","GRUPO","INGRESO OPERACIONAL")*35% -> #REF!
E47: ABRIL | F47: =+GETPIVOTDATA("VALOR",'E.R. PPTO - REAL'!$S$11,"MES","ABRIL","CLASE","INGRESO","GRUPO","INGRESO OPERACIONAL")*30% -> #REF!
E48: TOTAL | F48: =+SUM(F44:F47) -> #REF!
A51: PROYECCIÓN CIERRE AJUSTADO - ESCENARIO 3 | E51: CÁLCULO ANTICIPO
A53: INGRESOS | B53: =+B27 -> #REF! | C53: =+B53/B53 -> #REF! | E53: OPCIÓN 1 | H53: OPCIÓN 2
A54: COSTO | B54: =+B53*45% -> #REF! | C54: =+B54/B53 -> #REF! | E54: Impuesto de Renta 2023 | F54: 58748000 | H54: Promedio 2023 - 2024 | I54: =+(F54+F55)/2 -> #REF!
A55: GASTOS DE ADMINISTRACIÓN Y VENTAS | B55: =+B29 -> #REF! | C55: =+B55/B53 -> #REF! | E55: Impuesto de Renta 2024 | F55: =+B57 -> #REF! | I55: 0.75
A56: UTILIDAD | B56: =+B53-B54-B55 -> #REF! | C56: =+B56/B53 -> #REF! | E56: OPCIÓN 1 | F56: 0.75
A57: IMPUESTO DE RENTA 35% | B57: =+B56*35% -> #REF! | E57: Menos Retención en la Fuente | F57: =+(26923045.08/9)*12 -> 35897393 | H57: Menos Retención en la Fuente | I57: =+F57 -> 35897393
A58: ANTICIPO AÑO 2025 | B58: =+SMALL(E58:I58,1) -> #REF! | E58: ANTICIPO OPCIÓN 1 | F58: =+(F55*F56)-F57 -> #REF! | H58: ANTICIPO OPCIÓN 2 | I58: =+(I54*I55)-I57 -> #REF!
A59: RETENCIONES EN LA FUENTE | B59: =+B53*3.1% -> #REF!
A60: ANTICIPO DEL AÑO 2024 (PAGADO EN 2023) | B60: 5602000
A61: TOTAL A PAGAR | B61: =+B57+B58-B59-B60 -> #REF!
A62: CUOTA 1 | B62: =+B61*50% -> #REF!
A63: CUOTA 2 | B63: =+B61*50% -> #REF!
A65: TOTAL PAGADO AÑO 2023 | B65: 44288000 | E65: UNIAGRO 2023 | F65: 88990000 | G65: =+F65/B66 -> 0.080553306 | I65: =+(360354759+(157000000+16921680+2800000)) -> 537076439
A66: INGRESOS 2023 | B66: 1104734298 | E66: UNIAGRO 2024 | F66: =+(F65*35%)+F65 -> 120136500 | G66: =+F66/B53 -> #REF! | H66: =+B53*13% -> #REF! | I66: =+B54-I65 -> #REF!
A67: INGRESOS 2024 | B67: =+B53 -> #REF! | E67: EXCEDENTE | F67: =+F66-32760000 -> 87376500 | G67: =+G65-G66 -> #REF! | I67: =+H66-32760000 -> #REF! | J67: =+I67-45150000 -> #REF!
A68: INCREMENTO INGRESOS | B68: =+(B67/B66)-1 -> #REF! | I68: =+I65+I67 -> #REF!
E69: ESTIMADO COSTO | I69: =+B54-I68 -> #REF!
A70: INCREMENTO IMPUESTO DE RENTA | B70: =+(B57/F54)-1 -> #REF! | E70: ENERO | F70: =+GETPIVOTDATA("VALOR",'E.R. PPTO - REAL'!$S$11,"MES","ENERO","CLASE","INGRESO","GRUPO","INGRESO OPERACIONAL")*30% -> #REF!
A71: BENEFICIO DE AUDITORÍA | B71: 6 MESES | E71: FEBRERO | F71: =+GETPIVOTDATA("VALOR",'E.R. PPTO - REAL'!$S$11,"MES","FEBRERO","CLASE","INGRESO","GRUPO","INGRESO OPERACIONAL")*30% -> #REF!
E72: MARZO | F72: =+GETPIVOTDATA("VALOR",'E.R. PPTO - REAL'!$S$11,"MES","MARZO","CLASE","INGRESO","GRUPO","INGRESO OPERACIONAL")*30% -> #REF!
A73: =+B53*3.3/1000 -> #REF! | B73: ICA | E73: ABRIL | F73: =+GETPIVOTDATA("VALOR",'E.R. PPTO - REAL'!$S$11,"MES","ABRIL","CLASE","INGRESO","GRUPO","INGRESO OPERACIONAL")*30% -> #REF!
E74: TOTAL | F74: =+SUM(F70:F73) -> #REF!
J75: =13*1300000 -> 16900000
J76: =+J75*12 -> 202800000
A77: COSTO A SEPT 2024 | B77: 360354759 | J77: =+J76*25% -> 50700000
A78: GESTIÓN FERTILIZANTES A CIERRE | B78: 150000000 | J78: =+J76*8% -> 16224000
A79: EXCEDENTE REQUERIDO PARA COSTO AL 45% | B79: =+B54-B77-B78 -> #REF! | J79: =+J76*10% -> 20280000
J80: =+J76-J77-J78-J79 -> 115596000
J81: =+J80*15% -> 17339400
J82: =+J80-J81 -> 98256600
J84: =94/2 -> 47

Sheet BASE DE DATOS BG
A1: MES | B1: AÑO | C1: CENTRO DE COSTO | D1: CLASE | E1: GRUPO | F1: SUBGRUPO | G1: CUENTA | H1: TERCERO | I1: VALOR
A2: AGOSTO | B2: 2018 | C2: HARINA | D2: ACTIVO | E2: ACTIVO CORRIENTE | F2: DISPONIBLE | G2: 11050501 - Caja general | I2: 0
A3: AGOSTO | B3: 2018 | C3: HARINA | D3: ACTIVO | E3: ACTIVO CORRIENTE | F3: DISPONIBLE | G3: 11100503 - Cuenta Cte. Banco Bogotá 8798 | I3: 15163900
A4: AGOSTO | B4: 2018 | C4: HARINA | D4: ACTIVO | E4: ACTIVO CORRIENTE | F4: DISPONIBLE | G4: 13309501 - Otros | I4: 100000
A5: AGOSTO | B5: 2018 | C5: HARINA | D5: ACTIVO | E5: ACTIVO NO CORRIENTE | I5: 0
A6: AGOSTO | B6: 2018 | C6: HARINA | D6: PASIVO | E6: PASIVO CORRIENTE | F6: IMPUESTOS, GRAVÁMENES Y TASAS | G6: 23652001 - Comisiones | I6: 75000
A7: AGOSTO | B7: 2018 | C7: HARINA | D7: PASIVO | E7: PASIVO CORRIENTE | F7: IMPUESTOS, GRAVÁMENES Y TASAS | G7: 23680515 - Rete Ica 6,6 | I7: 2970
A8: AGOSTO | B8: 2018 | C8: HARINA | D8: PASIVO | E8: PASIVO CORRIENTE | F8: IMPUESTOS, GRAVÁMENES Y TASAS | G8: 24081001 - Iva descontable por compras 19% | I8: -137784
A9: AGOSTO | B9: 2018 | C9: HARINA | D9: PASIVO | E9: PASIVO CORRIENTE | F9: DEUDA CON ACCIONISTAS O SOCIOS | G9: 235511 - Deuda con socios | H9: SEBASTIÁN MENDOZA CASTAÑO | I9: 2994651
A10: AGOSTO | B10: 2018 | C10: HARINA | D10: PASIVO | E10: PASIVO CORRIENTE | F10: DEUDA CON ACCIONISTAS O SOCIOS | G10: 235511 - Deuda con socios | H10: JORGE MOLINA CABAL | I10: 13999825
A11: AGOSTO | B11: 2018 | C11: HARINA | D11: PATRIMONIO | E11: PATRIMONIO | F11: CAPITAL SOCIAL | G11: 31050501 - Capital autorizado | I11: 200000000
A12: AGOSTO | B12: 2018 | C12: HARINA | D12: PATRIMONIO | E12: PATRIMONIO | F12: CAPITAL SOCIAL | G12: 31051001 - Capital por suscribir (db) | I12: -198000000
A13: AGOSTO | B13: 2018 | C13: HARINA | D13: PATRIMONIO | E13: PATRIMONIO | F13: UTILIDAD Y/O PÉRDIDA DEL EJERCICIO | G13: Pérdida del Ejercicio | I13: -3670762
A14: SEPTIEMBRE | B14: 2018 | C14: HARINA | D14: ACTIVO | E14: ACTIVO CORRIENTE | F14: DISPONIBLE | G14: 11050501 - Caja general | I14: 0
A15: SEPTIEMBRE | B15: 2018 | C15: HARINA | D15: ACTIVO | E15: ACTIVO CORRIENTE | F15: DISPONIBLE | G15: 11051001 - Cajas menores | I15: 300000
A16: SEPTIEMBRE | B16: 2018 | C16: HARINA | D16: ACTIVO | E16: ACTIVO CORRIENTE | F16: DISPONIBLE | G16: 11100503 - Cuenta Cte. Banco Bogotá 8798 | I16: 22319605
A17: SEPTIEMBRE | B17: 2018 | C17: HARINA | D17: ACTIVO | E17: ACTIVO CORRIENTE | F17: DISPONIBLE | G17: 13309501 - Otros | I17: 100000
A18: SEPTIEMBRE | B18: 2018 | C18: HARINA | D18: ACTIVO | E18: ACTIVO CORRIENTE | F18: INVENTARIOS | G18: 14350101 - Mercancías no fabricadas | I18: 200500
A19: SEPTIEMBRE | B19: 2018 | C19: HARINA | D19: ACTIVO | E19: ACTIVO NO CORRIENTE | F19: PROPIEDAD, PLANTA Y EQUIPO | G19: 15240501 - Muebles y enseres | I19: 230750
A20: SEPTIEMBRE | B20: 2018 | C20: HARINA | D20: PASIVO | E20: PASIVO CORRIENTE | F20: OTROS PASIVOS | G20: 23359505 - Varios | H20: LA CONCEPCIÓN | I20: 238595
A21: SEPTIEMBRE | B21: 2018 | C21: HARINA | D21: PASIVO | E21: PASIVO CORRIENTE | F21: OBLIGACIONES LABORALES | G21: 2510100102 - Cesantías | I21: 123968
A22: SEPTIEMBRE | B22: 2018 | C22: HARINA | D22: PASIVO | E22: PASIVO CORRIENTE | F22: OBLIGACIONES LABORALES | G22: 2510100202 - Intereses sobre cesantías | I22: 14876
A23: SEPTIEMBRE | B23: 2018 | C23: HARINA | D23: PASIVO | E23: PASIVO CORRIENTE | F23: OBLIGACIONES LABORALES | G23: 2510100302 - Vacaciones | I23: 58380
A24: SEPTIEMBRE | B24: 2018 | C24: HARINA | D24: PASIVO | E24: PASIVO CORRIENTE | F24: OBLIGACIONES LABORALES | G24: 2510100402 - Prima de servicios | I24: 123968
A25: SEPTIEMBRE | B25: 2018 | C25: HARINA | D25: PASIVO | E25: PASIVO CORRIENTE | F25: IMPUESTOS, GRAVÁMENES Y TASAS | G25: 23653001 - Arrendamientos | I25: 28000
A26: SEPTIEMBRE | B26: 2018 | C26: HARINA | D26: PASIVO | E26: PASIVO CORRIENTE | F26: IMPUESTOS, GRAVÁMENES Y TASAS | G26: 24080602 - Iva generado | I26: 0
A27: SEPTIEMBRE | B27: 2018 | C27: HARINA | D27: PASIVO | E27: PASIVO CORRIENTE | F27: IMPUESTOS, GRAVÁMENES Y TASAS | G27: 24081001 - Iva descontable por compras 19% | I27: -204009
A28: SEPTIEMBRE | B28: 2018 | C28: HARINA | D28: PASIVO | E28: PASIVO CORRIENTE | F28: IMPUESTOS, GRAVÁMENES Y TASAS | G28: 24081501 - Descontable por servicios | I28: -2158
A29: SEPTIEMBRE | B29: 2018 | C29: HARINA | D29: PASIVO | E29: PASIVO CORRIENTE | F29: OTROS PASIVOS | G29: 23704501 - Fondos | I29: 343308
A30: SEPTIEMBRE | B30: 2018 | C30: HARINA | D30: PASIVO | E30: PASIVO CORRIENTE | F30: DEUDA CON ACCIONISTAS O SOCIOS | G30: 235511 - Deuda con socios | H30: SEBASTIÁN MENDOZA CASTAÑO | I30: =14263124-164075 -> 14099049
A31: SEPTIEMBRE | B31: 2018 | C31: HARINA | D31: PASIVO | E31: PASIVO CORRIENTE | F31: DEUDA CON ACCIONISTAS O SOCIOS | G31: 235511 - Deuda con socios | H31: JORGE MOLINA CABAL | I31: 14163900
A32: SEPTIEMBRE | B32: 2018 | C32: HARINA | D32: PATRIMONIO | E32: PATRIMONIO | F32: CAPITAL SOCIAL | G32: 31050501 - Capital autorizado | I32: 200000000
A33: SEPTIEMBRE | B33: 2018 | C33: HARINA | D33: PATRIMONIO | E33: PATRIMONIO | F33: CAPITAL SOCIAL | G33: 31051001 - Capital por suscribir (db) | I33: -198000000
A34: SEPTIEMBRE | B34: 2018 | C34: HARINA | D34: PATRIMONIO | E34: PATRIMONIO | F34: UTILIDAD Y/O PÉRDIDA DEL EJERCICIO | G34: Pérdida del Ejercicio | I34: -4166260
A35: SEPTIEMBRE | B35: 2018 | C35: HARINA | D35: PATRIMONIO | E35: PATRIMONIO | F35: UTILIDAD Y/O PÉRDIDA DEL EJERCICIO | G35: Pérdida ejercicios anteriores | I35: -3670762
A36: OCTUBRE | B36: 2018 | C36: HARINA | D36: ACTIVO | E36: ACTIVO CORRIENTE | F36: DISPONIBLE | G36: 11050501 - Caja general | I36: 0
A37: OCTUBRE | B37: 2018 | C37: HARINA | D37: ACTIVO | E37: ACTIVO CORRIENTE | F37: DISPONIBLE | G37: 11051001 - Cajas menores | I37: 300000
A38: OCTUBRE | B38: 2018 | C38: HARINA | D38: ACTIVO | E38: ACTIVO CORRIENTE | F38: DISPONIBLE | G38: 11100503 - Cuenta Cte. Banco Bogotá 8798 | I38: 13157397
A39: OCTUBRE | B39: 2018 | C39: HARINA | D39: ACTIVO | E39: ACTIVO CORRIENTE | F39: DISPONIBLE | G39: 13300501 - A proveedores | I39: 1866261
A40: OCTUBRE | B40: 2018 | C40: HARINA | D40: ACTIVO | E40: ACTIVO CORRIENTE | F40: DISPONIBLE | G40: 13309501 - Otros | I40: 100000
A41: OCTUBRE | B41: 2018 | C41: HARINA | D41: ACTIVO | E41: ACTIVO CORRIENTE | F41: INVENTARIOS | G41: 14350101 - Mercancías no fabricadas | I41: 200500
A42: OCTUBRE | B42: 2018 | C42: HARINA | D42: ACTIVO | E42: ACTIVO NO CORRIENTE | F42: PROPIEDAD, PLANTA Y EQUIPO | G42: 15240501 - Muebles y enseres | I42: 230750
A43: OCTUBRE | B43: 2018 | C43: HARINA | D43: PASIVO | E43: PASIVO CORRIENTE | F43: OTROS PASIVOS | G43: 23359505 - Varios | H43: LA CONCEPCIÓN | I43: 238595
A44: OCTUBRE | B44: 2018 | C44: HARINA | D44: PASIVO | E44: PASIVO CORRIENTE | F44: OBLIGACIONES LABORALES | G44: 2510100102 - Cesantías | I44: 247936
A45: OCTUBRE | B45: 2018 | C45: HARINA | D45: PASIVO | E45: PASIVO CORRIENTE | F45: OBLIGACIONES LABORALES | G45: 2510100202 - Intereses sobre cesantías | I45: 29752
A46: OCTUBRE | B46: 2018 | C46: HARINA | D46: PASIVO | E46: PASIVO CORRIENTE | F46: OBLIGACIONES LABORALES | G46: 2510100302 - Vacaciones | I46: 116760
A47: OCTUBRE | B47: 2018 | C47: HARINA | D47: PASIVO | E47: PASIVO CORRIENTE | F47: OBLIGACIONES LABORALES | G47: 2510100402 - Prima de servicios | I47: 247936
A48: OCTUBRE | B48: 2018 | C48: HARINA | D48: PASIVO | E48: PASIVO CORRIENTE | F48: IMPUESTOS, GRAVÁMENES Y TASAS | G48: 23651501 - Honorarios | I48: 42938
A49: OCTUBRE | B49: 2018 | C49: HARINA | D49: PASIVO | E49: PASIVO CORRIENTE | F49: IMPUESTOS, GRAVÁMENES Y TASAS | G49: 23652001 - Comisiones | I49: 22000
A50: OCTUBRE | B50: 2018 | C50: HARINA | D50: PASIVO | E50: PASIVO CORRIENTE | F50: IMPUESTOS, GRAVÁMENES Y TASAS | G50: 23652501 - Servicios 6% | I50: 18000
A51: OCTUBRE | B51: 2018 | C51: HARINA | D51: PASIVO | E51: PASIVO CORRIENTE | F51: IMPUESTOS, GRAVÁMENES Y TASAS | G51: 23653001 - Arrendamientos | I51: 28000
A52: OCTUBRE | B52: 2018 | C52: HARINA | D52: PASIVO | E52: PASIVO CORRIENTE | F52: IMPUESTOS, GRAVÁMENES Y TASAS | G52: 23680515 - Rete Ica 6,6 | I52: 2578
A53: OCTUBRE | B53: 2018 | C53: HARINA | D53: PASIVO | E53: PASIVO CORRIENTE | F53: IMPUESTOS, GRAVÁMENES Y TASAS | G53: 23680517 - Rete Ica 10 | I53: 3010
A54: OCTUBRE | B54: 2018 | C54: HARINA | D54: PASIVO | E54: PASIVO CORRIENTE | F54: IMPUESTOS, GRAVÁMENES Y TASAS | G54: 24080602 - Iva generado
A55: OCTUBRE | B55: 2018 | C55: HARINA | D55: PASIVO | E55: PASIVO CORRIENTE | F55: IMPUESTOS, GRAVÁMENES Y TASAS | G55: 24081001 - Iva descontable por compras 19% | I55: -278227
A56: OCTUBRE | B56: 2018 | C56: HARINA | D56: PASIVO | E56: PASIVO CORRIENTE | F56: IMPUESTOS, GRAVÁMENES Y TASAS | G56: 24081501 - Descontable por servicios | I56: -18544
A57: OCTUBRE | B57: 2018 | C57: HARINA | D57: PASIVO | E57: PASIVO CORRIENTE | F57: OTROS PASIVOS | G57: 23704501 - Fondos | I57: 343308
A58: OCTUBRE | B58: 2018 | C58: HARINA | D58: PASIVO | E58: PASIVO CORRIENTE | F58: DEUDA CON ACCIONISTAS O SOCIOS | G58: 235511 - Deuda con socios | H58: SEBASTIÁN MENDOZA CASTAÑO | I58: =14263124-164075 -> 14099049
A59: OCTUBRE | B59: 2018 | C59: HARINA | D59: PASIVO | E59: PASIVO CORRIENTE | F59: DEUDA CON ACCIONISTAS O SOCIOS | G59: 235511 - Deuda con socios | H59: JORGE MOLINA CABAL | I59: 14163900
A60: OCTUBRE | B60: 2018 | C60: HARINA | D60: PATRIMONIO | E60: PATRIMONIO | F60: CAPITAL SOCIAL | G60: 31050501 - Capital autorizado | I60: 200000000
A61: OCTUBRE | B61: 2018 | C61: HARINA | D61: PATRIMONIO | E61: PATRIMONIO | F61: CAPITAL SOCIAL | G61: 31051001 - Capital por suscribir (db) | I61: -198000000
A62: OCTUBRE | B62: 2018 | C62: HARINA | D62: PATRIMONIO | E62: PATRIMONIO | F62: UTILIDAD Y/O PÉRDIDA DEL EJERCICIO | G62: Pérdida del Ejercicio | I62: -7615061
A63: OCTUBRE | B63: 2018 | C63: HARINA | D63: PATRIMONIO | E63: PATRIMONIO | F63: UTILIDAD Y/O PÉRDIDA DEL EJERCICIO | G63: Pérdida ejercicios anteriores | I63: -7837022
A64: NOVIEMBRE | B64: 2018 | C64: HARINA | D64: ACTIVO | E64: ACTIVO CORRIENTE | F64: DISPONIBLE | G64: 11050501 - Caja general | I64: 1325000
A65: NOVIEMBRE | B65: 2018 | C65: HARINA | D65: ACTIVO | E65: ACTIVO CORRIENTE | F65: DISPONIBLE | G65: 11051001 - Cajas menores | I65: 300000
A66: NOVIEMBRE | B66: 2018 | C66: HARINA | D66: ACTIVO | E66: ACTIVO CORRIENTE | F66: DISPONIBLE | G66: 11100503 - Cuenta Cte. Banco Bogotá 8798 | I66: 11732527
A67: NOVIEMBRE | B67: 2018 | C67: HARINA | D67: ACTIVO | E67: ACTIVO CORRIENTE | F67: DISPONIBLE | G67: 13050501 - Clientes nacionales | I67: 255998
A68: NOVIEMBRE | B68: 2018 | C68: HARINA | D68: ACTIVO | E68: ACTIVO CORRIENTE | F68: DISPONIBLE | G68: 13300501 - A proveedores | I68: 1157552
A69: NOVIEMBRE | B69: 2018 | C69: HARINA | D69: ACTIVO | E69: ACTIVO CORRIENTE | F69: DISPONIBLE | G69: 13309501 - Otros | I69: 100000
A70: NOVIEMBRE | B70: 2018 | C70: HARINA | D70: ACTIVO | E70: ACTIVO CORRIENTE | F70: INVENTARIOS | G70: 14350101 - Mercancías no fabricadas | I70: 245500
A71: NOVIEMBRE | B71: 2018 | C71: HARINA | D71: ACTIVO | E71: ACTIVO NO CORRIENTE | F71: PROPIEDAD, PLANTA Y EQUIPO | G71: 15240501 - Muebles y enseres | I71: 230750
A72: NOVIEMBRE | B72: 2018 | C72: HARINA | D72: PASIVO | E72: PASIVO CORRIENTE | F72: OTROS PASIVOS | G72: 23359505 - Varios | H72: LA CONCEPCIÓN | I72: 1688524
A73: NOVIEMBRE | B73: 2018 | C73: HARINA | D73: PASIVO | E73: PASIVO CORRIENTE | F73: OBLIGACIONES LABORALES | G73: 25050501 - Salarios por pagar | I73: 2288211
A74: NOVIEMBRE | B74: 2018 | C74: HARINA | D74: PASIVO | E74: PASIVO CORRIENTE | F74: OBLIGACIONES LABORALES | G74: 2510100102 - Cesantías | I74: 371904
A75: NOVIEMBRE | B75: 2018 | C75: HARINA | D75: PASIVO | E75: PASIVO CORRIENTE | F75: OBLIGACIONES LABORALES | G75: 2510100202 - Intereses sobre cesantías | I75: 44628
A76: NOVIEMBRE | B76: 2018 | C76: HARINA | D76: PASIVO | E76: PASIVO CORRIENTE | F76: OBLIGACIONES LABORALES | G76: 2510100302 - Vacaciones | I76: 175140
A77: NOVIEMBRE | B77: 2018 | C77: HARINA | D77: PASIVO | E77: PASIVO CORRIENTE | F77: OBLIGACIONES LABORALES | G77: 2510100402 - Prima de servicios | I77: 371904
A78: NOVIEMBRE | B78: 2018 | C78: HARINA | D78: PASIVO | E78: PASIVO CORRIENTE | F78: IMPUESTOS, GRAVÁMENES Y TASAS | G78: 23651501 - Honorarios | I78: 42968
A79: NOVIEMBRE | B79: 2018 | C79: HARINA | D79: PASIVO | E79: PASIVO CORRIENTE | F79: IMPUESTOS, GRAVÁMENES Y TASAS | G79: 23652001 - Comisiones | I79: 391500
A80: NOVIEMBRE | B80: 2018 | C80: HARINA | D80: PASIVO | E80: PASIVO CORRIENTE | F80: IMPUESTOS, GRAVÁMENES Y TASAS | G80: 23653001 - Arrendamientos | I80: 28000
A81: NOVIEMBRE | B81: 2018 | C81: HARINA | D81: PASIVO | E81: PASIVO CORRIENTE | F81: IMPUESTOS, GRAVÁMENES Y TASAS | G81: 23680515 - Rete Ica 6,6 | I81: 8786
A82: NOVIEMBRE | B82: 2018 | C82: HARINA | D82: PASIVO | E82: PASIVO CORRIENTE | F82: IMPUESTOS, GRAVÁMENES Y TASAS | G82: 23680517 - Rete Ica 10 | I82: 33160
A83: NOVIEMBRE | B83: 2018 | C83: HARINA | D83: PASIVO | E83: PASIVO CORRIENTE | F83: IMPUESTOS, GRAVÁMENES Y TASAS | G83: 23680519 - Reteica 7,7 | I83: 4172
A84: NOVIEMBRE | B84: 2018 | C84: HARINA | D84: PASIVO | E84: PASIVO CORRIENTE | F84: IMPUESTOS, GRAVÁMENES Y TASAS | G84: 24080601 - Iva generado | I84: 252432
... A87: NOVIEMBRE | B87: 2018 | C87: HARINA | D87: PASIVO | E87: PASIVO CORRIENTE | F87: OTROS PASIVOS | G87: 23704501 - Fondos | I87: 343308
A88: NOVIEMBRE | B88: 2018 | C88: HARINA | D88: PASIVO | E88: PASIVO CORRIENTE | F88: DEUDA CON ACCIONISTAS O SOCIOS | G88: 235511 - Deuda con socios | H88: SEBASTIÁN MENDOZA CASTAÑO | I88: =14263124-164075-119899 -> 13979150
A89: NOVIEMBRE | B89: 2018 | C89: HARINA | D89: PASIVO | E89: PASIVO CORRIENTE | F89: DEUDA CON ACCIONISTAS O SOCIOS | G89: 235511 - Deuda con socios | H89: JORGE MOLINA CABAL | I89: 14163900
A90: NOVIEMBRE | B90: 2018 | C90: HARINA | D90: PASIVO | E90: PASIVO CORRIENTE | F90: DEUDA CON ACCIONISTAS O SOCIOS | G90: 235511 - Deuda con socios | H90: SEBASTIÁN MENDOZA CASTAÑO | I90: 10000000
A91: NOVIEMBRE | B91: 2018 | C91: HARINA | D91: PATRIMONIO | E91: PATRIMONIO | F91: CAPITAL SOCIAL | G91: 31050501 - Capital autorizado | I91: 200000000
A92: NOVIEMBRE | B92: 2018 | C92: HARINA | D92: PATRIMONIO | E92: PATRIMONIO | F92: CAPITAL SOCIAL | G92: 31051001 - Capital por suscribir (db) | I92: -198000000
A93: NOVIEMBRE | B93: 2018 | C93: HARINA | D93: PATRIMONIO | E93: PATRIMONIO | F93: UTILIDAD Y/O PÉRDIDA DEL EJERCICIO | G93: Pérdida del Ejercicio | I93: -13720827
A94: NOVIEMBRE | B94: 2018 | C94: HARINA | D94: PATRIMONIO | E94: PATRIMONIO | F94: UTILIDAD Y/O PÉRDIDA DEL EJERCICIO | G94: Pérdida ejercicios anteriores | I94: -15452113
A95: DICIEMBRE | B95: 2018 | C95: HARINA | D95: ACTIVO | E95: ACTIVO CORRIENTE | F95: DISPONIBLE | G95: 11050501 - Caja general | I95: 1884322
A96: DICIEMBRE | B96: 2018 | C96: HARINA | D96: ACTIVO | E96: ACTIVO CORRIENTE | F96: DISPONIBLE | G96: 11051001 - Cajas menores | I96: 300000
A97: DICIEMBRE | B97: 2018 | C97: HARINA | D97: ACTIVO | E97: ACTIVO CORRIENTE | F97: DISPONIBLE | G97: 11100503 - Cuenta Cte. Banco Bogotá 8798 | I97: 2286886
A98: DICIEMBRE | B98: 2018 | C98: HARINA | D98: ACTIVO | E98: ACTIVO CORRIENTE | F98: DISPONIBLE | G98: 13050501 - Clientes nacionales | I98: 250003
A99: DICIEMBRE | B99: 2018 | C99: HARINA | D99: ACTIVO | E99: ACTIVO CORRIENTE | F99: DISPONIBLE | G99: 13300501 - A proveedores | I99: 1277413
A100: DICIEMBRE | B100: 2018 | C100: HARINA | D100: ACTIVO | E100: ACTIVO CORRIENTE | F100: DISPONIBLE | G100: 13309501 - Otros | I100: 100000
A101: DICIEMBRE | B101: 2018 | C101: HARINA | D101: ACTIVO | E101: ACTIVO CORRIENTE | F101: INVENTARIOS | G101: 14350101 - Mercancías no fabricadas | I101: 3233500
A102: DICIEMBRE | B102: 2018 | C102: HARINA | D102: ACTIVO | E102: ACTIVO NO CORRIENTE | F102: PROPIEDAD, PLANTA Y EQUIPO | G102: 15240501 - Muebles y enseres | I102: 230750
...

Sheet PROYECCIÓN CIERRE 2025
A1: PROYECCIÓN CIERRE CONTABLE 2025 | E1: CÁLCULO ANTICIPO
A2: REAL
A3: INGRESOS | B3: =3744412422.86382-500000000 -> 3.2444124e+09 | C3: =+B3/B3 -> 1 | E3: OPCIÓN 1 | H3: OPCIÓN 2
A4: COSTO | B4: 1.0441368e+09 | C4: =+B4/B3 -> 0.32182616 | E4: Impuesto de Renta 2024 | F4: 90220000 | H4: Promedio 2023 - 2024 | I4: =+(F4+F5)/2 -> 2.4455351e+08
A5: GASTOS DE ADMINISTRACIÓN Y VENTAS | B5: =+(B3*C5) -> 1.0605984e+09 | C5: 0.3269 | E5: Impuesto de Renta 2025 | F5: =+B7 -> 3.9888702e+08 | I5: 0.75
A6: UTILIDAD | B6: =+B3-B4-B5 -> 1.1396772e+09 | C6: =+B6/B3 -> 0.35127384 | E6: OPCIÓN 1 | F6: 0.75
A7: IMPUESTO DE RENTA 35% | B7: =+B6*35% -> 3.9888702e+08 | E7: Menos Retención en la Fuente | F7: =(+B3*(2.5%))*80%+(B3*0.55%) -> 82732517 | H7: Menos Retención en la Fuente | I7: =+F7 -> 82732517
A8: ANTICIPO AÑO 2025 | B8: =+SMALL(E8:I8,1) -> 1.0068261e+08 | E8: ANTICIPO OPCIÓN 1 | F8: =+(F5*F6)-F7 -> 2.1643275e+08 | H8: ANTICIPO OPCIÓN 2 | I8: =+(I4*I5)-I7 -> 1.0068261e+08
A9: RETENCIONES EN LA FUENTE | B9: =+F7 -> 82732517
A10: ANTICIPO DEL AÑO 2024 | B10: 13745000
A11: TOTAL A PAGAR | B11: =+B7+B8-B9-B10 -> 4.0309212e+08 | C11: =+B11/B3 -> 0.12424195
A12: CUOTA 1 | B12: =+B11*50% -> 2.0154606e+08
A13: CUOTA 2 | B13: =+B11*50% -> 2.0154606e+08
A17: TOTAL PAGADO AÑO 2024 | B17: 56246000 | D17: =+B11 -> 4.0309212e+08 | E17: 2025
A18: INGRESOS 2024 | B18: 1899158000
A19: INGRESOS 2025 | B19: =+B3 -> 3.2444124e+09 | D19: =+D17-B17 -> 3.4684612e+08 | E19: =+D19/B17 -> 6.1665917
A20: INCREMENTO INGRESOS | B20: =+(B19/B18)-1 -> 0.70834255
A22: INCREMENTO IMPUESTO DE RENTA | B22: =+(F5/F4)-1 -> 3.4212704
A25: PROYECCIÓN CIERRE AJUSTADO - ESCENARIO 1 | E25: CÁLCULO ANTICIPO
A26: COSTO AL 45%
A27: INGRESOS | B27: =+B3 -> 3.2444124e+09 | C27: =+B27/B27 -> 1 | E27: OPCIÓN 1 | H27: OPCIÓN 2
A28: COSTO | B28: =+B27*C28 -> 1.4599856e+09 | C28: 0.45 | E28: Impuesto de Renta 2024 | F28: 90220000 | H28: Promedio 2024 - 2025 | I28: =+(F28+F29)/2 -> 1.7177997e+08
A29: GASTOS DE ADMINISTRACIÓN Y VENTAS | B29: =+B5 -> 1.0605984e+09 | C29: =+B29/B27 -> 0.3269 | E29: Impuesto de Renta 2025 | F29: =+B31 -> 2.5333994e+08 | I29: 0.75
A30: UTILIDAD | B30: =+B27-B28-B29 -> 7.2382841e+08 | C30: =+B30/B27 -> 0.2231 | E30: OPCIÓN 1 | F30: 0.75
A31: IMPUESTO DE RENTA 35% | B31: =+B30*35% -> 2.5333994e+08 | E31: Menos Retención en la Fuente | F31: =+((B27*2.5%))*80%+(B27*0.55%) -> 82732517 | H31: Menos Retención en la Fuente | I31: =+F31 -> 82732517
A32: ANTICIPO AÑO 2025 | B32: =+SMALL(E32:I32,1) -> 46102462 | E32: ANTICIPO OPCIÓN 1 | F32: =+(F29*F30)-F31 -> 1.0727244e+08 | H32: ANTICIPO OPCIÓN 2 | I32: =+(I28*I29)-I31 -> 46102462
A33: RETENCIONES EN LA FUENTE | B33: =+F31 -> 82732517
A34: ANTICIPO DEL AÑO 2024 | B34: 13745000
A35: TOTAL A PAGAR | B35: =+B31+B32-B33-B34 -> 2.0296489e+08
A36: CUOTA 1 | B36: =+B35*50% -> 1.0148244e+08
A37: CUOTA 2 | B37: =+B35*50% -> 1.0148244e+08
A39: TOTAL PAGADO AÑO 2024 | B39: 56246000
A40: INGRESOS 2024 | B40: 1899158000
A41: INGRESOS 2025 | B41: =+B27 -> 3.2444124e+09
A42: INCREMENTO INGRESOS | B42: =+(B41/B40)-1 -> 0.70834255
A44: INCREMENTO IMPUESTO DE RENTA | B44: =+(B31/F28)-1 -> 1.8080242
A45: BENEFICIO DE AUDITORÍA | B45: 6 MESES
A51: PROYECCIÓN CIERRE AJUSTADO - ESCENARIO 3 | E51: CÁLCULO ANTICIPO
A52: COSTO AL 40%
A53: INGRESOS | B53: =+B27 -> 3.2444124e+09 | C53: =+B53/B53 -> 1 | E53: OPCIÓN 1 | H53: OPCIÓN 2
A54: COSTO | B54: =+B53*C54 -> 1.557318e+09 | C54: 0.48 | E54: Impuesto de Renta 2024 | F54: 90220000 | H54: Promedio 2024 - 2025 | I54: =+(F54+F55)/2 -> 1.4163127e+08
A55: GASTOS DE ADMINISTRACIÓN Y VENTAS | B55: =+B53*C55 -> 1.1355443e+09 | C55: 0.35 | E55: Impuesto de Renta 2025 | F55: =+B57 -> 1.9304254e+08 | I55: 0.75
A56: UTILIDAD | B56: =+B53-B54-B55 -> 5.5155011e+08 | C56: =+B56/B53 -> 0.17 | E56: OPCIÓN 1 | F56: 0.75
A57: IMPUESTO DE RENTA 35% | B57: =+B56*35% -> 1.9304254e+08 | E57: Menos Retención en la Fuente | F57: =+F31 -> 82732517 | H57: Menos Retención en la Fuente | I57: =+F57 -> 82732517
A58: ANTICIPO AÑO 2025 | B58: =+SMALL(E58:I58,1) -> 23490935 | E58: ANTICIPO OPCIÓN 1 | F58: =+(F55*F56)-F57 -> 62049388 | H58: ANTICIPO OPCIÓN 2 | I58: =+(I54*I55)-I57 -> 23490935
A59: RETENCIONES EN LA FUENTE | B59: =+F57 -> 82732517
A60: ANTICIPO DEL AÑO 2024 | B60: 13745000
A61: TOTAL A PAGAR | B61: =+B57+B58-B59-B60 -> 1.2005596e+08 | C61: =+B61-F54 -> 29835958 | D61: =+C61/F54 -> 0.33070226
A62: CUOTA 1 | B62: =+B61*50% -> 60027979
A63: CUOTA 2 | B63: =+B61*50% -> 60027979
A65: TOTAL PAGADO AÑO 2024 | B65: 56246000 | E65: UNIAGRO 2023 | F65: 88990000 | G65: 1105400000 | H65: =+F65/G65 -> 0.080504795
A66: INGRESOS 2024 | B66: 1899158000 | E66: UNIAGRO 2024 | F66: 202935000 | G66: 1899158000 | H66: =+F66/G66 -> 0.10685525
A67: INGRESOS 2025 | B67: =+B53 -> 3.2444124e+09 | E67: UNIAGRO 2025 | F67: ?
A68: INCREMENTO INGRESOS | B68: =+(B67/B66)-1 -> 0.70834255
A70: INCREMENTO IMPUESTO DE RENTA | B70: =+(B57/F54)-1 -> 1.1396868
A71: BENEFICIO DE AUDITORÍA | B71: 6 MESES
A73: =+B53*3.3/1000 -> 10706561 | B73: ICA
A77: COSTO A JUNIO 2025 | B77: =+'E.R. PPTO - REAL'!AG16 -> #REF! | C77: 6 MESES | D77: =+B77/E77 -> #REF! | E77: =+'PROYECCIÓN JUNIO 2025'!B3 -> 1.7936419e+09 | F77: INGRESO A JUNIO
A78: COSTO PROYECTADO | B78: =+B4 -> 1.0441368e+09 | D78: =+B78/E78 -> 0.32182616 | E78: =+B3 -> 3.2444124e+09 | F78: INGRESO CIERRE
A80: EXCEDENTE REQUERIDO PARA COSTO AL 48% | B80: =+B54-B78 -> 5.1318116e+08
A81: EXCEDENTE REQUERIDO PARA COSTO AL 45% | B81: =+B28-B4 -> 4.1584878e+08
A85: PROYECCIÓN CIERRE CONTABLE 2025 | E85: CÁLCULO ANTICIPO
A87: INGRESOS | B87: =3744412422.86382-500000000 -> 3.2444124e+09 | C87: =+B87/B87 -> 1 | E87: OPCIÓN 1 | H87: OPCIÓN 2
A88: COSTO | B88: =+B87*45% -> 1.4599856e+09 | C88: =+B88/B87 -> 0.45 | D88: =+B88-B4 -> 4.1584878e+08 | E88: Impuesto de Renta 2024 | F88: 90220000 | H88: Promedio 2024 - 2025 | I88: =+(F88+F89)/2 -> 1.0877997e+08
A89: GASTOS DE ADMINISTRACIÓN Y VENTAS | B89: =+(B87*C89)+360000000 -> 1.4205984e+09 | C89: 0.3269 | E89: Impuesto de Renta 2025 | F89: =+B91 -> 1.2733994e+08 | I89: 0.75
A90: UTILIDAD | B90: =+B87-B88-B89 -> 3.6382841e+08 | C90: =+B90/B87 -> 0.11214 | E90: OPCIÓN 1 | F90: 0.75
A91: IMPUESTO DE RENTA 35% | B91: =+B90*35% -> 1.2733994e+08 | C91: =+(B91/F88)-1 -> 0.41143809 | E91: Menos Retención en la Fuente | F91: =+F65 -> 88990000 | H91: Menos Retención en la Fuente | I91: =+F91 -> 88990000
A92: ANTICIPO AÑO 2025 | B92: 0 | E92: ANTICIPO OPCIÓN 1 | F92: =+(F89*F90)-F91 -> 6514958 | H92: ANTICIPO OPCIÓN 2 | I92: =+(I88*I89)-I91 -> -7405021
A93: RETENCIONES EN LA FUENTE | B93: =+F91 -> 88990000
A94: ANTICIPO DEL AÑO 2024 | B94: 13745000
A95: TOTAL A PAGAR | B95: =+B91+B92-B93-B94 -> 24604944 | C95: =+B95/B87 -> 0.0075837905
A96: CUOTA 1 | B96: =+B95*50% -> 12302472
A97: CUOTA 2 | B97: =+B95*50% -> 12302472
E98: UNIAGRO - AGOSTO | F98: 110000000
E99: UNIAGRO - SEPTIEMBRE | F99: 95000000
E100: UNIAGRO - OCTUBRE | F100: 33000000
A101: TOTAL PAGADO AÑO 2024 | B101: 56246000 | E101: UNIAGRO - NOVIEMBRE | F101: 32000000
A102: INGRESOS 2024 | B102: 1899158000 | E102: TOTAL | F102: =+SUM(F98:F101) -> 270000000
A103: INGRESOS 2025 | B103: =+B87 -> 3.2444124e+09
A104: INCREMENTO INGRESOS | B104: =+(B103/B102)-1 -> 0.70834255 | E104: COSTO NUEVAS MP Y OTROS | F104: =+D88-F102 -> 1.4584878e+08
A106: INCREMENTO IMPUESTO DE RENTA | B106: =+(F89/F88)-1 -> 0.41143809

Sheet PROYECCIÓN JUNIO 2025
A1: PROYECCIÓN CIERRE CONTABLE 2025 | E1: CÁLCULO ANTICIPO
A3: INGRESOS | B3: 1.7936419e+09 | C3: =+B3/B3 -> 1 | E3: OPCIÓN 1 | H3: OPCIÓN 2
A4: COSTO | B4: 390859732 | C4: =+B4/B3 -> 0.21791402 | E4: Impuesto de Renta 2024 | F4: 90220000 | H4: Promedio 2023 - 2024 | I4: =+(F4+F5)/2 -> 1.8911444e+08
A5: GASTOS DE ADMINISTRACIÓN Y VENTAS | B5: =586416134.14-6516448 -> 5.7989969e+08 | C5: =+B5/B3 -> 0.3233085 | E5: Impuesto de Renta 2025 | F5: =+B7 -> 2.8800888e+08 | I5: 0.75
A6: UTILIDAD | B6: =+B3-B4-B5 -> 8.2288253e+08 | C6: =+B6/B3 -> 0.45877748 | E6: OPCIÓN 1 | F6: 0.75
A7: IMPUESTO DE RENTA 35% | B7: =+B6*35% -> 2.8800888e+08 | E7: Menos Retención en la Fuente | F7: =(+B3*2.5%)*80% -> 35872839 | H7: Menos Retención en la Fuente | I7: =+F7 -> 35872839
A8: ANTICIPO AÑO 2025 | B8: =+SMALL(E8:I8,1) -> 1.0596299e+08 | E8: ANTICIPO OPCIÓN 1 | F8: =+(F5*F6)-F7 -> 1.8013382e+08 | H8: ANTICIPO OPCIÓN 2 | I8: =+(I4*I5)-I7 -> 1.0596299e+08
A9: RETENCIONES EN LA FUENTE | B9: =+F7+'BASE DE DATOS BG'!I4405 -> 47293792
A10: ANTICIPO PAGADO EN 2024 | B10: 13745000
A11: TOTAL A PAGAR | B11: =+B7+B8-B9-B10 -> 3.3293309e+08 | C11: =+B11/B3 -> 0.18561848
A12: CUOTA 1 | B12: =+B11*50% -> 1.6646654e+08 | E12: 378012467 | F12: INVENTARIO A JUNIO
A13: CUOTA 2 | B13: =+B11*50% -> 1.6646654e+08
J18: =94/2 -> 47

Sheet PROYECCIÓN CIERRE 2025 TENTATIV
A1: PROYECCIÓN CIERRE CONTABLE 2025 | E1: CÁLCULO ANTICIPO
A2: REAL
A3: INGRESOS | B3: =3744412422.86382-500000000 -> 3.2444124e+09 | C3: =+B3/B3 -> 1 | E3: OPCIÓN 1 | H3: OPCIÓN 2
A4: COSTO | B4: =+B3*C4 -> #REF! | C4: =+'E.R. PPTO - REAL'!#REF! -> #REF! | E4: Impuesto de Renta 2024 | F4: 90220000 | H4: Promedio 2023 - 2024 | I4: =+(F4+F5)/2 -> #REF!
A5: GASTOS DE ADMINISTRACIÓN Y VENTAS | B5: =+(B3*C5) -> #REF! | C5: =+'E.R. PPTO - REAL'!#REF! -> #REF! | E5: Impuesto de Renta 2025 | F5: =+B7 -> #REF! | I5: 0.75
A6: UTILIDAD | B6: =+B3-B4-B5 -> #REF! | C6: =+B6/B3 -> #REF! | E6: OPCIÓN 1 | F6: 0.75
A7: IMPUESTO DE RENTA 35% | B7: =+B6*35% -> #REF! | E7: Menos Retención en la Fuente | F7: =(+B3*(2.5%))*80%+(B3*0.55%) -> 82732517 | H7: Menos Retención en la Fuente | I7: =+F7 -> 82732517
A8: ANTICIPO AÑO 2025 | B8: =+SMALL(E8:I8,1) -> #REF! | E8: ANTICIPO OPCIÓN 1 | F8: =+(F5*F6)-F7 -> #REF! | H8: ANTICIPO OPCIÓN 2 | I8: =+(I4*I5)-I7 -> #REF!
A9: RETENCIONES EN LA FUENTE | B9: =+F7 -> 82732517
A10: ANTICIPO DEL AÑO 2024 | B10: 13745000
A11: TOTAL A PAGAR | B11: =+B7+B8-B9-B10 -> #REF! | C11: =+B11/B3 -> #REF!
A12: CUOTA 1 | B12: =+B11*50% -> #REF!
A13: CUOTA 2 | B13: =+B11*50% -> #REF!
A17: TOTAL PAGADO AÑO 2024 | B17: 56246000 | D17: =+B11 -> #REF! | E17: 2025
A18: INGRESOS 2024 | B18: 1899158000
A19: INGRESOS 2025 | B19: =+B3 -> 3.2444124e+09 | D19: =+D17-B17 -> #REF! | E19: =+D19/B17 -> #REF!
A20: INCREMENTO INGRESOS | B20: =+(B19/B18)-1 -> 0.70834255
A22: INCREMENTO IMPUESTO DE RENTA | B22: =+(F5/F4)-1 -> #REF!
A25: PROYECCIÓN CIERRE AJUSTADO - ESCENARIO 1 | E25: CÁLCULO ANTICIPO
A26: COSTO AL 45%
A27: INGRESOS | B27: =+B3 -> 3.2444124e+09 | C27: =+B27/B27 -> 1 | E27: OPCIÓN 1 | H27: OPCIÓN 2
A28: COSTO | B28: =+B27*C28 -> 1.4599856e+09 | C28: 0.45 | E28: Impuesto de Renta 2024 | F28: 90220000 | H28: Promedio 2024 - 2025 | I28: =+(F28+F29)/2 -> #REF!
A29: GASTOS DE ADMINISTRACIÓN Y VENTAS | B29: =+B5 -> #REF! | C29: =+B29/B27 -> #REF! | E29: Impuesto de Renta 2025 | F29: =+B31 -> #REF! | I29: 0.75
A30: UTILIDAD | B30: =+B27-B28-B29 -> #REF! | C30: =+B30/B27 -> #REF! | E30: OPCIÓN 1 | F30: 0.75
A31: IMPUESTO DE RENTA 35% | B31: =+B30*35% -> #REF! | E31: Menos Retención en la Fuente | F31: =+((B27*2.5%))*80%+(B27*0.55%) -> 82732517 | H31: Menos Retención en la Fuente | I31: =+F31 -> 82732517
A32: ANTICIPO AÑO 2025 | B32: =+SMALL(E32:I32,1) -> #REF! | E32: ANTICIPO OPCIÓN 1 | F32: =+(F29*F30)-F31 -> #REF! | H32: ANTICIPO OPCIÓN 2 | I32: =+(I28*I29)-I31 -> #REF!
A33: RETENCIONES EN LA FUENTE | B33: =+F31 -> 82732517
A34: ANTICIPO DEL AÑO 2024 | B34: 13745000
A35: TOTAL A PAGAR | B35: =+B31+B32-B33-B34 -> #REF!
A36: CUOTA 1 | B36: =+B35*50% -> #REF!
A37: CUOTA 2 | B37: =+B35*50% -> #REF!
A39: TOTAL PAGADO AÑO 2024 | B39: 56246000
A40: INGRESOS 2024 | B40: 1899158000
A41: INGRESOS 2025 | B41: =+B27 -> 3.2444124e+09
A42: INCREMENTO INGRESOS | B42: =+(B41/B40)-1 -> 0.70834255
A44: INCREMENTO IMPUESTO DE RENTA | B44: =+(B31/F28)-1 -> #REF!
A45: BENEFICIO DE AUDITORÍA | B45: 6 MESES
A51: PROYECCIÓN CIERRE AJUSTADO - ESCENARIO 3 | E51: CÁLCULO ANTICIPO
A52: COSTO AL 40%
A53: INGRESOS | B53: =+B27 -> 3.2444124e+09 | C53: =+B53/B53 -> 1 | E53: OPCIÓN 1 | H53: OPCIÓN 2
A54: COSTO | B54: =+B53*C54 -> 1.557318e+09 | C54: 0.48 | E54: Impuesto de Renta 2024 | F54: 90220000 | H54: Promedio 2024 - 2025 | I54: =+(F54+F55)/2 -> 1.4163127e+08
A55: GASTOS DE ADMINISTRACIÓN Y VENTAS | B55: =+B53*C55 -> 1.1355443e+09 | C55: 0.35 | E55: Impuesto de Renta 2025 | F55: =+B57 -> 1.9304254e+08 | I55: 0.75
A56: UTILIDAD | B56: =+B53-B54-B55 -> 5.5155011e+08 | C56: =+B56/B53 -> 0.17 | E56: OPCIÓN 1 | F56: 0.75
A57: IMPUESTO DE RENTA 35% | B57: =+B56*35% -> 1.9304254e+08 | E57: Menos Retención en la Fuente | F57: =+F31 -> 82732517 | H57: Menos Retención en la Fuente | I57: =+F57 -> 82732517
A58: ANTICIPO AÑO 2025 | B58: =+SMALL(E58:I58,1) -> 23490935 | E58: ANTICIPO OPCIÓN 1 | F58: =+(F55*F56)-F57 -> 62049388 | H58: ANTICIPO OPCIÓN 2 | I58: =+(I54*I55)-I57 -> 23490935
A59: RETENCIONES EN LA FUENTE | B59: =+F57 -> 82732517
A60: ANTICIPO DEL AÑO 2024 | B60: 13745000
A61: TOTAL A PAGAR | B61: =+B57+B58-B59-B60 -> 1.2005596e+08 | C61: =+B61-F54 -> 29835958 | D61: =+C61/F54 -> 0.33070226
A62: CUOTA 1 | B62: =+B61*50% -> 60027979
A63: CUOTA 2 | B63: =+B61*50% -> 60027979
A65: TOTAL PAGADO AÑO 2024 | B65: 56246000 | E65: UNIAGRO 2023 | F65: 88990000 | G65: 1105400000 | H65: =+F65/G65 -> 0.080504795
A66: INGRESOS 2024 | B66: 1899158000 | E66: UNIAGRO 2024 | F66: 202935000 | G66: 1899158000 | H66: =+F66/G66 -> 0.10685525
A67: INGRESOS 2025 | B67: =+B53 -> 3.2444124e+09 | E67: UNIAGRO 2025 | F67: ?
A68: INCREMENTO INGRESOS | B68: =+(B67/B66)-1 -> 0.70834255
A70: INCREMENTO IMPUESTO DE RENTA | B70: =+(B57/F54)-1 -> 1.1396868
A71: BENEFICIO DE AUDITORÍA | B71: 6 MESES
A73: =+B53*3.3/1000 -> 10706561 | B73: ICA
A77: COSTO A JUNIO 2025 | B77: =+'E.R. PPTO - REAL'!AG16 -> #REF! | C77: 6 MESES | D77: =+B77/E77 -> #REF! | E77: =+'PROYECCIÓN JUNIO 2025'!B3 -> 1.7936419e+09 | F77: INGRESO A JUNIO
A78: COSTO PROYECTADO | B78: =+B4 -> #REF! | D78: =+B78/E78 -> #REF! | E78: =+B3 -> 3.2444124e+09 | F78: INGRESO CIERRE
A80: EXCEDENTE REQUERIDO PARA COSTO AL 48% | B80: =+B54-B78 -> #REF!
A81: EXCEDENTE REQUERIDO PARA COSTO AL 45% | B81: =+B28-B4 -> #REF!
A85: PROYECCIÓN CIERRE CONTABLE 2025 | E85: CÁLCULO ANTICIPO
A87: INGRESOS | B87: =3744412422.86382-500000000 -> 3.2444124e+09 | C87: =+B87/B87 -> 1 | E87: OPCIÓN 1 | H87: OPCIÓN 2
A88: COSTO | B88: =+B87*45%+56000000 -> 1.5159856e+09 | C88: =+B88/B87 -> 0.46726044 | D88: =+B88-B4 -> #REF! | E88: Impuesto de Renta 2024 | F88: 90220000 | H88: Promedio 2024 - 2025 | I88: =+(F88+F89)/2 -> 1.0877997e+08
A89: GASTOS DE ADMINISTRACIÓN Y VENTAS | B89: =+(B87*C89)+304000000 -> 1.3645984e+09 | C89: 0.3269 | D89: =+B89/B87 -> 0.42059955 | E89: Impuesto de Renta 2025 | F89: =+B91 -> 1.2733994e+08 | I89: 0.75
A90: UTILIDAD | B90: =+B87-B88-B89 -> 3.6382841e+08 | C90: =+B90/B87 -> 0.11214 | E90: OPCIÓN 1 | F90: 0.75
A91: IMPUESTO DE RENTA 35% | B91: =+B90*35% -> 1.2733994e+08 | C91: =+(B91/F88)-1 -> 0.41143809 | E91: Menos Retención en la Fuente | F91: =+F65 -> 88990000 | H91: Menos Retención en la Fuente | I91: =+F91 -> 88990000
A92: ANTICIPO AÑO 2025 | B92: 0 | E92: ANTICIPO OPCIÓN 1 | F92: =+(F89*F90)-F91 -> 6514958 | H92: ANTICIPO OPCIÓN 2 | I92: =+(I88*I89)-I91 -> -7405021
A93: RETENCIONES EN LA FUENTE | B93: =+F91 -> 88990000
A94: ANTICIPO DEL AÑO 2024 | B94: 13745000
A95: TOTAL A PAGAR | B95: =+B91+B92-B93-B94 -> 24604944 | C95: =+B95/B87 -> 0.0075837905 | E95: =+GETPIVOTDATA("VALOR",'E.R. PPTO - REAL'!$S$11,"CLASE","COSTO") -> #REF! | F95: =+B88-E95 -> #REF!
A96: CUOTA 1 | B96: =+B95*50% -> 12302472
A97: CUOTA 2 | B97: =+B95*50% -> 12302472
E98: UNIAGRO - AGOSTO | F98: 115000000
E99: UNIAGRO - SEPTIEMBRE | F99: 104400000
E100: UNIAGRO - OCTUBRE | F100: =33000000+28300000 -> 61300000
A101: TOTAL PAGADO AÑO 2024 | B101: 56246000 | E101: UNIAGRO - NOVIEMBRE | F101: =18000000+29000000+28300000 -> 75300000
A102: INGRESOS 2024 | B102: 1899158000 | E102: TOTAL | F102: =+SUM(F98:F101) -> 356000000 | G102: =+F102/B87 -> 0.10972711 | H102: =+B87*11% -> 3.5688537e+08 | I102: =+H102-F102 -> 885366.52
A103: INGRESOS 2025 | B103: =+B87 -> 3.2444124e+09 | I103: =+I102/2 -> 442683.26
A104: INCREMENTO INGRESOS | B104: =+(B103/B102)-1 -> 0.70834255 | E104: COSTO NUEVAS MP Y OTROS | F104: =+D88-F102 -> #REF!
A106: INCREMENTO IMPUESTO DE RENTA | B106: =+(F89/F88)-1 -> 0.41143809

Sheet PROYECCIÓN CIERRE 2025 FINAL
A1: PROYECCIÓN CIERRE CONTABLE 2025 | E1: CÁLCULO ANTICIPO
A2: REAL
A3: INGRESOS | B3: =+GETPIVOTDATA("VALOR",'E.R. PPTO - REAL'!$S$11,"CLASE","INGRESO") -> #REF! | C3: =+B3/B3 -> #REF! | E3: OPCIÓN 1 | H3: OPCIÓN 2
A4: COSTO | B4: =+GETPIVOTDATA("VALOR",'E.R. PPTO - REAL'!$S$11,"CLASE","COSTO") -> #REF! | C4: =+'E.R. PPTO - REAL'!AG16 -> #REF! | E4: Impuesto de Renta 2024 | F4: 90220000 | H4: Promedio 2023 - 2024 | I4: =+(F4+F5)/2 -> #REF!
A5: GASTOS DE ADMINISTRACIÓN Y VENTAS | B5: =+GETPIVOTDATA("VALOR",'E.R. PPTO - REAL'!$S$11,"CLASE","GASTO","GRUPO","OPERACIONAL DE ADMINISTRACIÓN")+GETPIVOTDATA("VALOR",'E.R. PPTO - REAL'!$S$11,"CLASE","GASTO","GRUPO","GASTOS DE VENTAS")+48537667.24 -> #REF! | C5: =+'E.R. PPTO - REAL'!AG17 -> #REF! | E5: Impuesto de Renta 2025 | F5: =+B7 -> #REF! | I5: 0.75
A6: UTILIDAD | B6: =+B3-B4-B5 -> #REF! | C6: =+B6/B3 -> #REF! | D6: =+B6*56.42% -> #REF! | E6: OPCIÓN 1 | F6: 0.75
A7: IMPUESTO DE RENTA 35% | B7: =+B6*35% -> #REF! | E7: Menos Retención en la Fuente | F7: =70150552-5000000 -> 65150552 | H7: Menos Retención en la Fuente | I7: =+F7 -> 65150552
A8: ANTICIPO AÑO 2025 | B8: =+SMALL(E8:I8,1) -> #REF! | E8: ANTICIPO OPCIÓN 1 | F8: =+(F5*F6)-F7 -> #REF! | H8: ANTICIPO OPCIÓN 2 | I8: =+(I4*I5)-I7 -> #REF!
A9: RETENCIONES EN LA FUENTE | B9: =+F7 -> 65150552
A10: ANTICIPO DEL AÑO 2024 | B10: 13745000
A11: TOTAL A PAGAR | B11: =+B7+B8-B9-B10 -> #REF! | C11: =+B11/B3 -> #REF!
A12: CUOTA 1 | B12: =+B11*50% -> #REF! | E12: BENEFICIO DE AUDITORIA | F12: =(+B7-F4)/F4 -> #REF!
A13: CUOTA 2 | B13: =+B11*50% -> #REF!
A17: TOTAL PAGADO AÑO 2024 | B17: 56246000 | D17: =+B11 -> #REF! | E17: 2025
A18: TOTAL A PAGAR AÑO 2025 (SUJETO A RECAUDO CERTIFICADOS) | B18: =+B11 -> #REF!
A19: INGRESOS 2024 | B19: 1899158000
A20: INGRESOS 2025 | B20: =+B3 -> #REF!
A21: INCREMENTO INGRESOS | B21: =+(B20/B19)-1 -> #REF!
A23: INCREMENTO IMPUESTO DE RENTA | B23: =+(F5/F4)-1 -> #REF! | D23: =+D17-B17 -> #REF!

Sheet NOTAS REUNIÓN 310725
A1: NOTAS
A3: NUEVOS PRODUCTOS
A4: REGISTROS INVIMA | B4: 30000000
A5: COSTO MP + EMPAQUE | B5: 50000000
A6: LANZAMIENTO DE PRODUCTO | B6: 10000000

Sheet Hoja2
A1: AÑO | B1: 2019 | E1: SELECCIONE
A2: CENTRO DE COSTO | B2: (Varios elementos)
A3: ESTADO | B3: PRESUPUESTO
A5: PRESUPUESTO | B5: PERIODO
A6: CUENTA | B6: ENERO | C6: FEBRERO | D6: MARZO | E6: TOTAL PRESUPUESTO
A7: INGRESO | B7: 2297200 | C7: 4012400 | D7: 3696340 | E7: 10005940
A8: INGRESO OPERACIONAL | B8: 2297200 | C8: 4012400 | D8: 3696340 | E8: 10005940
A9: COMERCIO AL POR MAYOR Y AL POR MENOR | B9: 2297200 | C9: 4012400 | D9: 3696340 | E9: 10005940
A10: COSTO | B10: 395000 | C10: 650000 | D10: 350000 | E10: 1395000
A11: COSTO DE VENTA | B11: 395000 | C11: 650000 | D11: 350000 | E11: 1395000
A12: COMERCIO AL POR MAYOR Y AL POR MENOR | B12: 395000 | C12: 650000 | D12: 350000 | E12: 1395000
A13: GASTO | B13: 2755601.6 | C13: 2755601.6 | D13: 2755601.6 | E13: 8266804.8
A14: OPERACIONAL DE ADMINISTRACIÓN | B14: 2755601.6 | C14: 2755601.6 | D14: 2755601.6 | E14: 8266804.8
A15: GASTOS DE PERSONAL | B15: 2184980.6 | C15: 2184980.6 | D15: 2184980.6 | E15: 6554941.8
A16: HONORARIOS | B16: 390621 | C16: 390621 | D16: 390621 | E16: 1171863
A17: IMPUESTOS
A18: ARRENDAMIENTOS
A19: SERVICIOS | B19: 150000 | C19: 150000 | D19: 150000 | E19: 450000
A20: GASTOS LEGALES
A21: DIVERSOS | B21: 30000 | C21: 30000 | D21: 30000 | E21: 90000
A22: DE VENTAS
A23: DIVERSOS
A24: NO OPERACIONALES
A25: FINANCIEROS
A26: EXTRAORDINARIOS
A27: DIVERSOS
A28: UTILIDAD Y/O PÉRDIDA | B28: =+GETPIVOTDATA("VALOR",$A$11,"MES","ENERO","CLASE","INGRESO")-GETPIVOTDATA("VALOR",$A$11,"MES","ENERO","CLASE","COSTO")-GETPIVOTDATA("VALOR",$A$11,"MES","ENERO","CLASE","GASTO") -> -853401.61 | C28: =+GETPIVOTDATA("VALOR",$A$11,"MES","FEBRERO","CLASE","INGRESO")-GETPIVOTDATA("VALOR",$A$11,"MES","FEBRERO","CLASE","COSTO")-GETPIVOTDATA("VALOR",$A$11,"MES","FEBRERO","CLASE","GASTO") -> 606798.39 | D28: =+GETPIVOTDATA("VALOR",$A$11,"MES","MARZO","CLASE","INGRESO")-GETPIVOTDATA("VALOR",$A$11,"MES","MARZO","CLASE","COSTO")-GETPIVOTDATA("VALOR",$A$11,"MES","MARZO","CLASE","GASTO") -> 590738.39 | E28: =+GETPIVOTDATA("VALOR",$A$11,"CLASE","INGRESO")-GETPIVOTDATA("VALOR",$A$11,"CLASE","COSTO")-GETPIVOTDATA("VALOR",$A$11,"CLASE","GASTO") -> 344135.17

Sheet PROYECCIÓN CIERRE DIC. 2021
A1: PANGEA NATURAL PRODUCTS S.A.S.
A2: PROYECCIÓN CIERRE DICIEMBRE 2021
A6: AÑO | B6: 2021
A7: CENTRO DE COSTO | B7: (Varios elementos) | P7: REAL
A8: ESTADO | B8: REAL | P8: =+P9/P12 -> 0.16447323
A9: UTILIDAD Y/O PÉRDIDA | B9: =+GETPIVOTDATA("VALOR",$A$10,"MES","ENERO","CLASE","INGRESO")-GETPIVOTDATA("VALOR",$A$10,"MES","ENERO","CLASE","COSTO")-GETPIVOTDATA("VALOR",$A$10,"MES","ENERO","CLASE","GASTO") -> 7291266 | C9: =+GETPIVOTDATA("VALOR",$A$10,"MES","FEBRERO","CLASE","INGRESO")-GETPIVOTDATA("VALOR",$A$10,"MES","FEBRERO","CLASE","COSTO")-GETPIVOTDATA("VALOR",$A$10,"MES","FEBRERO","CLASE","GASTO") -> 6559927.2 | D9: =+GETPIVOTDATA("VALOR",$A$10,"MES","MARZO","CLASE","INGRESO")-GETPIVOTDATA("VALOR",$A$10,"MES","MARZO","CLASE","COSTO")-GETPIVOTDATA("VALOR",$A$10,"MES","MARZO","CLASE","GASTO") -> 10493418 | E9: =+GETPIVOTDATA("VALOR",$A$10,"MES","ABRIL","CLASE","INGRESO")-GETPIVOTDATA("VALOR",$A$10,"MES","ABRIL","CLASE","COSTO")-GETPIVOTDATA("VALOR",$A$10,"MES","ABRIL","CLASE","GASTO") -> 7526166 | F9: =+GETPIVOTDATA("VALOR",$A$10,"MES","MAYO","CLASE","INGRESO")-GETPIVOTDATA("VALOR",$A$10,"MES","MAYO","CLASE","COSTO")-GETPIVOTDATA("VALOR",$A$10,"MES","MAYO","CLASE","GASTO") -> 7780923.3 | G9: =+GETPIVOTDATA("VALOR",$A$10,"MES","JUNIO","CLASE","INGRESO")-GETPIVOTDATA("VALOR",$A$10,"MES","JUNIO","CLASE","COSTO")-GETPIVOTDATA("VALOR",$A$10,"MES","JUNIO","CLASE","GASTO") -> 9761695 | H9: =+GETPIVOTDATA("VALOR",$A$10,"MES","JULIO","CLASE","INGRESO")-GETPIVOTDATA("VALOR",$A$10,"MES","JULIO","CLASE","COSTO")-GETPIVOTDATA("VALOR",$A$10,"MES","JULIO","CLASE","GASTO") -> 8176452.8 | I9: =+GETPIVOTDATA("VALOR",$A$10,"MES","AGOSTO","CLASE","INGRESO")-GETPIVOTDATA("VALOR",$A$10,"MES","AGOSTO","CLASE","COSTO")-GETPIVOTDATA("VALOR",$A$10,"MES","AGOSTO","CLASE","GASTO") -> 3330135.5 | J9: =+GETPIVOTDATA("VALOR",$A$10,"MES","SEPTIEMBRE","CLASE","INGRESO")-GETPIVOTDATA("VALOR",$A$10,"MES","SEPTIEMBRE","CLASE","COSTO")-GETPIVOTDATA("VALOR",$A$10,"MES","SEPTIEMBRE","CLASE","GASTO") -> -14400132 | K9: =+K12-K15-K17 -> -8119306.4 | L9: =+L12-L15-L17 -> -301650.1 | M9: =+M12-M15-M17 -> -32239556 | N9: =+N12-N15-N17 -> 5859338.6 | P9: =+P12-P15-P17 -> 62381339 | R9: PROYECCIÓN IMPUESTO DE RENTA 2021 | T9: SIN GESTIÓN
A10: COMPORTAMIENTO REAL | B10: PERIODO | R10: UTILIDAD FISCAL | S10: =+N9+N20+3000000 -> 20540146 | T10: =+N9+33750000+N20+3000000+5334000 -> 59624146 | U10: =+T10-3000000+(700000*12) -> 65024146
A11: CUENTA | B11: ENERO | C11: FEBRERO | D11: MARZO | E11: ABRIL | F11: MAYO | G11: JUNIO | H11: JULIO | I11: AGOSTO | J11: SEPTIEMBRE | K11: OCTUBRE | L11: NOVIEMBRE | M11: DICIEMBRE | N11: TOTAL | O11: =+N13+O14 -> 3.7927959e+08 | R11: IMPUESTO RENTA 31% | S11: =+S10*31% -> 6367445.1 | T11: =+T10*31% -> 18483485
A12: INGRESO | B12: 23566695 | C12: 24367830 | D12: 30112667 | E12: 25718752 | F12: 33739236 | G12: 33736754 | H12: 34656350 | I12: 27849166 | J12: 31200136 | K12: 38404950 | L12: 36867504 | M12: 30659547 | N12: =+SUM(B12:M12) -> 3.7087959e+08 | O12: =+N12/N12 -> 1 | P12: =+SUM(P13:P14) -> 3.7927959e+08 | R12: AUTORRETENCIÓN | S12: 1484896 | T12: 1484896
A13: INGRESO OPERACIONAL | B13: 23565829 | C13: 24367830 | D13: 30112163 | E13: 25717564 | F13: 33738468 | G13: 33736108 | H13: 34656349 | I13: 27797034 | J13: 31198164 | K13: 38396333 | L13: 36385057 | M13: 30608260 | N13: =+SUM(B13:M13) -> 3.7027916e+08 | P13: =+N13 -> 3.7027916e+08 | R13: ANTICIPO RETEFUENTE | S13: 3387243 | T13: 3387243 | U13: AHORRO EN IMPUESTO A CARGO
A14: INGRESO NO OPERACIONAL | B14: 866 | D14: 504.44 | E14: 1188 | F14: 767.28 | G14: 646 | H14: 1.28 | I14: 52132.61 | J14: 1972.25 | K14: 8617 | L14: 482446.52 | M14: 51287.22 | N14: =+SUM(B14:M14) -> 600428.6 | O14: =+N14+(700000*12) -> 9000428.6 | P14: =+O14 -> 9000428.6 | R14: TOTAL ESTIMADO A PAGAR IMP. RENTA | S14: =+S11-S12-S13 -> 1495306.1 | T14: =+T11-T12-T13 -> 13611346 | U14: =+T14-S14 -> 12116040
A15: COSTO | B15: 7329138 | C15: 8538026 | D15: 8774320 | E15: 7696276 | F15: 10472560 | G15: 11308754 | H15: 10714108 | I15: 8750840 | J15: 26448456 | K15: 23175424 | L15: 15230915 | M15: 30801526 | N15: =+SUM(B15:M15) -> 1.6924034e+08 | O15: =+N15/N12 -> 0.45632154 | P15: =+P16 -> 1.3549034e+08
A16: COSTO DE VENTA | B16: 7329138 | C16: 8538026 | D16: 8774320 | E16: 7696276 | F16: 10472560 | G16: 11308754 | H16: 10714108 | I16: 8750840 | J16: 26448456 | K16: 23175424 | L16: 15230915 | M16: 30801526 | N16: =+SUM(B16:M16) -> 1.6924034e+08 | O16: =+N16-33750000 -> 1.3549034e+08 | P16: =+O16 -> 1.3549034e+08 | R16: ANTICIPO DE RENTA 75% | S16: =+S11*75% -> 4775583.8 | T16: =+T11*75% -> 13862614
A17: GASTO | B17: 8946290.7 | C17: 9269876.3 | D17: 10844930 | E17: 10496310 | F17: 15485752 | G17: 12666305 | H17: 15765789 | I17: 15768191 | J17: 19151812 | K17: 23348832 | L17: 21938239 | M17: 32097577 | N17: =+SUM(B17:M17) -> 1.957799e+08 | O17: =+N17/N12 -> 0.52787997 | P17: =+P18+P19+P20 -> 1.814079e+08 | R17: OPCIÓN 1 | S17: =+S13+S12 -> 4872139 | T17: =+T13+T12 -> 4872139
A18: OPERACIONAL DE ADMINISTRACIÓN | B18: 7756304 | C18: 8451524 | D18: 9331949 | E18: 7499436 | F18: 12293882 | G18: 9228143 | H18: 12600952 | I18: 12361064 | J18: 16081747 | K18: 18729601 | L18: 17267227 | M18: 18265234 | N18: =+SUM(B18:M18) -> 1.4986706e+08 | O18: =+N18-5334000 -> 1.4453306e+08 | P18: =+O18 -> 1.4453306e+08 | S18: =+S16-S17 -> -96555.169 | T18: =+T16-T17 -> 8990474.8
A19: GASTOS DE VENTAS | E19: 2200591 | F19: 2200591 | G19: 2618770 | H19: 2458917 | I19: 2714610 | J19: 2200591 | K19: 2977750 | L19: 3947107 | M19: 3875107 | N19: =+SUM(B19:M19) -> 25194034 | P19: =+N19 -> 25194034
A20: NO OPERACIONALES | B20: 1189986.7 | C20: 818352.26 | D20: 1512980.7 | E20: 796283.17 | F20: 991279.58 | G20: 819391.95 | H20: 705919.79 | I20: 692516.72 | J20: 869474.06 | K20: 1641480.6 | L20: 723904.98 | M20: 919236.38 | N20: =+SUM(B20:M20) -> 11680807 | P20: =+N20 -> 11680807 | R20: OPCIÓN 2
A21: IMPUESTO DE RENTA Y COMPLEMENTARIOS | M21: 9038000 | R21: ANTICIPO DE RENTA 75% | S21: =+(S11+3749000)*75% -> 7587333.8 | T21: =+(T11+3749000)*75% -> 16674364
S22: =+S12+S13 -> 4872139 | T22: =+T12+T13 -> 4872139
S23: =+S21-S22 -> 2715194.8 | T23: =+T21-T22 -> 11802225
R25: IMPUESTO NETO DE RENTA A PAGAR | S25: =+S14+S18 -> 1398750.9 | T25: =+T14+T18 -> 22601821
R27: 44652 | S27: =+S25*50% -> 699375.47 | T27: =+T25*50% -> 11300910
R28: 44713 | S28: =+S25*50% -> 699375.47 | T28: =+T25*50% -> 11300910
R30: PROYECCIÓN IMPUESTO DE INDUSTRIA Y COMERCIO
R31: INGRESOS TOTALES | S31: =+N12 -> 3.7087959e+08
R32: ICA ANUAL 0,33% | S32: =+S31*3.3/1000 -> 1223902.6
R33: ANTICIPO RETEICA | S33: 743491.84
R34: TOTAL ESTIMADO A PAGAR ICA 2021 | S34: =+S32-S33 -> 480410.79
R37: ESTIMADO OBLIGACIONES FISCALES A PAGAR EN ENERO 2022
R39: IVA | S39: 14680000
R40: RETEFUENTE | S40: 937000
R41: RETEICA | S41: 160000
R42: TOTAL A PAGAR | S42: =+SUM(S39:S41) -> 15777000

Sheet PROYECCIÓN CIERRE DIC. 2021 (2
A1: PANGEA NATURAL PRODUCTS S.A.S.
A2: PROYECCIÓN CIERRE DICIEMBRE 2021
N5: =+N6/N12 -> 0.16948719
A6: AÑO | B6: 2021 | N6: =+N7+N9+13000000 -> 62859339
A7: CENTRO DE COSTO | B7: (Varios elementos) | N7: =32000000+12000000 -> 44000000
A8: ESTADO | B8: REAL | L8: 31931000 | M8: 32241000 | N8: =+N9-R25 -> 421893.53
A9: UTILIDAD Y/O PÉRDIDA | B9: =+GETPIVOTDATA("VALOR",$A$10,"MES","ENERO","CLASE","INGRESO")-GETPIVOTDATA("VALOR",$A$10,"MES","ENERO","CLASE","COSTO")-GETPIVOTDATA("VALOR",$A$10,"MES","ENERO","CLASE","GASTO") -> 7291266 | C9: =+GETPIVOTDATA("VALOR",$A$10,"MES","FEBRERO","CLASE","INGRESO")-GETPIVOTDATA("VALOR",$A$10,"MES","FEBRERO","CLASE","COSTO")-GETPIVOTDATA("VALOR",$A$10,"MES","FEBRERO","CLASE","GASTO") -> 6559927.2 | D9: =+GETPIVOTDATA("VALOR",$A$10,"MES","MARZO","CLASE","INGRESO")-GETPIVOTDATA("VALOR",$A$10,"MES","MARZO","CLASE","COSTO")-GETPIVOTDATA("VALOR",$A$10,"MES","MARZO","CLASE","GASTO") -> 10493418 | E9: =+GETPIVOTDATA("VALOR",$A$10,"MES","ABRIL","CLASE","INGRESO")-GETPIVOTDATA("VALOR",$A$10,"MES","ABRIL","CLASE","COSTO")-GETPIVOTDATA("VALOR",$A$10,"MES","ABRIL","CLASE","GASTO") -> 7526166 | F9: =+GETPIVOTDATA("VALOR",$A$10,"MES","MAYO","CLASE","INGRESO")-GETPIVOTDATA("VALOR",$A$10,"MES","MAYO","CLASE","COSTO")-GETPIVOTDATA("VALOR",$A$10,"MES","MAYO","CLASE","GASTO") -> 7780923.3 | G9: =+GETPIVOTDATA("VALOR",$A$10,"MES","JUNIO","CLASE","INGRESO")-GETPIVOTDATA("VALOR",$A$10,"MES","JUNIO","CLASE","COSTO")-GETPIVOTDATA("VALOR",$A$10,"MES","JUNIO","CLASE","GASTO") -> 9761695 | H9: =+GETPIVOTDATA("VALOR",$A$10,"MES","JULIO","CLASE","INGRESO")-GETPIVOTDATA("VALOR",$A$10,"MES","JULIO","CLASE","COSTO")-GETPIVOTDATA("VALOR",$A$10,"MES","JULIO","CLASE","GASTO") -> 8176452.8 | I9: =+GETPIVOTDATA("VALOR",$A$10,"MES","AGOSTO","CLASE","INGRESO")-GETPIVOTDATA("VALOR",$A$10,"MES","AGOSTO","CLASE","COSTO")-GETPIVOTDATA("VALOR",$A$10,"MES","AGOSTO","CLASE","GASTO") -> 3330135.5 | J9: =+GETPIVOTDATA("VALOR",$A$10,"MES","SEPTIEMBRE","CLASE","INGRESO")-GETPIVOTDATA("VALOR",$A$10,"MES","SEPTIEMBRE","CLASE","COSTO")-GETPIVOTDATA("VALOR",$A$10,"MES","SEPTIEMBRE","CLASE","GASTO") -> -14400132 | K9: =+K12-K15-K17 -> -8119306.4 | L9: =+L12-L15-L17 -> -301650.1 | M9: =+M12-M15-M17 -> -32239556 | N9: =+N12-N15-N17 -> 5859338.6 | Q9: PROYECCIÓN IMPUESTO DE RENTA 2021
A10: COMPORTAMIENTO REAL | B10: PERIODO | Q10: UTILIDAD FISCAL | R10: =+N9+N20 -> 17540146
A11: CUENTA | B11: ENERO | C11: FEBRERO | D11: MARZO | E11: ABRIL | F11: MAYO | G11: JUNIO | H11: JULIO | I11: AGOSTO | J11: SEPTIEMBRE | K11: OCTUBRE | L11: NOVIEMBRE | M11: DICIEMBRE | N11: TOTAL | Q11: IMPUESTO RENTA 31% | R11: =+R10*31% -> 5437445.1
A12: INGRESO | B12: 23566695 | C12: 24367830 | D12: 30112667 | E12: 25718752 | F12: 33739236 | G12: 33736754 | H12: 34656350 | I12: 27849166 | J12: 31200136 | K12: 38404950 | L12: 36867504 | M12: 30659547 | N12: =+SUM(B12:M12) -> 3.7087959e+08 | O12: =+N12/N12 -> 1 | Q12: AUTORRETENCIÓN | R12: =+(1063133/9)*12 -> 1417510.7
A13: INGRESO OPERACIONAL | B13: 23565829 | C13: 24367830 | D13: 30112163 | E13: 25717564 | F13: 33738468 | G13: 33736108 | H13: 34656349 | I13: 27797034 | J13: 31198164 | K13: 38396333 | L13: 36385057 | M13: 30608260 | N13: =+SUM(B13:M13) -> 3.7027916e+08 | Q13: ANTICIPO RETEFUENTE | R13: =+((1935772.96+38702)/9)*12 -> 2632633.3
A14: INGRESO NO OPERACIONAL | B14: 866 | D14: 504.44 | E14: 1188 | F14: 767.28 | G14: 646 | H14: 1.28 | I14: 52132.61 | J14: 1972.25 | K14: 8617 | L14: 482446.52 | M14: 51287.22 | N14: =+SUM(B14:M14) -> 600428.6 | Q14: TOTAL ESTIMADO A PAGAR IMP. RENTA | R14: =+R11-R12-R13 -> 1387301.2
A15: COSTO | B15: 7329138 | C15: 8538026 | D15: 8774320 | E15: 7696276 | F15: 10472560 | G15: 11308754 | H15: 10714108 | I15: 8750840 | J15: 26448456 | K15: 23175424 | L15: 15230915 | M15: 30801526 | N15: =+SUM(B15:M15) -> 1.6924034e+08 | O15: =+N15/N12 -> 0.45632154 | R15: =+R14*50% -> 693650.58
A16: COSTO DE VENTA | B16: 7329138 | C16: 8538026 | D16: 8774320 | E16: 7696276 | F16: 10472560 | G16: 11308754 | H16: 10714108 | I16: 8750840 | J16: 26448456 | K16: 23175424 | L16: 15230915 | M16: 30801526 | N16: =+SUM(B16:M16) -> 1.6924034e+08 | Q16: ANTICIPO DE RENTA 75% | R16: =+R11*75% -> 4078083.8
A17: GASTO | B17: 8946290.7 | C17: 9269876.3 | D17: 10844930 | E17: 10496310 | F17: 15485752 | G17: 12666305 | H17: 15765789 | I17: 15768191 | J17: 19151812 | K17: 23348832 | L17: 21938239 | M17: 32097577 | N17: =+SUM(B17:M17) -> 1.957799e+08 | O17: =+N17/N12 -> 0.52787997 | Q17: OPCIÓN 1 | R17: =+R16-R12-R13 -> 27939.884
A18: OPERACIONAL DE ADMINISTRACIÓN | B18: 7756304 | C18: 8451524 | D18: 9331949 | E18: 7499436 | F18: 12293882 | G18: 9228143 | H18: 12600952 | I18: 12361064 | J18: 16081747 | K18: 18729601 | L18: 17267227 | M18: 18265234 | N18: =+SUM(B18:M18) -> 1.4986706e+08 | R18: =+R16-R17 -> 4050143.9
A19: GASTOS DE VENTAS | E19: 2200591 | F19: 2200591 | G19: 2618770 | H19: 2458917 | I19: 2714610 | J19: 2200591 | K19: 2977750 | L19: 3947107 | M19: 3875107 | N19: =+SUM(B19:M19) -> 25194034
A20: NO OPERACIONALES | B20: 1189986.7 | C20: 818352.26 | D20: 1512980.7 | E20: 796283.17 | F20: 991279.58 | G20: 819391.95 | H20: 705919.79 | I20: 692516.72 | J20: 869474.06 | K20: 1641480.6 | L20: 723904.98 | M20: 919236.38 | N20: =+SUM(B20:M20) -> 11680807 | Q20: OPCIÓN 2
A21: IMPUESTO DE RENTA Y COMPLEMENTARIOS | M21: 9038000 | Q21: ANTICIPO DE RENTA 75% | R21: =+(R11+3749000)*75% -> 6889833.8
R22: =+R12+R13 -> 4050143.9
R23: =+R21-R22 -> 2839689.9
Q25: IMPUESTO NETO DE RENTA A PAGAR | R25: =+R14+R18 -> 5437445.1
Q27: 44652 | R27: =+R25*50% -> 2718722.6
Q28: 44713 | R28: =+R25*50% -> 2718722.6
Q30: PROYECCIÓN IMPUESTO DE INDUSTRIA Y COMERCIO
Q31: INGRESOS TOTALES | R31: =+N12 -> 3.7087959e+08
Q32: ICA ANUAL 0,33% | R32: =+R31*3.3/1000 -> 1223902.6
Q33: ANTICIPO RETEICA | R33: =+(737194.41/9)*12 -> 982925.88
Q34: TOTAL ESTIMADO A PAGAR ICA 2021 | R34: =+R32-R33 -> 240976.75
