Workbook

Sheet EF
A1: PANGEA NATURAL PRODUCTS S.A.S.
A2: NIT. 901.196.219-5
A3: ESTADO DE SITUACIÓN FINANCIERA
A4: (Expresados en pesos colombianos)
A6: Período terminado a
B7: ACTIVO | C7: Nota | D7: MARZO de 2026 | E7: % | F7: PERIODO ANTERIOR TEST | G7: % | H7: Variación | I7: % | J7: FILTRO
B8: CORRIENTE | J8: TRUE
A9: 11 11C | B9: Efectivo y Equivalentes al Efectivo | C9: 1 | D9: =SUM(D10,D213,D220,D273,D3813,D3816,D6895) | E9: =IF($D$7125=0,0,D9/ABS($D$7125)) | F9: =SUM(F10,F213,F220,F273,F3813,F3816,F6895) | G9: =IF($F$7125=0,0,F9/ABS($F$7125)) | H9: =D9-F9 | I9: =IF(F9=0,0,H9/ABS(F9)) | J9: TRUE
A10: 1105050101 | B10: Caja Menor | D10: =SUM(D11:D212) | E10: =IF($D$7125=0,0,D10/ABS($D$7125)) | F10: =SUM(F11:F212) | G10: =IF($F$7125=0,0,F10/ABS($F$7125)) | H10: =D10-F10 | I10: =IF(F10=0,0,H10/ABS(F10)) | J10: TRUE
B11: Abhay Organica | D11: 199998 | E11: =IF($D$7125=0,0,D11/ABS($D$7125)) | F11: 199998 | G11: =IF($F$7125=0,0,F11/ABS($F$7125)) | H11: =D11-F11 | I11: =IF(F11=0,0,H11/ABS(F11)) | J11: TRUE
B12: BIOMARKET | D12: 153333 | E12: =IF($D$7125=0,0,D12/ABS($D$7125)) | F12: 153333 | G12: =IF($F$7125=0,0,F12/ABS($F$7125)) | H12: =D12-F12 | I12: =IF(F12=0,0,H12/ABS(F12)) | J12: TRUE
B13: BOLSAS Y PLASTICOS LA 15 LTDA | D13: -58100 | E13: =IF($D$7125=0,0,D13/ABS($D$7125)) | F13: -58100 | G13: =IF($F$7125=0,0,F13/ABS($F$7125)) | H13: =D13-F13 | I13: =IF(F13=0,0,H13/ABS(F13)) | J13: TRUE
B14: CAMARA DE COMERCIO DE CALI | D14: -6200 | E14: =IF($D$7125=0,0,D14/ABS($D$7125)) | F14: -6200 | G14: =IF($F$7125=0,0,F14/ABS($F$7125)) | H14: =D14-F14 | I14: =IF(F14=0,0,H14/ABS(F14)) | J14: TRUE
B15: DENOMINACION ORIGEN SAS | D15: 347996 | E15: =IF($D$7125=0,0,D15/ABS($D$7125)) | F15: 347996 | G15: =IF($F$7125=0,0,F15/ABS($F$7125)) | H15: =D15-F15 | I15: =IF(F15=0,0,H15/ABS(F15)) | J15: TRUE
B16: Fisioactivity | D16: 413917 | E16: =IF($D$7125=0,0,D16/ABS($D$7125)) | F16: 413917 | G16: =IF($F$7125=0,0,F16/ABS($F$7125)) | H16: =D16-F16 | I16: =IF(F16=0,0,H16/ABS(F16)) | J16: TRUE
B17: HEALTHY ORGANIC MARKET | D17: 419999 | E17: =IF($D$7125=0,0,D17/ABS($D$7125)) | F17: 419999 | G17: =IF($F$7125=0,0,F17/ABS($F$7125)) | H17: =D17-F17 | I17: =IF(F17=0,0,H17/ABS(F17)) | J17: TRUE
B18: KOBA COLOMBIA SAS | D18: -91740 | E18: =IF($D$7125=0,0,D18/ABS($D$7125)) | F18: -91740 | G18: =IF($F$7125=0,0,F18/ABS($F$7125)) | H18: =D18-F18 | I18: =IF(F18=0,0,H18/ABS(F18)) | J18: TRUE
B19: MANCHOLA ASOCIADOS LTDA | D19: 60000 | E19: =IF($D$7125=0,0,D19/ABS($D$7125)) | F19: 60000 | G19: =IF($F$7125=0,0,F19/ABS($F$7125)) | H19: =D19-F19 | I19: =IF(F19=0,0,H19/ABS(F19)) | J19: TRUE
B20: Naturalfit | D20: 183333 | E20: =IF($D$7125=0,0,D20/ABS($D$7125)) | F20: 183333 | G20: =IF($F$7125=0,0,F20/ABS($F$7125)) | H20: =D20-F20 | I20: =IF(F20=0,0,H20/ABS(F20)) | J20: TRUE
B21: PANGEA NATURAL PRODUCTS S.A.S. | D21: -31137534 | E21: =IF($D$7125=0,0,D21/ABS($D$7125)) | F21: -31137534 | G21: =IF($F$7125=0,0,F21/ABS($F$7125)) | H21: =D21-F21 | I21: =IF(F21=0,0,H21/ABS(F21)) | J21: TRUE
B22: SUPERFUDS SAS | D22: 26001 | E22: =IF($D$7125=0,0,D22/ABS($D$7125)) | F22: 26001 | G22: =IF($F$7125=0,0,F22/ABS($F$7125)) | H22: =D22-F22 | I22: =IF(F22=0,0,H22/ABS(F22)) | J22: TRUE
... B212: isabela Arias | D212: 215000 | E212: =IF($D$7125=0,0,D212/ABS($D$7125)) | F212: 215000 | G212: =IF($F$7125=0,0,F212/ABS($F$7125)) | H212: =D212-F212 | I212: =IF(F212=0,0,H212/ABS(F212)) | J212: TRUE
A213: 11051001 | B213: Cajas menores | D213: =SUM(D214:D219) | E213: =IF($D$7125=0,0,D213/ABS($D$7125)) | F213: =SUM(F214:F219) | G213: =IF($F$7125=0,0,F213/ABS($F$7125)) | H213: =D213-F213 | I213: =IF(F213=0,0,H213/ABS(F213)) | J213: TRUE
B214: PANGEA NATURAL PRODUCTS S.A.S. | D214: 248059.44 | E214: =IF($D$7125=0,0,D214/ABS($D$7125)) | F214: 248059.44 | G214: =IF($F$7125=0,0,F214/ABS($F$7125)) | H214: =D214-F214 | I214: =IF(F214=0,0,H214/ABS(F214)) | J214: TRUE
B215: AEROVIAS DEL CONTINENTE AMERICANO S.A. | D215: -708459.44 | E215: =IF($D$7125=0,0,D215/ABS($D$7125)) | F215: -708459.44 | G215: =IF($F$7125=0,0,F215/ABS($F$7125)) | H215: =D215-F215 | I215: =IF(F215=0,0,H215/ABS(F215)) | J215: TRUE
B216: FRISBY S.A. | D216: -23300 | E216: =IF($D$7125=0,0,D216/ABS($D$7125)) | F216: -23300 | G216: =IF($F$7125=0,0,F216/ABS($F$7125)) | H216: =D216-F216 | I216: =IF(F216=0,0,H216/ABS(F216)) | J216: TRUE
B217: MUNICIPIO DE SANTIAGO DE CALI | D217: -253000 | E217: =IF($D$7125=0,0,D217/ABS($D$7125)) | F217: -253000 | G217: =IF($F$7125=0,0,F217/ABS($F$7125)) | H217: =D217-F217 | I217: =IF(F217=0,0,H217/ABS(F217)) | J217: TRUE
B218: OLGA BARBOSA DE HURTADO | D218: -100000 | E218: =IF($D$7125=0,0,D218/ABS($D$7125)) | F218: -100000 | G218: =IF($F$7125=0,0,F218/ABS($F$7125)) | H218: =D218-F218 | I218: =IF(F218=0,0,H218/ABS(F218)) | J218: TRUE
B219: Sebastian Mendoza Castaño | D219: 1436700 | E219: =IF($D$7125=0,0,D219/ABS($D$7125)) | F219: 1436700 | G219: =IF($F$7125=0,0,F219/ABS($F$7125)) | H219: =D219-F219 | I219: =IF(F219=0,0,H219/ABS(F219)) | J219: TRUE
A220: 11100503 | B220: Cuenta Cte. Banco de Bogota | D220: =SUM(D221:D272) | E220: =IF($D$7125=0,0,D220/ABS($D$7125)) | F220: =SUM(F221:F272) | G220: =IF($F$7125=0,0,F220/ABS($F$7125)) | H220: =D220-F220 | I220: =IF(F220=0,0,H220/ABS(F220)) | J220: TRUE
B221: ANILLANDO CALI LTDA | D221: -45000 | E221: =IF($D$7125=0,0,D221/ABS($D$7125)) | F221: -45000 | G221: =IF($F$7125=0,0,F221/ABS($F$7125)) | H221: =D221-F221 | I221: =IF(F221=0,0,H221/ABS(F221)) | J221: TRUE
B222: DOCUPRINT SAS | D222: -10350 | E222: =IF($D$7125=0,0,D222/ABS($D$7125)) | F222: -10350 | G222: =IF($F$7125=0,0,F222/ABS($F$7125)) | H222: =D222-F222 | I222: =IF(F222=0,0,H222/ABS(F222)) | J222: TRUE
B223: ESCARRIA PRINTS DIGITAL SAS | D223: -590240 | E223: =IF($D$7125=0,0,D223/ABS($D$7125)) | F223: -590240 | G223: =IF($F$7125=0,0,F223/ABS($F$7125)) | H223: =D223-F223 | I223: =IF(F223=0,0,H223/ABS(F223)) | J223: TRUE
B224: GERMAN DE JESUS CARDONA | D224: 270302 | E224: =IF($D$7125=0,0,D224/ABS($D$7125)) | F224: 270302 | G224: =IF($F$7125=0,0,F224/ABS($F$7125)) | H224: =D224-F224 | I224: =IF(F224=0,0,H224/ABS(F224)) | J224: TRUE
B225: INALI ZONA FRANCA SAS | D225: -464100 | E225: =IF($D$7125=0,0,D225/ABS($D$7125)) | F225: -464100 | G225: =IF($F$7125=0,0,F225/ABS($F$7125)) | H225: =D225-F225 | I225: =IF(F225=0,0,H225/ABS(F225)) | J225: TRUE
B226: INSTITUTO NACIONAL DE VIGILANCIA DE MEDICAMENTOS Y ALIMENTOS - INVIMA | D226: -2578099 | E226: =IF($D$7125=0,0,D226/ABS($D$7125)) | F226: -2578099 | G226: =IF($F$7125=0,0,F226/ABS($F$7125)) | H226: =D226-F226 | I226: =IF(F226=0,0,H226/ABS(F226)) | J226: TRUE
B227: MANCHOLA ASOCIADOS LTDA | D227: -2675000 | E227: =IF($D$7125=0,0,D227/ABS($D$7125)) | F227: -2675000 | G227: =IF($F$7125=0,0,F227/ABS($F$7125)) | H227: =D227-F227 | I227: =IF(F227=0,0,H227/ABS(F227)) | J227: TRUE
B228: MONCIEL SAS | D228: 1073334 | E228: =IF($D$7125=0,0,D228/ABS($D$7125)) | F228: 1073334 | G228: =IF($F$7125=0,0,F228/ABS($F$7125)) | H228: =D228-F228 | I228: =IF(F228=0,0,H228/ABS(F228)) | J228: TRUE
B229: MULTICARTON S.A.S. | D229: -477359 | E229: =IF($D$7125=0,0,D229/ABS($D$7125)) | F229: -477359 | G229: =IF($F$7125=0,0,F229/ABS($F$7125)) | H229: =D229-F229 | I229: =IF(F229=0,0,H229/ABS(F229)) | J229: TRUE
B230: PANGEA NATURAL PRODUCTS S.A.S. | D230: 22663323 | E230: =IF($D$7125=0,0,D230/ABS($D$7125)) | F230: 22663323 | G230: =IF($F$7125=0,0,F230/ABS($F$7125)) | H230: =D230-F230 | I230: =IF(F230=0,0,H230/ABS(F230)) | J230: TRUE
B231: SIIGO SAS | D231: -1560000 | E231: =IF($D$7125=0,0,D231/ABS($D$7125)) | F231: -1560000 | G231: =IF($F$7125=0,0,F231/ABS($F$7125)) | H231: =D231-F231 | I231: =IF(F231=0,0,H231/ABS(F231)) | J231: TRUE
B232: SUNA COLOMBIA SAS | D232: 439991 | E232: =IF($D$7125=0,0,D232/ABS($D$7125)) | F232: 439991 | G232: =IF($F$7125=0,0,F232/ABS($F$7125)) | H232: =D232-F232 | I232: =IF(F232=0,0,H232/ABS(F232)) | J232: TRUE
... B272: VITAFITNESS SAS | D272: 2256717 | E272: =IF($D$7125=0,0,D272/ABS($D$7125)) | F272: 2256717 | G272: =IF($F$7125=0,0,F272/ABS($F$7125)) | H272: =D272-F272 | I272: =IF(F272=0,0,H272/ABS(F272)) | J272: TRUE
A273: 11100504 | B273: Cuenta Cte. Bancolombia 1211 | D273: =SUM(D274:D3812) | E273: =IF($D$7125=0,0,D273/ABS($D$7125)) | F273: =SUM(F274:F3812) | G273: =IF($F$7125=0,0,F273/ABS($F$7125)) | H273: =D273-F273 | I273: =IF(F273=0,0,H273/ABS(F273)) | J273: TRUE
B274: ANILLANDO CALI LTDA | D274: -278900.45 | E274: =IF($D$7125=0,0,D274/ABS($D$7125)) | F274: -278900.45 | G274: =IF($F$7125=0,0,F274/ABS($F$7125)) | H274: =D274-F274 | I274: =IF(F274=0,0,H274/ABS(F274)) | J274: TRUE
B275: CAMARA DE COMERCIO DE CALI | D275: -15893838 | E275: =IF($D$7125=0,0,D275/ABS($D$7125)) | F275: -15893838 | G275: =IF($F$7125=0,0,F275/ABS($F$7125)) | H275: =D275-F275 | I275: =IF(F275=0,0,H275/ABS(F275)) | J275: TRUE
B276: COLOMBIA TELECOMUNICACIONES S.A. E.S.P. | D276: -19006644 | E276: =IF($D$7125=0,0,D276/ABS($D$7125)) | F276: -19006644 | G276: =IF($F$7125=0,0,F276/ABS($F$7125)) | H276: =D276-F276 | I276: =IF(F276=0,0,H276/ABS(F276)) | J276: TRUE
B277: DENOMINACION ORIGEN SAS | D277: 1240283 | E277: =IF($D$7125=0,0,D277/ABS($D$7125)) | F277: 1240283 | G277: =IF($F$7125=0,0,F277/ABS($F$7125)) | H277: =D277-F277 | I277: =IF(F277=0,0,H277/ABS(F277)) | J277: TRUE
B278: GERMAN DE JESUS CARDONA | D278: 239250 | E278: =IF($D$7125=0,0,D278/ABS($D$7125)) | F278: 239250 | G278: =IF($F$7125=0,0,F278/ABS($F$7125)) | H278: =D278-F278 | I278: =IF(F278=0,0,H278/ABS(F278)) | J278: TRUE
B279: GLOBAL MENSAJERIA SAS | D279: -4800 | E279: =IF($D$7125=0,0,D279/ABS($D$7125)) | F279: -4800 | G279: =IF($F$7125=0,0,F279/ABS($F$7125)) | H279: =D279-F279 | I279: =IF(F279=0,0,H279/ABS(F279)) | J279: TRUE
B280: HEALTHY ORGANIC MARKET | D280: 240000 | E280: =IF($D$7125=0,0,D280/ABS($D$7125)) | F280: 240000 | G280: =IF($F$7125=0,0,F280/ABS($F$7125)) | H280: =D280-F280 | I280: =IF(F280=0,0,H280/ABS(F280)) | J280: TRUE
B281: HOTELES ESTELAR SA | D281: -743200 | E281: =IF($D$7125=0,0,D281/ABS($D$7125)) | F281: -743200 | G281: =IF($F$7125=0,0,F281/ABS($F$7125)) | H281: =D281-F281 | I281: =IF(F281=0,0,H281/ABS(F281)) | J281: TRUE
B282: IKEBANA HEALTHY FOOD | D282: 99998 | E282: =IF($D$7125=0,0,D282/ABS($D$7125)) | F282: 99998 | G282: =IF($F$7125=0,0,F282/ABS($F$7125)) | H282: =D282-F282 | I282: =IF(F282=0,0,H282/ABS(F282)) | J282: TRUE
B283: INALI ZONA FRANCA SAS | D283: -1584069 | E283: =IF($D$7125=0,0,D283/ABS($D$7125)) | F283: -1584069 | G283: =IF($F$7125=0,0,F283/ABS($F$7125)) | H283: =D283-F283 | I283: =IF(F283=0,0,H283/ABS(F283)) | J283: TRUE
B284: KOBA COLOMBIA SAS | D284: -55010 | E284: =IF($D$7125=0,0,D284/ABS($D$7125)) | F284: -55010 | G284: =IF($F$7125=0,0,F284/ABS($F$7125)) | H284: =D284-F284 | I284: =IF(F284=0,0,H284/ABS(F284)) | J284: TRUE
B285: MANCHOLA ASOCIADOS LTDA | D285: -78198705 | E285: =IF($D$7125=0,0,D285/ABS($D$7125)) | F285: -78198705 | G285: =IF($F$7125=0,0,F285/ABS($F$7125)) | H285: =D285-F285 | I285: =IF(F285=0,0,H285/ABS(F285)) | J285: TRUE
... B3812: Ángela Rodríguez | D3812: 160000 | E3812: =IF($D$7125=0,0,D3812/ABS($D$7125)) | F3812: 160000 | G3812: =IF($F$7125=0,0,F3812/ABS($F$7125)) | H3812: =D3812-F3812 | I3812: =IF(F3812=0,0,H3812/ABS(F3812)) | J3812: TRUE
A3813: 11100505 | B3813: Pagos en línea Mercado Pago | D3813: =SUM(D3814:D3815) | E3813: =IF($D$7125=0,0,D3813/ABS($D$7125)) | F3813: =SUM(F3814:F3815) | G3813: =IF($F$7125=0,0,F3813/ABS($F$7125)) | H3813: =D3813-F3813 | I3813: =IF(F3813=0,0,H3813/ABS(F3813)) | J3813: TRUE
B3814: PANGEA NATURAL PRODUCTS S.A.S. | D3814: 306421.94 | E3814: =IF($D$7125=0,0,D3814/ABS($D$7125)) | F3814: 306421.94 | G3814: =IF($F$7125=0,0,F3814/ABS($F$7125)) | H3814: =D3814-F3814 | I3814: =IF(F3814=0,0,H3814/ABS(F3814)) | J3814: TRUE
B3815: Mercadopago Colombia Ltda | D3815: -306421.94 | E3815: =IF($D$7125=0,0,D3815/ABS($D$7125)) | F3815: -306421.94 | G3815: =IF($F$7125=0,0,F3815/ABS($F$7125)) | H3815: =D3815-F3815 | I3815: =IF(F3815=0,0,H3815/ABS(F3815)) | J3815: TRUE
A3816: 11100506 | B3816: Mercadopago | D3816: =SUM(D3817:D6894) | E3816: =IF($D$7125=0,0,D3816/ABS($D$7125)) | F3816: =SUM(F3817:F6894) | G3816: =IF($F$7125=0,0,F3816/ABS($F$7125)) | H3816: =D3816-F3816 | I3816: =IF(F3816=0,0,H3816/ABS(F3816)) | J3816: TRUE
B3817: PANGEA NATURAL PRODUCTS S.A.S. | D3817: -83560130 | E3817: =IF($D$7125=0,0,D3817/ABS($D$7125)) | F3817: -83560130 | G3817: =IF($F$7125=0,0,F3817/ABS($F$7125)) | H3817: =D3817-F3817 | I3817: =IF(F3817=0,0,H3817/ABS(F3817)) | J3817: TRUE
B3818: Banco de bogotá | D3818: -2.0210371e+08 | E3818: =IF($D$7125=0,0,D3818/ABS($D$7125)) | F3818: -2.0210371e+08 | G3818: =IF($F$7125=0,0,F3818/ABS($F$7125)) | H3818: =D3818-F3818 | I3818: =IF(F3818=0,0,H3818/ABS(F3818)) | J3818: TRUE
B3819: Carolina Hoyos Cardona | D3819: 3655688.7 | E3819: =IF($D$7125=0,0,D3819/ABS($D$7125)) | F3819: 3655688.7 | G3819: =IF($F$7125=0,0,F3819/ABS($F$7125)) | H3819: =D3819-F3819 | I3819: =IF(F3819=0,0,H3819/ABS(F3819)) | J3819: TRUE
B3820: Consumidor Final | D3820: 4199430 | E3820: =IF($D$7125=0,0,D3820/ABS($D$7125)) | F3820: 4199430 | G3820: =IF($F$7125=0,0,F3820/ABS($F$7125)) | H3820: =D3820-F3820 | I3820: =IF(F3820=0,0,H3820/ABS(F3820)) | J3820: TRUE
B3821: DOMINICAS HIJAS DE NUESTRA SEÑORA DE NAZARETH | D3821: 68500 | E3821: =IF($D$7125=0,0,D3821/ABS($D$7125)) | F3821: 68500 | G3821: =IF($F$7125=0,0,F3821/ABS($F$7125)) | H3821: =D3821-F3821 | I3821: =IF(F3821=0,0,H3821/ABS(F3821)) | J3821: TRUE
B3822: Geicer Dorys Bedoya Marín | D3822: 3274892.6 | E3822: =IF($D$7125=0,0,D3822/ABS($D$7125)) | F3822: 3274892.6 | G3822: =IF($F$7125=0,0,F3822/ABS($F$7125)) | H3822: =D3822-F3822 | I3822: =IF(F3822=0,0,H3822/ABS(F3822)) | J3822: TRUE
B3823: Gustavo Durazo | D3823: 2148369 | E3823: =IF($D$7125=0,0,D3823/ABS($D$7125)) | F3823: 2148369 | G3823: =IF($F$7125=0,0,F3823/ABS($F$7125)) | H3823: =D3823-F3823 | I3823: =IF(F3823=0,0,H3823/ABS(F3823)) | J3823: TRUE
B3824: INFINITO MEDICAL SERVICE DROGUERIA-HOMEOPATIA SAS | D3824: 5945578.6 | E3824: =IF($D$7125=0,0,D3824/ABS($D$7125)) | F3824: 5945578.6 | G3824: =IF($F$7125=0,0,F3824/ABS($F$7125)) | H3824: =D3824-F3824 | I3824: =IF(F3824=0,0,H3824/ABS(F3824)) | J3824: TRUE
B3825: Manuel Londoño | D3825: 2071280 | E3825: =IF($D$7125=0,0,D3825/ABS($D$7125)) | F3825: 2071280 | G3825: =IF($F$7125=0,0,F3825/ABS($F$7125)) | H3825: =D3825-F3825 | I3825: =IF(F3825=0,0,H3825/ABS(F3825)) | J3825: TRUE
B3826: Martha Lucia Orozco | D3826: 84000 | E3826: =IF($D$7125=0,0,D3826/ABS($D$7125)) | F3826: 84000 | G3826: =IF($F$7125=0,0,F3826/ABS($F$7125)) | H3826: =D3826-F3826 | I3826: =IF(F3826=0,0,H3826/ABS(F3826)) | J3826: TRUE
B3827: Mercadopago Colombia Ltda | D3827: -2.1388909e+08 | E3827: =IF($D$7125=0,0,D3827/ABS($D$7125)) | F3827: -2.1388909e+08 | G3827: =IF($F$7125=0,0,F3827/ABS($F$7125)) | H3827: =D3827-F3827 | I3827: =IF(F3827=0,0,H3827/ABS(F3827)) | J3827: TRUE
B3828: NUTRICIÓN HONESTA SAS Diego Mariño | D3828: 40000 | E3828: =IF($D$7125=0,0,D3828/ABS($D$7125)) | F3828: 40000 | G3828: =IF($F$7125=0,0,F3828/ABS($F$7125)) | H3828: =D3828-F3828 | I3828: =IF(F3828=0,0,H3828/ABS(F3828)) | J3828: TRUE
... B6894: Yina Yereinza Acevedo Álvarez | D6894: 4215720 | E6894: =IF($D$7125=0,0,D6894/ABS($D$7125)) | F6894: 4215720 | G6894: =IF($F$7125=0,0,F6894/ABS($F$7125)) | H6894: =D6894-F6894 | I6894: =IF(F6894=0,0,H6894/ABS(F6894)) | J6894: TRUE
A6895: 11100507 | B6895: Cuenta CTE. Banco de Bogota 4331 | D6895: =SUM(D6896:D6897) | E6895: =IF($D$7125=0,0,D6895/ABS($D$7125)) | F6895: =SUM(F6896:F6897) | G6895: =IF($F$7125=0,0,F6895/ABS($F$7125)) | H6895: =D6895-F6895 | I6895: =IF(F6895=0,0,H6895/ABS(F6895)) | J6895: TRUE
B6896: PANGEA NATURAL PRODUCTS S.A.S. | D6896: 86737423 | E6896: =IF($D$7125=0,0,D6896/ABS($D$7125)) | F6896: 86737423 | G6896: =IF($F$7125=0,0,F6896/ABS($F$7125)) | H6896: =D6896-F6896 | I6896: =IF(F6896=0,0,H6896/ABS(F6896)) | J6896: TRUE
B6897: Banco de bogotá | D6897: 53797767 | E6897: =IF($D$7125=0,0,D6897/ABS($D$7125)) | F6897: 53797767 | G6897: =IF($F$7125=0,0,F6897/ABS($F$7125)) | H6897: =D6897-F6897 | I6897: =IF(F6897=0,0,H6897/ABS(F6897)) | J6897: TRUE
A6898: 13 13C | B6898: Deudores comerciales y otras cuentas por cobrar | C6898: 2 | D6898: =SUM(D6899,D6945,D6991,D6995,D6997,D7047,D7052,D7056,D7063,D7067,D7071,D7078,D7081,D7088,D7090) | E6898: =IF($D$7125=0,0,D6898/ABS($D$7125)) | F6898: =SUM(F6899,F6945,F6991,F6995,F6997,F7047,F7052,F7056,F7063,F7067,F7071,F7078,F7081,F7088,F7090) | G6898: =IF($F$7125=0,0,F6898/ABS($F$7125)) | H6898: =D6898-F6898 | I6898: =IF(F6898=0,0,H6898/ABS(F6898)) | J6898: TRUE
A6899: 13050501 | B6899: Clientes nacionales | D6899: =SUM(D6900:D6944) | E6899: =IF($D$7125=0,0,D6899/ABS($D$7125)) | F6899: =SUM(F6900:F6944) | G6899: =IF($F$7125=0,0,F6899/ABS($F$7125)) | H6899: =D6899-F6899 | I6899: =IF(F6899=0,0,H6899/ABS(F6899)) | J6899: TRUE
B6900: ACM PHARMA S.A.S | D6900: 1020443.9 | E6900: =IF($D$7125=0,0,D6900/ABS($D$7125)) | F6900: 1020443.9 | G6900: =IF($F$7125=0,0,F6900/ABS($F$7125)) | H6900: =D6900-F6900 | I6900: =IF(F6900=0,0,H6900/ABS(F6900)) | J6900: TRUE
B6901: ADWELLCH SAS | D6901: 18366468 | E6901: =IF($D$7125=0,0,D6901/ABS($D$7125)) | F6901: 18366468 | G6901: =IF($F$7125=0,0,F6901/ABS($F$7125)) | H6901: =D6901-F6901 | I6901: =IF(F6901=0,0,H6901/ABS(F6901)) | J6901: TRUE
B6902: ALIMENTOS SOSTENIBLES SAS | D6902: 1801231.7 | E6902: =IF($D$7125=0,0,D6902/ABS($D$7125)) | F6902: 1801231.7 | G6902: =IF($F$7125=0,0,F6902/ABS($F$7125)) | H6902: =D6902-F6902 | I6902: =IF(F6902=0,0,H6902/ABS(F6902)) | J6902: TRUE
B6903: ARTEMISA S.A.S BIC | D6903: 39638302 | E6903: =IF($D$7125=0,0,D6903/ABS($D$7125)) | F6903: 39638302 | G6903: =IF($F$7125=0,0,F6903/ABS($F$7125)) | H6903: =D6903-F6903 | I6903: =IF(F6903=0,0,H6903/ABS(F6903)) | J6903: TRUE
B6904: CAJA COLOMBIANA DE SUBSIDIO FAMILIAR COLSUBSIDIO | D6904: 159257426 | E6904: =IF($D$7125=0,0,D6904/ABS($D$7125)) | F6904: 159257426 | G6904: =IF($F$7125=0,0,F6904/ABS($F$7125)) | H6904: =D6904-F6904 | I6904: =IF(F6904=0,0,H6904/ABS(F6904)) | J6904: TRUE
B6905: COPRA GLUTEN FREE S.A.S - green house | D6905: 1218904.5 | E6905: =IF($D$7125=0,0,D6905/ABS($D$7125)) | F6905: 1218904.5 | G6905: =IF($F$7125=0,0,F6905/ABS($F$7125)) | H6905: =D6905-F6905 | I6905: =IF(F6905=0,0,H6905/ABS(F6905)) | J6905: TRUE
B6906: Clavijo Martinez Inversiones cia s en c | D6906: 3366897 | E6906: =IF($D$7125=0,0,D6906/ABS($D$7125)) | F6906: 3366897 | G6906: =IF($F$7125=0,0,F6906/ABS($F$7125)) | H6906: =D6906-F6906 | I6906: =IF(F6906=0,0,H6906/ABS(F6906)) | J6906: TRUE
B6907: Consumidor Final | D6907: 0 | E6907: =IF($D$7125=0,0,D6907/ABS($D$7125)) | F6907: 0 | G6907: =IF($F$7125=0,0,F6907/ABS($F$7125)) | H6907: =D6907-F6907 | I6907: =IF(F6907=0,0,H6907/ABS(F6907)) | J6907: TRUE
B6908: DANIELA ARBELAEZ | D6908: 0 | E6908: =IF($D$7125=0,0,D6908/ABS($D$7125)) | F6908: 0 | G6908: =IF($F$7125=0,0,F6908/ABS($F$7125)) | H6908: =D6908-F6908 | I6908: =IF(F6908=0,0,H6908/ABS(F6908)) | J6908: TRUE
B6909: DISTRIBUIDORA PASTEUR | D6909: 2.4084697e+08 | E6909: =IF($D$7125=0,0,D6909/ABS($D$7125)) | F6909: 2.4084697e+08 | G6909: =IF($F$7125=0,0,F6909/ABS($F$7125)) | H6909: =D6909-F6909 | I6909: =IF(F6909=0,0,H6909/ABS(F6909)) | J6909: TRUE
B6910: DISTRIBUIDORA SALUD NATURAL S.A.S | D6910: 4775774 | E6910: =IF($D$7125=0,0,D6910/ABS($D$7125)) | F6910: 4775774 | G6910: =IF($F$7125=0,0,F6910/ABS($F$7125)) | H6910: =D6910-F6910 | I6910: =IF(F6910=0,0,H6910/ABS(F6910)) | J6910: TRUE
B6911: Droguerías Juliao S.A Mariela Ester Juliao del Río | D6911: 9517436 | E6911: =IF($D$7125=0,0,D6911/ABS($D$7125)) | F6911: 9517436 | G6911: =IF($F$7125=0,0,F6911/ABS($F$7125)) | H6911: =D6911-F6911 | I6911: =IF(F6911=0,0,H6911/ABS(F6911)) | J6911: TRUE
... B6944: Vida Simple SAS | D6944: 0.16 | E6944: =IF($D$7125=0,0,D6944/ABS($D$7125)) | F6944: 0.16 | G6944: =IF($F$7125=0,0,F6944/ABS($F$7125)) | H6944: =D6944-F6944 | I6944: =IF(F6944=0,0,H6944/ABS(F6944)) | J6944: TRUE
A6945: 13300501 | B6945: A proveedores | D6945: =SUM(D6946:D6990) | E6945: =IF($D$7125=0,0,D6945/ABS($D$7125)) | F6945: =SUM(F6946:F6990) | G6945: =IF($F$7125=0,0,F6945/ABS($F$7125)) | H6945: =D6945-F6945 | I6945: =IF(F6945=0,0,H6945/ABS(F6945)) | J6945: TRUE
B6946: CAMARA DE COMERCIO DE CALI | D6946: 2416600 | E6946: =IF($D$7125=0,0,D6946/ABS($D$7125)) | F6946: 2416600 | G6946: =IF($F$7125=0,0,F6946/ABS($F$7125)) | H6946: =D6946-F6946 | I6946: =IF(F6946=0,0,H6946/ABS(F6946)) | J6946: TRUE
B6947: COLOMBIA TELECOMUNICACIONES S.A. E.S.P. | D6947: 175299 | E6947: =IF($D$7125=0,0,D6947/ABS($D$7125)) | F6947: 175299 | G6947: =IF($F$7125=0,0,F6947/ABS($F$7125)) | H6947: =D6947-F6947 | I6947: =IF(F6947=0,0,H6947/ABS(F6947)) | J6947: TRUE
B6948: MANCHOLA ASOCIADOS LTDA | D6948: 5000000 | E6948: =IF($D$7125=0,0,D6948/ABS($D$7125)) | F6948: 5000000 | G6948: =IF($F$7125=0,0,F6948/ABS($F$7125)) | H6948: =D6948-F6948 | I6948: =IF(F6948=0,0,H6948/ABS(F6948)) | J6948: TRUE
B6949: MULTICARTON S.A.S. | D6949: 477359 | E6949: =IF($D$7125=0,0,D6949/ABS($D$7125)) | F6949: 477359 | G6949: =IF($F$7125=0,0,F6949/ABS($F$7125)) | H6949: =D6949-F6949 | I6949: =IF(F6949=0,0,H6949/ABS(F6949)) | J6949: TRUE
B6950: ABORIGEN CIENCIA ANCESTRAL S.A.S | D6950: 26070731 | E6950: =IF($D$7125=0,0,D6950/ABS($D$7125)) | F6950: 26070731 | G6950: =IF($F$7125=0,0,F6950/ABS($F$7125)) | H6950: =D6950-F6950 | I6950: =IF(F6950=0,0,H6950/ABS(F6950)) | J6950: TRUE
B6951: AGUSTIN ARMANDO POVEDA OVIEDO | D6951: 1246000 | E6951: =IF($D$7125=0,0,D6951/ABS($D$7125)) | F6951: 1246000 | G6951: =IF($F$7125=0,0,F6951/ABS($F$7125)) | H6951: =D6951-F6951 | I6951: =IF(F6951=0,0,H6951/ABS(F6951)) | J6951: TRUE
B6952: ALIMENTOS JOMAS | D6952: 1148684.4 | E6952: =IF($D$7125=0,0,D6952/ABS($D$7125)) | F6952: 1148684.4 | G6952: =IF($F$7125=0,0,F6952/ABS($F$7125)) | H6952: =D6952-F6952 | I6952: =IF(F6952=0,0,H6952/ABS(F6952)) | J6952: TRUE
...

Sheet ER
A1: PANGEA NATURAL PRODUCTS S.A.S.
A2: NIT. 901.196.219-5
A3: ESTADO DE RESULTADO INTEGRAL
A4: (Expresados en pesos colombianos)
A6: Período comprendido entre
A7: 01 de Enero y al fin del mes de : MARZO de 2026
A9: Actividades Ordinarias | C9: Nota | D9: MARZO de 2026 | E9: % | F9: PERIODO ANTERIOR TEST | G9: % | H9: VARIACIÓN | I9: % | J9: FILTRO
B10: Venta de producto y prestación de servicios | C10: 14 | D10: =SUM(D11,D3174,D3176,D3238,D3244,D3246,D3331) | E10: =IF($D$10=0,0,D10/ABS($D$10)) | F10: =SUM(F11,F3174,F3176,F3238,F3244,F3246,F3331) | G10: =IF($F$10=0,0,F10/ABS($F$10)) | H10: =D10-F10 | I10: =IF(F10=0,0,H10/ABS(F10)) | J10: TRUE
B11: 41350101 - Comercio al por mayor y al detal | D11: =SUM(D12:D3173) | E11: =IF($D$10=0,0,D11/ABS($D$10)) | F11: =SUM(F12:F3173) | G11: =IF($F$10=0,0,F11/ABS($F$10)) | H11: =D11-F11 | I11: =IF(F11=0,0,H11/ABS(F11)) | J11: TRUE
B12: PANGEA NATURAL PRODUCTS S.A.S. | D12: 0 | E12: =IF($D$10=0,0,D12/ABS($D$10)) | F12: 0 | G12: =IF($F$10=0,0,F12/ABS($F$10)) | H12: =D12-F12 | I12: =IF(F12=0,0,H12/ABS(F12)) | J12: TRUE
B13: ACM PHARMA S.A.S | D13: 0 | E13: =IF($D$10=0,0,D13/ABS($D$10)) | F13: 0 | G13: =IF($F$10=0,0,F13/ABS($F$10)) | H13: =D13-F13 | I13: =IF(F13=0,0,H13/ABS(F13)) | J13: TRUE
B14: ADWELLCH SAS | D14: 3644026.9 | E14: =IF($D$10=0,0,D14/ABS($D$10)) | F14: 3644026.9 | G14: =IF($F$10=0,0,F14/ABS($F$10)) | H14: =D14-F14 | I14: =IF(F14=0,0,H14/ABS(F14)) | J14: TRUE
B15: ALIMENTOS SOSTENIBLES SAS | D15: 0 | E15: =IF($D$10=0,0,D15/ABS($D$10)) | F15: 0 | G15: =IF($F$10=0,0,F15/ABS($F$10)) | H15: =D15-F15 | I15: =IF(F15=0,0,H15/ABS(F15)) | J15: TRUE
B16: ARTEMISA S.A.S BIC | D16: 22044504 | E16: =IF($D$10=0,0,D16/ABS($D$10)) | F16: 22044504 | G16: =IF($F$10=0,0,F16/ABS($F$10)) | H16: =D16-F16 | I16: =IF(F16=0,0,H16/ABS(F16)) | J16: TRUE
B17: Alejandra Muñoz Fernández | D17: 0 | E17: =IF($D$10=0,0,D17/ABS($D$10)) | F17: 0 | G17: =IF($F$10=0,0,F17/ABS($F$10)) | H17: =D17-F17 | I17: =IF(F17=0,0,H17/ABS(F17)) | J17: TRUE
B18: Alfonso Narvaez | D18: 0 | E18: =IF($D$10=0,0,D18/ABS($D$10)) | F18: 0 | G18: =IF($F$10=0,0,F18/ABS($F$10)) | H18: =D18-F18 | I18: =IF(F18=0,0,H18/ABS(F18)) | J18: TRUE
B19: Amelia Bueno | D19: 0 | E19: =IF($D$10=0,0,D19/ABS($D$10)) | F19: 0 | G19: =IF($F$10=0,0,F19/ABS($F$10)) | H19: =D19-F19 | I19: =IF(F19=0,0,H19/ABS(F19)) | J19: TRUE
B20: Ana Maria Rugeles | D20: 0 | E20: =IF($D$10=0,0,D20/ABS($D$10)) | F20: 0 | G20: =IF($F$10=0,0,F20/ABS($F$10)) | H20: =D20-F20 | I20: =IF(F20=0,0,H20/ABS(F20)) | J20: TRUE
B21: Andrea Marcela Martínez Pulido | D21: 0 | E21: =IF($D$10=0,0,D21/ABS($D$10)) | F21: 0 | G21: =IF($F$10=0,0,F21/ABS($F$10)) | H21: =D21-F21 | I21: =IF(F21=0,0,H21/ABS(F21)) | J21: TRUE
B22: Andrea Restrepo | D22: 0 | E22: =IF($D$10=0,0,D22/ABS($D$10)) | F22: 0 | G22: =IF($F$10=0,0,F22/ABS($F$10)) | H22: =D22-F22 | I22: =IF(F22=0,0,H22/ABS(F22)) | J22: TRUE
B23: Artha Group SAS | D23: 0 | E23: =IF($D$10=0,0,D23/ABS($D$10)) | F23: 0 | G23: =IF($F$10=0,0,F23/ABS($F$10)) | H23: =D23-F23 | I23: =IF(F23=0,0,H23/ABS(F23)) | J23: TRUE
... B3173: Yorleidy Sarrazola | D3173: 0 | E3173: =IF($D$10=0,0,D3173/ABS($D$10)) | F3173: 0 | G3173: =IF($F$10=0,0,F3173/ABS($F$10)) | H3173: =D3173-F3173 | I3173: =IF(F3173=0,0,H3173/ABS(F3173)) | J3173: TRUE
B3174: 41350102 - Descuentos | D3174: =SUM(D3175:D3175) | E3174: =IF($D$10=0,0,D3174/ABS($D$10)) | F3174: =SUM(F3175:F3175) | G3174: =IF($F$10=0,0,F3174/ABS($F$10)) | H3174: =D3174-F3174 | I3174: =IF(F3174=0,0,H3174/ABS(F3174)) | J3174: TRUE
B3175: ONLINE Paula Andrea Ramirez Forero | D3175: 0 | E3175: =IF($D$10=0,0,D3175/ABS($D$10)) | F3175: 0 | G3175: =IF($F$10=0,0,F3175/ABS($F$10)) | H3175: =D3175-F3175 | I3175: =IF(F3175=0,0,H3175/ABS(F3175)) | J3175: TRUE
B3176: 41750501 - Devolución en ventas | D3176: =SUM(D3177:D3237) | E3176: =IF($D$10=0,0,D3176/ABS($D$10)) | F3176: =SUM(F3177:F3237) | G3176: =IF($F$10=0,0,F3176/ABS($F$10)) | H3176: =D3176-F3176 | I3176: =IF(F3176=0,0,H3176/ABS(F3176)) | J3176: TRUE
B3177: ACM PHARMA S.A.S | D3177: 0 | E3177: =IF($D$10=0,0,D3177/ABS($D$10)) | F3177: 0 | G3177: =IF($F$10=0,0,F3177/ABS($F$10)) | H3177: =D3177-F3177 | I3177: =IF(F3177=0,0,H3177/ABS(F3177)) | J3177: TRUE
B3178: ADWELLCH SAS | D3178: -761643.54 | E3178: =IF($D$10=0,0,D3178/ABS($D$10)) | F3178: -761643.54 | G3178: =IF($F$10=0,0,F3178/ABS($F$10)) | H3178: =D3178-F3178 | I3178: =IF(F3178=0,0,H3178/ABS(F3178)) | J3178: TRUE
B3179: ARTEMISA S.A.S BIC | D3179: -1055505.9 | E3179: =IF($D$10=0,0,D3179/ABS($D$10)) | F3179: -1055505.9 | G3179: =IF($F$10=0,0,F3179/ABS($F$10)) | H3179: =D3179-F3179 | I3179: =IF(F3179=0,0,H3179/ABS(F3179)) | J3179: TRUE
B3180: AUDIFARMA S.A. | D3180: 0 | E3180: =IF($D$10=0,0,D3180/ABS($D$10)) | F3180: 0 | G3180: =IF($F$10=0,0,F3180/ABS($F$10)) | H3180: =D3180-F3180 | I3180: =IF(F3180=0,0,H3180/ABS(F3180)) | J3180: TRUE
B3181: CAJA COLOMBIANA DE SUBSIDIO FAMILIAR COLSUBSIDIO | D3181: 0 | E3181: =IF($D$10=0,0,D3181/ABS($D$10)) | F3181: 0 | G3181: =IF($F$10=0,0,F3181/ABS($F$10)) | H3181: =D3181-F3181 | I3181: =IF(F3181=0,0,H3181/ABS(F3181)) | J3181: TRUE
B3182: COCOFIT MERCADO SALUDABLE S.A.S. | D3182: 0 | E3182: =IF($D$10=0,0,D3182/ABS($D$10)) | F3182: 0 | G3182: =IF($F$10=0,0,F3182/ABS($F$10)) | H3182: =D3182-F3182 | I3182: =IF(F3182=0,0,H3182/ABS(F3182)) | J3182: TRUE
B3183: Clavijo Martinez Inversiones cia s en c | D3183: 0 | E3183: =IF($D$10=0,0,D3183/ABS($D$10)) | F3183: 0 | G3183: =IF($F$10=0,0,F3183/ABS($F$10)) | H3183: =D3183-F3183 | I3183: =IF(F3183=0,0,H3183/ABS(F3183)) | J3183: TRUE
B3184: Consumidor Final | D3184: -841092.43 | E3184: =IF($D$10=0,0,D3184/ABS($D$10)) | F3184: -841092.43 | G3184: =IF($F$10=0,0,F3184/ABS($F$10)) | H3184: =D3184-F3184 | I3184: =IF(F3184=0,0,H3184/ABS(F3184)) | J3184: TRUE
B3185: DANIELA ARBELAEZ | D3185: 0 | E3185: =IF($D$10=0,0,D3185/ABS($D$10)) | F3185: 0 | G3185: =IF($F$10=0,0,F3185/ABS($F$10)) | H3185: =D3185-F3185 | I3185: =IF(F3185=0,0,H3185/ABS(F3185)) | J3185: TRUE
B3186: DISTRIBUIDORA PASTEUR | D3186: -25953413 | E3186: =IF($D$10=0,0,D3186/ABS($D$10)) | F3186: -25953413 | G3186: =IF($F$10=0,0,F3186/ABS($F$10)) | H3186: =D3186-F3186 | I3186: =IF(F3186=0,0,H3186/ABS(F3186)) | J3186: TRUE
B3187: DISTRIBUIDORA SALUD NATURAL S.A.S | D3187: 0 | E3187: =IF($D$10=0,0,D3187/ABS($D$10)) | F3187: 0 | G3187: =IF($F$10=0,0,F3187/ABS($F$10)) | H3187: =D3187-F3187 | I3187: =IF(F3187=0,0,H3187/ABS(F3187)) | J3187: TRUE
B3188: Droguerías Juliao S.A Mariela Ester Juliao del Río | D3188: -2575149.9 | E3188: =IF($D$10=0,0,D3188/ABS($D$10)) | F3188: -2575149.9 | G3188: =IF($F$10=0,0,F3188/ABS($F$10)) | H3188: =D3188-F3188 | I3188: =IF(F3188=0,0,H3188/ABS(F3188)) | J3188: TRUE
... B3237: VITAINTEGRAL SAS | D3237: 0 | E3237: =IF($D$10=0,0,D3237/ABS($D$10)) | F3237: 0 | G3237: =IF($F$10=0,0,F3237/ABS($F$10)) | H3237: =D3237-F3237 | I3237: =IF(F3237=0,0,H3237/ABS(F3237)) | J3237: TRUE
B3238: 41750502 - Devolución en servicios | D3238: =SUM(D3239:D3243) | E3238: =IF($D$10=0,0,D3238/ABS($D$10)) | F3238: =SUM(F3239:F3243) | G3238: =IF($F$10=0,0,F3238/ABS($F$10)) | H3238: =D3238-F3238 | I3238: =IF(F3238=0,0,H3238/ABS(F3238)) | J3238: TRUE
B3239: ARTEMISA S.A.S BIC | D3239: 0 | E3239: =IF($D$10=0,0,D3239/ABS($D$10)) | F3239: 0 | G3239: =IF($F$10=0,0,F3239/ABS($F$10)) | H3239: =D3239-F3239 | I3239: =IF(F3239=0,0,H3239/ABS(F3239)) | J3239: TRUE
B3240: Clavijo Martinez Inversiones cia s en c | D3240: 0 | E3240: =IF($D$10=0,0,D3240/ABS($D$10)) | F3240: 0 | G3240: =IF($F$10=0,0,F3240/ABS($F$10)) | H3240: =D3240-F3240 | I3240: =IF(F3240=0,0,H3240/ABS(F3240)) | J3240: TRUE
B3241: DANIELA ARBELAEZ | D3241: 0 | E3241: =IF($D$10=0,0,D3241/ABS($D$10)) | F3241: 0 | G3241: =IF($F$10=0,0,F3241/ABS($F$10)) | H3241: =D3241-F3241 | I3241: =IF(F3241=0,0,H3241/ABS(F3241)) | J3241: TRUE
B3242: INVERSIONES FARMACIAS ALPHA S.A.S | D3242: 0 | E3242: =IF($D$10=0,0,D3242/ABS($D$10)) | F3242: 0 | G3242: =IF($F$10=0,0,F3242/ABS($F$10)) | H3242: =D3242-F3242 | I3242: =IF(F3242=0,0,H3242/ABS(F3242)) | J3242: TRUE
B3243: VITAINTEGRAL SAS | D3243: 0 | E3243: =IF($D$10=0,0,D3243/ABS($D$10)) | F3243: 0 | G3243: =IF($F$10=0,0,F3243/ABS($F$10)) | H3243: =D3243-F3243 | I3243: =IF(F3243=0,0,H3243/ABS(F3243)) | J3243: TRUE
B3244: 41750503 - Devolución en descuentos | D3244: =SUM(D3245:D3245) | E3244: =IF($D$10=0,0,D3244/ABS($D$10)) | F3244: =SUM(F3245:F3245) | G3244: =IF($F$10=0,0,F3244/ABS($F$10)) | H3244: =D3244-F3244 | I3244: =IF(F3244=0,0,H3244/ABS(F3244)) | J3244: TRUE
B3245: ONLINE Paula Andrea Ramirez Forero | D3245: 0 | E3245: =IF($D$10=0,0,D3245/ABS($D$10)) | F3245: 0 | G3245: =IF($F$10=0,0,F3245/ABS($F$10)) | H3245: =D3245-F3245 | I3245: =IF(F3245=0,0,H3245/ABS(F3245)) | J3245: TRUE
B3246: 41800101 - Servicios | D3246: =SUM(D3247:D3330) | E3246: =IF($D$10=0,0,D3246/ABS($D$10)) | F3246: =SUM(F3247:F3330) | G3246: =IF($F$10=0,0,F3246/ABS($F$10)) | H3246: =D3246-F3246 | I3246: =IF(F3246=0,0,H3246/ABS(F3246)) | J3246: TRUE
B3247: ACM PHARMA S.A.S | D3247: 0 | E3247: =IF($D$10=0,0,D3247/ABS($D$10)) | F3247: 0 | G3247: =IF($F$10=0,0,F3247/ABS($F$10)) | H3247: =D3247-F3247 | I3247: =IF(F3247=0,0,H3247/ABS(F3247)) | J3247: TRUE
B3248: ALIMENTOS SOSTENIBLES SAS | D3248: 0 | E3248: =IF($D$10=0,0,D3248/ABS($D$10)) | F3248: 0 | G3248: =IF($F$10=0,0,F3248/ABS($F$10)) | H3248: =D3248-F3248 | I3248: =IF(F3248=0,0,H3248/ABS(F3248)) | J3248: TRUE
B3249: ARTEMISA S.A.S BIC | D3249: 0 | E3249: =IF($D$10=0,0,D3249/ABS($D$10)) | F3249: 0 | G3249: =IF($F$10=0,0,F3249/ABS($F$10)) | H3249: =D3249-F3249 | I3249: =IF(F3249=0,0,H3249/ABS(F3249)) | J3249: TRUE
B3250: Alejandra Muñoz Fernández | D3250: 0 | E3250: =IF($D$10=0,0,D3250/ABS($D$10)) | F3250: 0 | G3250: =IF($F$10=0,0,F3250/ABS($F$10)) | H3250: =D3250-F3250 | I3250: =IF(F3250=0,0,H3250/ABS(F3250)) | J3250: TRUE
B3251: Alfonso Narvaez | D3251: 0 | E3251: =IF($D$10=0,0,D3251/ABS($D$10)) | F3251: 0 | G3251: =IF($F$10=0,0,F3251/ABS($F$10)) | H3251: =D3251-F3251 | I3251: =IF(F3251=0,0,H3251/ABS(F3251)) | J3251: TRUE
B3252: Amelia Bueno | D3252: 0 | E3252: =IF($D$10=0,0,D3252/ABS($D$10)) | F3252: 0 | G3252: =IF($F$10=0,0,F3252/ABS($F$10)) | H3252: =D3252-F3252 | I3252: =IF(F3252=0,0,H3252/ABS(F3252)) | J3252: TRUE
B3253: Andrea Marcela Martínez Pulido | D3253: 0 | E3253: =IF($D$10=0,0,D3253/ABS($D$10)) | F3253: 0 | G3253: =IF($F$10=0,0,F3253/ABS($F$10)) | H3253: =D3253-F3253 | I3253: =IF(F3253=0,0,H3253/ABS(F3253)) | J3253: TRUE
B3254: Andrea Restrepo | D3254: 0 | E3254: =IF($D$10=0,0,D3254/ABS($D$10)) | F3254: 0 | G3254: =IF($F$10=0,0,F3254/ABS($F$10)) | H3254: =D3254-F3254 | I3254: =IF(F3254=0,0,H3254/ABS(F3254)) | J3254: TRUE
B3255: COCOFIT MERCADO SALUDABLE S.A.S. | D3255: 0 | E3255: =IF($D$10=0,0,D3255/ABS($D$10)) | F3255: 0 | G3255: =IF($F$10=0,0,F3255/ABS($F$10)) | H3255: =D3255-F3255 | I3255: =IF(F3255=0,0,H3255/ABS(F3255)) | J3255: TRUE
B3256: COPRA GLUTEN FREE S.A.S - green house | D3256: 0 | E3256: =IF($D$10=0,0,D3256/ABS($D$10)) | F3256: 0 | G3256: =IF($F$10=0,0,F3256/ABS($F$10)) | H3256: =D3256-F3256 | I3256: =IF(F3256=0,0,H3256/ABS(F3256)) | J3256: TRUE
B3257: CORPOFIT S.A.S. | D3257: 0 | E3257: =IF($D$10=0,0,D3257/ABS($D$10)) | F3257: 0 | G3257: =IF($F$10=0,0,F3257/ABS($F$10)) | H3257: =D3257-F3257 | I3257: =IF(F3257=0,0,H3257/ABS(F3257)) | J3257: TRUE
B3258: Carolina Hoyos Cardona | D3258: 0 | E3258: =IF($D$10=0,0,D3258/ABS($D$10)) | F3258: 0 | G3258: =IF($F$10=0,0,F3258/ABS($F$10)) | H3258: =D3258-F3258 | I3258: =IF(F3258=0,0,H3258/ABS(F3258)) | J3258: TRUE
... B3330: Yina Yereinza Acevedo Álvarez | D3330: 0 | E3330: =IF($D$10=0,0,D3330/ABS($D$10)) | F3330: 0 | G3330: =IF($F$10=0,0,F3330/ABS($F$10)) | H3330: =D3330-F3330 | I3330: =IF(F3330=0,0,H3330/ABS(F3330)) | J3330: TRUE
B3331: 41800102 - Descuentos en servicios | D3331: =SUM(D3332:D4068) | E3331: =IF($D$10=0,0,D3331/ABS($D$10)) | F3331: =SUM(F3332:F4068) | G3331: =IF($F$10=0,0,F3331/ABS($F$10)) | H3331: =D3331-F3331 | I3331: =IF(F3331=0,0,H3331/ABS(F3331)) | J3331: TRUE
B3332: PANGEA NATURAL PRODUCTS S.A.S. | D3332: 0 | E3332: =IF($D$10=0,0,D3332/ABS($D$10)) | F3332: 0 | G3332: =IF($F$10=0,0,F3332/ABS($F$10)) | H3332: =D3332-F3332 | I3332: =IF(F3332=0,0,H3332/ABS(F3332)) | J3332: TRUE
B3333: ADWELLCH SAS | D3333: 0 | E3333: =IF($D$10=0,0,D3333/ABS($D$10)) | F3333: 0 | G3333: =IF($F$10=0,0,F3333/ABS($F$10)) | H3333: =D3333-F3333 | I3333: =IF(F3333=0,0,H3333/ABS(F3333)) | J3333: TRUE
B3334: ARTEMISA S.A.S BIC | D3334: 0 | E3334: =IF($D$10=0,0,D3334/ABS($D$10)) | F3334: 0 | G3334: =IF($F$10=0,0,F3334/ABS($F$10)) | H3334: =D3334-F3334 | I3334: =IF(F3334=0,0,H3334/ABS(F3334)) | J3334: TRUE
B3335: Carolina Bula | D3335: 0 | E3335: =IF($D$10=0,0,D3335/ABS($D$10)) | F3335: 0 | G3335: =IF($F$10=0,0,F3335/ABS($F$10)) | H3335: =D3335-F3335 | I3335: =IF(F3335=0,0,H3335/ABS(F3335)) | J3335: TRUE
B3336: Clavijo Martinez Inversiones cia s en c | D3336: 0 | E3336: =IF($D$10=0,0,D3336/ABS($D$10)) | F3336: 0 | G3336: =IF($F$10=0,0,F3336/ABS($F$10)) | H3336: =D3336-F3336 | I3336: =IF(F3336=0,0,H3336/ABS(F3336)) | J3336: TRUE
B3337: Consumidor Final | D3337: -82815.15 | E3337: =IF($D$10=0,0,D3337/ABS($D$10)) | F3337: -82815.15 | G3337: =IF($F$10=0,0,F3337/ABS($F$10)) | H3337: =D3337-F3337 | I3337: =IF(F3337=0,0,H3337/ABS(F3337)) | J3337: TRUE
B3338: DISTRIBUIDORA PASTEUR | D3338: 0 | E3338: =IF($D$10=0,0,D3338/ABS($D$10)) | F3338: 0 | G3338: =IF($F$10=0,0,F3338/ABS($F$10)) | H3338: =D3338-F3338 | I3338: =IF(F3338=0,0,H3338/ABS(F3338)) | J3338: TRUE
B3339: Daniela Cardona Marin | D3339: 0 | E3339: =IF($D$10=0,0,D3339/ABS($D$10)) | F3339: 0 | G3339: =IF($F$10=0,0,F3339/ABS($F$10)) | H3339: =D3339-F3339 | I3339: =IF(F3339=0,0,H3339/ABS(F3339)) | J3339: TRUE
B3340: Elian Enrique Meza Mercado | D3340: 0 | E3340: =IF($D$10=0,0,D3340/ABS($D$10)) | F3340: 0 | G3340: =IF($F$10=0,0,F3340/ABS($F$10)) | H3340: =D3340-F3340 | I3340: =IF(F3340=0,0,H3340/ABS(F3340)) | J3340: TRUE
B3341: FD SAN JORGE SAS | D3341: 0 | E3341: =IF($D$10=0,0,D3341/ABS($D$10)) | F3341: 0 | G3341: =IF($F$10=0,0,F3341/ABS($F$10)) | H3341: =D3341-F3341 | I3341: =IF(F3341=0,0,H3341/ABS(F3341)) | J3341: TRUE
B3342: Gladys Helena Tobar Calderon | D3342: 0 | E3342: =IF($D$10=0,0,D3342/ABS($D$10)) | F3342: 0 | G3342: =IF($F$10=0,0,F3342/ABS($F$10)) | H3342: =D3342-F3342 | I3342: =IF(F3342=0,0,H3342/ABS(F3342)) | J3342: TRUE
B3343: Go Healthy Vive Saludable SAS | D3343: 0 | E3343: =IF($D$10=0,0,D3343/ABS($D$10)) | F3343: 0 | G3343: =IF($F$10=0,0,F3343/ABS($F$10)) | H3343: =D3343-F3343 | I3343: =IF(F3343=0,0,H3343/ABS(F3343)) | J3343: TRUE
... B4068: VITAINTEGRAL SAS | D4068: 0 | E4068: =IF($D$10=0,0,D4068/ABS($D$10)) | F4068: 0 | G4068: =IF($F$10=0,0,F4068/ABS($F$10)) | H4068: =D4068-F4068 | I4068: =IF(F4068=0,0,H4068/ABS(F4068)) | J4068: TRUE
B4069: MENOS: COSTO DE VENTAS | D4069: =SUM(D4070,D4073,D4082,D4098,D4109,D4112,D4114,D4117) | E4069: =IF($D$10=0,0,D4069/ABS($D$10)) | F4069: =SUM(F4070,F4073,F4082,F4098,F4109,F4112,F4114,F4117) | G4069: =IF($F$10=0,0,F4069/ABS($F$10)) | H4069: =D4069-F4069 | I4069: =IF(F4069=0,0,H4069/ABS(F4069)) | J4069: TRUE
B4070: 61054505 - Fertilizantes e insumos para cultivos | D4070: =SUM(D4071:D4072) | E4070: =IF($D$10=0,0,D4070/ABS($D$10)) | F4070: =SUM(F4071:F4072) | G4070: =IF($F$10=0,0,F4070/ABS($F$10)) | H4070: =D4070-F4070 | I4070: =IF(F4070=0,0,H4070/ABS(F4070)) | J4070: TRUE
B4071: COOPERATIVA MULTIACTIVA UNIAGRO | D4071: 0 | E4071: =IF($D$10=0,0,D4071/ABS($D$10)) | F4071: 0 | G4071: =IF($F$10=0,0,F4071/ABS($F$10)) | H4071: =D4071-F4071 | I4071: =IF(F4071=0,0,H4071/ABS(F4071)) | J4071: TRUE
B4072: PRECOOPERATIVA INSUMOS AGRICOLAS DEL VALLE | D4072: 0 | E4072: =IF($D$10=0,0,D4072/ABS($D$10)) | F4072: 0 | G4072: =IF($F$10=0,0,F4072/ABS($F$10)) | H4072: =D4072-F4072 | I4072: =IF(F4072=0,0,H4072/ABS(F4072)) | J4072: TRUE
B4073: 613538 - Productos farmacéuticos y medicinales | D4073: =SUM(D4074:D4081) | E4073: =IF($D$10=0,0,D4073/ABS($D$10)) | F4073: =SUM(F4074:F4081) | G4073: =IF($F$10=0,0,F4073/ABS($F$10)) | H4073: =D4073-F4073 | I4073: =IF(F4073=0,0,H4073/ABS(F4073)) | J4073: TRUE
B4074: AGRICOLA HIMALAYA S.A | D4074: 0 | E4074: =IF($D$10=0,0,D4074/ABS($D$10)) | F4074: 0 | G4074: =IF($F$10=0,0,F4074/ABS($F$10)) | H4074: =D4074-F4074 | I4074: =IF(F4074=0,0,H4074/ABS(F4074)) | J4074: TRUE
B4075: ALISUM ALIMENTOS Y SUMINISTROS SAS | D4075: 0 | E4075: =IF($D$10=0,0,D4075/ABS($D$10)) | F4075: 0 | G4075: =IF($F$10=0,0,F4075/ABS($F$10)) | H4075: =D4075-F4075 | I4075: =IF(F4075=0,0,H4075/ABS(F4075)) | J4075: TRUE
B4076: ASOCIACION AGROPIMIENTERA VALLE DEL GUAMEZ | D4076: 0 | E4076: =IF($D$10=0,0,D4076/ABS($D$10)) | F4076: 0 | G4076: =IF($F$10=0,0,F4076/ABS($F$10)) | H4076: =D4076-F4076 | I4076: =IF(F4076=0,0,H4076/ABS(F4076)) | J4076: TRUE
B4077: CONNPLANTS SAS | D4077: 0 | E4077: =IF($D$10=0,0,D4077/ABS($D$10)) | F4077: 0 | G4077: =IF($F$10=0,0,F4077/ABS($F$10)) | H4077: =D4077-F4077 | I4077: =IF(F4077=0,0,H4077/ABS(F4077)) | J4077: TRUE
B4078: LA CONCEPCION SA | D4078: 0 | E4078: =IF($D$10=0,0,D4078/ABS($D$10)) | F4078: 0 | G4078: =IF($F$10=0,0,F4078/ABS($F$10)) | H4078: =D4078-F4078 | I4078: =IF(F4078=0,0,H4078/ABS(F4078)) | J4078: TRUE
B4079: LA VITAL COLOMBIA SAS | D4079: 0 | E4079: =IF($D$10=0,0,D4079/ABS($D$10)) | F4079: 0 | G4079: =IF($F$10=0,0,F4079/ABS($F$10)) | H4079: =D4079-F4079 | I4079: =IF(F4079=0,0,H4079/ABS(F4079)) | J4079: TRUE
B4080: MERCANTIL CONTINENTAL SAS | D4080: 0 | E4080: =IF($D$10=0,0,D4080/ABS($D$10)) | F4080: 0 | G4080: =IF($F$10=0,0,F4080/ABS($F$10)) | H4080: =D4080-F4080 | I4080: =IF(F4080=0,0,H4080/ABS(F4080)) | J4080: TRUE
B4081: ORGANICOS CAMPO S SAS | D4081: 0 | E4081: =IF($D$10=0,0,D4081/ABS($D$10)) | F4081: 0 | G4081: =IF($F$10=0,0,F4081/ABS($F$10)) | H4081: =D4081-F4081 | I4081: =IF(F4081=0,0,H4081/ABS(F4081)) | J4081: TRUE
B4082: 613566 - Envase y empaque | D4082: =SUM(D4083:D4097) | E4082: =IF($D$10=0,0,D4082/ABS($D$10)) | F4082: =SUM(F4083:F4097) | G4082: =IF($F$10=0,0,F4082/ABS($F$10)) | H4082: =D4082-F4082 | I4082: =IF(F4082=0,0,H4082/ABS(F4082)) | J4082: TRUE
B4083: BOLSAS Y PLASTICOS LA 15 LTDA | D4083: 0 | E4083: =IF($D$10=0,0,D4083/ABS($D$10)) | F4083: 0 | G4083: =IF($F$10=0,0,F4083/ABS($F$10)) | H4083: =D4083-F4083 | I4083: =IF(F4083=0,0,H4083/ABS(F4083)) | J4083: TRUE
B4084: ABORIGEN CIENCIA ANCESTRAL S.A.S | D4084: 0 | E4084: =IF($D$10=0,0,D4084/ABS($D$10)) | F4084: 0 | G4084: =IF($F$10=0,0,F4084/ABS($F$10)) | H4084: =D4084-F4084 | I4084: =IF(F4084=0,0,H4084/ABS(F4084)) | J4084: TRUE
B4085: AMAZON OPERATION SERVICES COLOMBIA SAS | D4085: 0 | E4085: =IF($D$10=0,0,D4085/ABS($D$10)) | F4085: 0 | G4085: =IF($F$10=0,0,F4085/ABS($F$10)) | H4085: =D4085-F4085 | I4085: =IF(F4085=0,0,H4085/ABS(F4085)) | J4085: TRUE
B4086: CAJAS Y EMPAQUES LEITON | D4086: 0 | E4086: =IF($D$10=0,0,D4086/ABS($D$10)) | F4086: 0 | G4086: =IF($F$10=0,0,F4086/ABS($F$10)) | H4086: =D4086-F4086 | I4086: =IF(F4086=0,0,H4086/ABS(F4086)) | J4086: TRUE
B4087: CONNPLANTS SAS | D4087: 0 | E4087: =IF($D$10=0,0,D4087/ABS($D$10)) | F4087: 0 | G4087: =IF($F$10=0,0,F4087/ABS($F$10)) | H4087: =D4087-F4087 | I4087: =IF(F4087=0,0,H4087/ABS(F4087)) | J4087: TRUE
B4088: EMPACKING GLOBAL SAS | D4088: 2025000 | E4088: =IF($D$10=0,0,D4088/ABS($D$10)) | F4088: 2025000 | G4088: =IF($F$10=0,0,F4088/ABS($F$10)) | H4088: =D4088-F4088 | I4088: =IF(F4088=0,0,H4088/ABS(F4088)) | J4088: TRUE
B4089: FARMAVIT EMPRESA ASOCIATIVA DE TRABAJO | D4089: 0 | E4089: =IF($D$10=0,0,D4089/ABS($D$10)) | F4089: 0 | G4089: =IF($F$10=0,0,F4089/ABS($F$10)) | H4089: =D4089-F4089 | I4089: =IF(F4089=0,0,H4089/ABS(F4089)) | J4089: TRUE
B4090: FITOBIOCELL SAS | D4090: 0 | E4090: =IF($D$10=0,0,D4090/ABS($D$10)) | F4090: 0 | G4090: =IF($F$10=0,0,F4090/ABS($F$10)) | H4090: =D4090-F4090 | I4090: =IF(F4090=0,0,H4090/ABS(F4090)) | J4090: TRUE
B4091: GRUPO NUTRIT LAB SAS | D4091: 0 | E4091: =IF($D$10=0,0,D4091/ABS($D$10)) | F4091: 0 | G4091: =IF($F$10=0,0,F4091/ABS($F$10)) | H4091: =D4091-F4091 | I4091: =IF(F4091=0,0,H4091/ABS(F4091)) | J4091: TRUE
B4092: NEW PLAST SAS | D4092: 0 | E4092: =IF($D$10=0,0,D4092/ABS($D$10)) | F4092: 0 | G4092: =IF($F$10=0,0,F4092/ABS($F$10)) | H4092: =D4092-F4092 | I4092: =IF(F4092=0,0,H4092/ABS(F4092)) | J4092: TRUE
B4093: NOGUERA GOMEZ ALEXANDER | D4093: 27720 | E4093: =IF($D$10=0,0,D4093/ABS($D$10)) | F4093: 27720 | G4093: =IF($F$10=0,0,F4093/ABS($F$10)) | H4093: =D4093-F4093 | I4093: =IF(F4093=0,0,H4093/ABS(F4093)) | J4093: TRUE
B4094: PRODUCCION GRAFICA EDITORES SAS | D4094: 1672000 | E4094: =IF($D$10=0,0,D4094/ABS($D$10)) | F4094: 1672000 | G4094: =IF($F$10=0,0,F4094/ABS($F$10)) | H4094: =D4094-F4094 | I4094: =IF(F4094=0,0,H4094/ABS(F4094)) | J4094: TRUE
...

Sheet Notas
A1: PANGEA NATURAL PRODUCTS S.A.S.
A2: NIT. 901.196.219-5
A3: NOTAS A LOS ESTADOS FINANCIEROS
A4: (Expresados en pesos colombianos) — MARZO de 2026
A6: NOTA 1 Efectivo y Equivalentes al Efectivo
A7: CTA | B7: Cuenta / Tercero | C7: MARZO de 2026 | D7: PERIODO ANTERIOR TEST | E7: Variación | F7: % Variación
A8: 1105050101 | B8: Caja Menor | C8: =SUM(C9:C210) | D8: =SUM(D9:D210) | E8: =C8-D8 | F8: =IF(D8=0,0,E8/ABS(D8))
B9: ALIMENTOS SOSTENIBLES SAS | C9: 83000 | D9: 83000 | E9: =C9-D9 | F9: =IF(D9=0,0,E9/ABS(D9))
B10: ALVARO SILVA RAMOS | C10: -18000 | D10: -18000 | E10: =C10-D10 | F10: =IF(D10=0,0,E10/ABS(D10))
B11: AUDIFARMA S.A. | C11: -515375 | D11: -515375 | E11: =C11-D11 | F11: =IF(D11=0,0,E11/ABS(D11))
B12: Abhay Organica | C12: 199998 | D12: 199998 | E12: =C12-D12 | F12: =IF(D12=0,0,E12/ABS(D12))
B13: Adriana Castrillon | C13: 460000 | D13: 460000 | E13: =C13-D13 | F13: =IF(D13=0,0,E13/ABS(D13))
B14: Adriana Jaramillo | C14: 50001 | D14: 50001 | E14: =C14-D14 | F14: =IF(D14=0,0,E14/ABS(D14))
B15: Adriana Vega | C15: 180000 | D15: 180000 | E15: =C15-D15 | F15: =IF(D15=0,0,E15/ABS(D15))
B16: Alejandra Ortiz | C16: 30000 | D16: 30000 | E16: =C16-D16 | F16: =IF(D16=0,0,E16/ABS(D16))
B17: Alfonso Narvaez | C17: 650000 | D17: 650000 | E17: =C17-D17 | F17: =IF(D17=0,0,E17/ABS(D17))
B18: Alfredo Cienfuegos | C18: 210000 | D18: 210000 | E18: =C18-D18 | F18: =IF(D18=0,0,E18/ABS(D18))
B19: Alfredo Otero | C19: 70000 | D19: 70000 | E19: =C19-D19 | F19: =IF(D19=0,0,E19/ABS(D19))
B20: Alicia Cliente | C20: 570000 | D20: 570000 | E20: =C20-D20 | F20: =IF(D20=0,0,E20/ABS(D20))
... B210: isabela Arias | C210: 215000 | D210: 215000 | E210: =C210-D210 | F210: =IF(D210=0,0,E210/ABS(D210))
A211: 11051001 | B211: Cajas menores | C211: =SUM(C212:C217) | D211: =SUM(D212:D217) | E211: =C211-D211 | F211: =IF(D211=0,0,E211/ABS(D211))
B212: AEROVIAS DEL CONTINENTE AMERICANO S.A. | C212: -708459.44 | D212: -708459.44 | E212: =C212-D212 | F212: =IF(D212=0,0,E212/ABS(D212))
B213: FRISBY S.A. | C213: -23300 | D213: -23300 | E213: =C213-D213 | F213: =IF(D213=0,0,E213/ABS(D213))
B214: MUNICIPIO DE SANTIAGO DE CALI | C214: -253000 | D214: -253000 | E214: =C214-D214 | F214: =IF(D214=0,0,E214/ABS(D214))
B215: OLGA BARBOSA DE HURTADO | C215: -100000 | D215: -100000 | E215: =C215-D215 | F215: =IF(D215=0,0,E215/ABS(D215))
B216: PANGEA NATURAL PRODUCTS S.A.S. | C216: 248059.44 | D216: 248059.44 | E216: =C216-D216 | F216: =IF(D216=0,0,E216/ABS(D216))
B217: Sebastian Mendoza Castaño | C217: 1436700 | D217: 1436700 | E217: =C217-D217 | F217: =IF(D217=0,0,E217/ABS(D217))
A218: 11100503 | B218: Cuenta Cte. Banco de Bogota | C218: =SUM(C219:C270) | D218: =SUM(D219:D270) | E218: =C218-D218 | F218: =IF(D218=0,0,E218/ABS(D218))
B219: 900546298 | C219: -67000 | D219: -67000 | E219: =C219-D219 | F219: =IF(D219=0,0,E219/ABS(D219))
B220: ALIMENTOS SOSTENIBLES SAS | C220: 2576073 | D220: 2576073 | E220: =C220-D220 | F220: =IF(D220=0,0,E220/ABS(D220))
B221: ALMACENES LA 14 S.A. | C221: -132129 | D221: -132129 | E221: =C221-D221 | F221: =IF(D221=0,0,E221/ABS(D221))
B222: ANDRES FELIPE SANTACOLOMA | C222: -491370 | D222: -491370 | E222: =C222-D222 | F222: =IF(D222=0,0,E222/ABS(D222))
B223: ANILLANDO CALI LTDA | C223: -45000 | D223: -45000 | E223: =C223-D223 | F223: =IF(D223=0,0,E223/ABS(D223))
B224: Administradora de Fondos de Pensiones y Cesantía Protección S.A. | C224: -496070 | D224: -496070 | E224: =C224-D224 | F224: =IF(D224=0,0,E224/ABS(D224))
B225: Alejandro Giraldo Mejia | C225: -280020 | D225: -280020 | E225: =C225-D225 | F225: =IF(D225=0,0,E225/ABS(D225))
B226: Banco de bogotá | C226: 12963977 | D226: 12963977 | E226: =C226-D226 | F226: =IF(D226=0,0,E226/ABS(D226))
B227: CAMILO ANDRES TINJACA VILLAMIL | C227: -120000 | D227: -120000 | E227: =C227-D227 | F227: =IF(D227=0,0,E227/ABS(D227))
B228: CAROLINA GALEANO GARCIA | C228: -2879326 | D228: -2879326 | E228: =C228-D228 | F228: =IF(D228=0,0,E228/ABS(D228))
B229: CLAUDIA ARACELY TORRES RODRIGUEZ | C229: -220000 | D229: -220000 | E229: =C229-D229 | F229: =IF(D229=0,0,E229/ABS(D229))
B230: DIAN | C230: -2039000 | D230: -2039000 | E230: =C230-D230 | F230: =IF(D230=0,0,E230/ABS(D230))
... B270: VITAFITNESS SAS | C270: 2256717 | D270: 2256717 | E270: =C270-D270 | F270: =IF(D270=0,0,E270/ABS(D270))
A271: 11100504 | B271: Cuenta Cte. Bancolombia 1211 | C271: =SUM(C272:C3810) | D271: =SUM(D272:D3810) | E271: =C271-D271 | F271: =IF(D271=0,0,E271/ABS(D271))
B272: ABORIGEN CIENCIA ANCESTRAL S.A.S | C272: -1072530147 | D272: -1072530147 | E272: =C272-D272 | F272: =IF(D272=0,0,E272/ABS(D272))
B273: ACCORHOTELS COLOMBIA S.A | C273: -982083 | D273: -982083 | E273: =C273-D273 | F273: =IF(D273=0,0,E273/ABS(D273))
B274: ACH Colombia S.A. | C274: -10242400 | D274: -10242400 | E274: =C274-D274 | F274: =IF(D274=0,0,E274/ABS(D274))
B275: ACM PHARMA S.A.S | C275: 12922349 | D275: 12922349 | E275: =C275-D275 | F275: =IF(D275=0,0,E275/ABS(D275))
B276: ADRIANA DIAZ QUINTERO | C276: -3742000 | D276: -3742000 | E276: =C276-D276 | F276: =IF(D276=0,0,E276/ABS(D276))
B277: ADWELLCH SAS | C277: 1.7765524e+08 | D277: 1.7765524e+08 | E277: =C277-D277 | F277: =IF(D277=0,0,E277/ABS(D277))
B278: AERO REPUBLICA S.A | C278: -1189695.9 | D278: -1189695.9 | E278: =C278-D278 | F278: =IF(D278=0,0,E278/ABS(D278))
B279: AEROVIAS DE INTEGRACION REGIONAL S A | C279: -6699698 | D279: -6699698 | E279: =C279-D279 | F279: =IF(D279=0,0,E279/ABS(D279))
B280: AEROVIAS DEL CONTINENTE AMERICANO S.A. | C280: -28693421 | D280: -28693421 | E280: =C280-D280 | F280: =IF(D280=0,0,E280/ABS(D280))
B281: AGUSTIN ARMANDO POVEDA OVIEDO | C281: -4018000 | D281: -4018000 | E281: =C281-D281 | F281: =IF(D281=0,0,E281/ABS(D281))
B282: AIRBNB | C282: -558644 | D282: -558644 | E282: =C282-D282 | F282: =IF(D282=0,0,E282/ABS(D282))
B283: ALACENA | C283: 970999.54 | D283: 970999.54 | E283: =C283-D283 | F283: =IF(D283=0,0,E283/ABS(D283))
... B3810: Ángela Rodríguez | C3810: 160000 | D3810: 160000 | E3810: =C3810-D3810 | F3810: =IF(D3810=0,0,E3810/ABS(D3810))
A3811: 11100505 | B3811: Pagos en línea Mercado Pago | C3811: =SUM(C3812:C3813) | D3811: =SUM(D3812:D3813) | E3811: =C3811-D3811 | F3811: =IF(D3811=0,0,E3811/ABS(D3811))
B3812: Mercadopago Colombia Ltda | C3812: -306421.94 | D3812: -306421.94 | E3812: =C3812-D3812 | F3812: =IF(D3812=0,0,E3812/ABS(D3812))
B3813: PANGEA NATURAL PRODUCTS S.A.S. | C3813: 306421.94 | D3813: 306421.94 | E3813: =C3813-D3813 | F3813: =IF(D3813=0,0,E3813/ABS(D3813))
A3814: 11100506 | B3814: Mercadopago | C3814: =SUM(C3815:C6892) | D3814: =SUM(D3815:D6892) | E3814: =C3814-D3814 | F3814: =IF(D3814=0,0,E3814/ABS(D3814))
B3815: Banco de bogotá | C3815: -2.0210371e+08 | D3815: -2.0210371e+08 | E3815: =C3815-D3815 | F3815: =IF(D3815=0,0,E3815/ABS(D3815))
B3816: Carolina Hoyos Cardona | C3816: 3655688.7 | D3816: 3655688.7 | E3816: =C3816-D3816 | F3816: =IF(D3816=0,0,E3816/ABS(D3816))
B3817: Consumidor Final | C3817: 4199430 | D3817: 4199430 | E3817: =C3817-D3817 | F3817: =IF(D3817=0,0,E3817/ABS(D3817))
B3818: DOMINICAS HIJAS DE NUESTRA SEÑORA DE NAZARETH | C3818: 68500 | D3818: 68500 | E3818: =C3818-D3818 | F3818: =IF(D3818=0,0,E3818/ABS(D3818))
B3819: Geicer Dorys Bedoya Marín | C3819: 3274892.6 | D3819: 3274892.6 | E3819: =C3819-D3819 | F3819: =IF(D3819=0,0,E3819/ABS(D3819))
B3820: Gustavo Durazo | C3820: 2148369 | D3820: 2148369 | E3820: =C3820-D3820 | F3820: =IF(D3820=0,0,E3820/ABS(D3820))
B3821: INFINITO MEDICAL SERVICE DROGUERIA-HOMEOPATIA SAS | C3821: 5945578.6 | D3821: 5945578.6 | E3821: =C3821-D3821 | F3821: =IF(D3821=0,0,E3821/ABS(D3821))
B3822: Manuel Londoño | C3822: 2071280 | D3822: 2071280 | E3822: =C3822-D3822 | F3822: =IF(D3822=0,0,E3822/ABS(D3822))
B3823: Martha Lucia Orozco | C3823: 84000 | D3823: 84000 | E3823: =C3823-D3823 | F3823: =IF(D3823=0,0,E3823/ABS(D3823))
B3824: Mercadopago Colombia Ltda | C3824: -2.1388909e+08 | D3824: -2.1388909e+08 | E3824: =C3824-D3824 | F3824: =IF(D3824=0,0,E3824/ABS(D3824))
B3825: NUTRICIÓN HONESTA SAS Diego Mariño | C3825: 40000 | D3825: 40000 | E3825: =C3825-D3825 | F3825: =IF(D3825=0,0,E3825/ABS(D3825))
B3826: Nini giovanna Betancourt Sandoval | C3826: 38000 | D3826: 38000 | E3826: =C3826-D3826 | F3826: =IF(D3826=0,0,E3826/ABS(D3826))
... B6892: Yina Yereinza Acevedo Álvarez | C6892: 4215720 | D6892: 4215720 | E6892: =C6892-D6892 | F6892: =IF(D6892=0,0,E6892/ABS(D6892))
A6893: 11100507 | B6893: Cuenta CTE. Banco de Bogota 4331 | C6893: =SUM(C6894:C6895) | D6893: =SUM(D6894:D6895) | E6893: =C6893-D6893 | F6893: =IF(D6893=0,0,E6893/ABS(D6893))
B6894: Banco de bogotá | C6894: 53797767 | D6894: 53797767 | E6894: =C6894-D6894 | F6894: =IF(D6894=0,0,E6894/ABS(D6894))
B6895: PANGEA NATURAL PRODUCTS S.A.S. | C6895: 86737423 | D6895: 86737423 | E6895: =C6895-D6895 | F6895: =IF(D6895=0,0,E6895/ABS(D6895))
B6896: Total | C6896: =SUM(C8,C211,C218,C271,C3811,C3814,C6893) | D6896: =SUM(D8,D211,D218,D271,D3811,D3814,D6893) | E6896: =C6896-D6896 | F6896: =IF(D6896=0,0,E6896/ABS(D6896))
A6898: NOTA 2 Deudores comerciales y otras cuentas por cobrar
A6899: CTA | B6899: Cuenta / Tercero | C6899: MARZO de 2026 | D6899: PERIODO ANTERIOR TEST | E6899: Variación | F6899: % Variación
A6900: 13050501 | B6900: Clientes nacionales | C6900: =SUM(C6901:C6945) | D6900: =SUM(D6901:D6945) | E6900: =C6900-D6900 | F6900: =IF(D6900=0,0,E6900/ABS(D6900))
B6901: ACM PHARMA S.A.S | C6901: 1020443.9 | D6901: 1020443.9 | E6901: =C6901-D6901 | F6901: =IF(D6901=0,0,E6901/ABS(D6901))
B6902: ADWELLCH SAS | C6902: 18366468 | D6902: 18366468 | E6902: =C6902-D6902 | F6902: =IF(D6902=0,0,E6902/ABS(D6902))
B6903: ALIMENTOS SOSTENIBLES SAS | C6903: 1801231.7 | D6903: 1801231.7 | E6903: =C6903-D6903 | F6903: =IF(D6903=0,0,E6903/ABS(D6903))
B6904: ARTEMISA S.A.S BIC | C6904: 39638302 | D6904: 39638302 | E6904: =C6904-D6904 | F6904: =IF(D6904=0,0,E6904/ABS(D6904))
B6905: CAJA COLOMBIANA DE SUBSIDIO FAMILIAR COLSUBSIDIO | C6905: 159257426 | D6905: 159257426 | E6905: =C6905-D6905 | F6905: =IF(D6905=0,0,E6905/ABS(D6905))
B6906: COPRA GLUTEN FREE S.A.S - green house | C6906: 1218904.5 | D6906: 1218904.5 | E6906: =C6906-D6906 | F6906: =IF(D6906=0,0,E6906/ABS(D6906))
B6907: Clavijo Martinez Inversiones cia s en c | C6907: 3366897 | D6907: 3366897 | E6907: =C6907-D6907 | F6907: =IF(D6907=0,0,E6907/ABS(D6907))
B6908: Consumidor Final | C6908: 0 | D6908: 0 | E6908: =C6908-D6908 | F6908: =IF(D6908=0,0,E6908/ABS(D6908))
B6909: DANIELA ARBELAEZ | C6909: 0 | D6909: 0 | E6909: =C6909-D6909 | F6909: =IF(D6909=0,0,E6909/ABS(D6909))
B6910: DISTRIBUIDORA PASTEUR | C6910: 2.4084697e+08 | D6910: 2.4084697e+08 | E6910: =C6910-D6910 | F6910: =IF(D6910=0,0,E6910/ABS(D6910))
B6911: DISTRIBUIDORA SALUD NATURAL S.A.S | C6911: 4775774 | D6911: 4775774 | E6911: =C6911-D6911 | F6911: =IF(D6911=0,0,E6911/ABS(D6911))
B6912: Droguerías Juliao S.A Mariela Ester Juliao del Río | C6912: 9517436 | D6912: 9517436 | E6912: =C6912-D6912 | F6912: =IF(D6912=0,0,E6912/ABS(D6912))
... B6945: Vida Simple SAS | C6945: 0.16 | D6945: 0.16 | E6945: =C6945-D6945 | F6945: =IF(D6945=0,0,E6945/ABS(D6945))
A6946: 13300501 | B6946: A proveedores | C6946: =SUM(C6947:C6991) | D6946: =SUM(D6947:D6991) | E6946: =C6946-D6946 | F6946: =IF(D6946=0,0,E6946/ABS(D6946))
B6947: ABORIGEN CIENCIA ANCESTRAL S.A.S | C6947: 26070731 | D6947: 26070731 | E6947: =C6947-D6947 | F6947: =IF(D6947=0,0,E6947/ABS(D6947))
B6948: AGUSTIN ARMANDO POVEDA OVIEDO | C6948: 1246000 | D6948: 1246000 | E6948: =C6948-D6948 | F6948: =IF(D6948=0,0,E6948/ABS(D6948))
B6949: ALIMENTOS JOMAS | C6949: 1148684.4 | D6949: 1148684.4 | E6949: =C6949-D6949 | F6949: =IF(D6949=0,0,E6949/ABS(D6949))
B6950: ALMACENES EXITO S.A. | C6950: 18988.99 | D6950: 18988.99 | E6950: =C6950-D6950 | F6950: =IF(D6950=0,0,E6950/ABS(D6950))
B6951: ASOCIACION AGROPIMIENTERA VALLE DEL GUAMEZ | C6951: 1642200 | D6951: 1642200 | E6951: =C6951-D6951 | F6951: =IF(D6951=0,0,E6951/ABS(D6951))
B6952: C.I. NUTREO S.A.S. | C6952: 4998000 | D6952: 4998000 | E6952: =C6952-D6952 | F6952: =IF(D6952=0,0,E6952/ABS(D6952))
B6953: CAMARA DE COMERCIO DE CALI | C6953: 2416600 | D6953: 2416600 | E6953: =C6953-D6953 | F6953: =IF(D6953=0,0,E6953/ABS(D6953))
...

Sheet Graficas
A1: PANGEA NATURAL PRODUCTS S.A.S.
A2: GRÁFICAS DE COMPOSICIÓN FINANCIERA
A5: Concepto | B5: Valor | F5: Concepto | G5: Valor | J5: Concepto | K5: Valor
A6: Efectivo y Equivalentes al Efectivo | B6: =ABS('EF'!D9) | F6: Obligaciones financieras | G6: =ABS('EF'!D7128) | J6: Ingresos | K6: =ABS('ER'!D10)
A7: Deudores comerciales y otras cuentas por cobrar | B7: =ABS('EF'!D6898) | F7: Cuentas comerciales por pagar y otras cuentas por pagar | G7: =ABS('EF'!D7195) | J7: Gastos Admin | K7: =ABS('ER'!D4669)
A8: Inventarios | B8: =ABS('EF'!D7093) | F8: Impuestos corrientes por pagar | G8: =ABS('EF'!D7717) | J8: Gastos Venta | K8: =ABS('ER'!D4747)
A9: Propiedades, Planta y Equipo | B9: =ABS('EF'!D7104) | F9: Obligaciones laborales | G9: =ABS('EF'!D14094) | J9: Costo Ventas | K9: =ABS('ER'!D4069)
A10: Intangibles | B10: =ABS('EF'!D7118) | F10: Otros pasivos | G10: =ABS('EF'!D14157) | J10: Gastos No Op | K10: =ABS('ER'!D4776)
